Workbook
Name grain18: '[1]Daily grain data'!#REF!
Name grains: '[1]Daily grain data'!#REF!
Name week4: '[1]Daily grain data'!#REF!
Name Week50s: [1]summary!#REF!
Name Week51s: [1]summary!#REF!
Name Week52s: [1]summary!#REF!

Sheet Definitions
B1: All price data is provided by John Jordan's Farm Market News Service
B2: John Jordan collects daily price information directly from those that producers would sell their production (elevators and processors)
B3: These corn prices represent the average price in the Chatham Kent area, representing a small geographic portion of Ontario, prices will vary across the province
B6: Price Term | C6: Definition
B7: Ontario Large and medium Frame Fed Steers over 1250 lbs.
B8: Ontario Large and medium Frame Fed Heifers over 1000 lbs.
B9: Average of All Stocker Cattle
B10: CME futures live cattle | C10: Reflects contracts exchanging hands on the commodity exchange at Chicago Board of Trade. Prices are calculated for the closest trading contract period in one years time (reflecting crops that have not been harvested) in American Dollars
B11: CME futures Feeder cattle | C11: Reflects contracts exchanging hands on the commodity exchange at Chicago Board of Trade. Prices are calculated for the closest trading contract period in one years time (reflecting crops that have not been harvested) in American Dollars
B12: Canadian Dollar Value | C12: The value of Canadian dollar in valued in American dollars

Sheet CttlePrices_Basis
A1: Ontario Large and Medium Frame Feeder & Fed Cattle and Basis
A2: *Definitions provided on Next sheet
C3: Ontario Large and medium Frame Fed Steers over 1250 lbs. | D3: Ontario Large and medium Frame Fed Heifers over 1000 lbs. | E3: Weighted Average Stocker Steer and Heifer Cattle Price | F3: CME futures live cattle | G3: CME futures Feeder cattle | H3: Canadian Dollar Value (C$/US$) | I3: Steers 500-599 | J3: Steers 900-999 | K3: Fed Steer Rail Price - Low | L3: Fed Steer Rail Price - High | M3: Fed Steer Rail Price - Average | N3: CANFAX Reported Fed Steer Price | O3: Basis for Steers 500-599 (Ont Live minus CME feeder futures) | P3: Basis for Steers 900-999 (Ont Live minus CME feeder futures) | Q3: Basis for Steers (Ont Ave Rail St minus CME live cattle futures)
A4: Year | B4: Week # | C4: $/cwt (live weight) | D4: $/cwt (live weight) | E4: $/cwt (live weight) | F4: US$/cwt | G4: US$/cwt | I4: $/cwt (live weight) | J4: $/cwt (live weight) | K4: ($/CWT carcsas weight) | L4: ($/CWT carcsas weight) | M4: ($/CWT carcsas weight) | N4: CANFAX $/cwt live weight | O4: $/cwt (live weight) | P4: $/cwt (live weight) | Q4: $/cwt (live weight)
A5: 2005 | B5: 1 | C5: 87.92 | D5: 86.75 | E5: 93.976029 | F5: 87.75 | G5: 98.8 | H5: 0.8166732 | I5: 108.72545 | J5: 87.4 | K5: 145 | L5: 150 | M5: 147.5 | O5: =+(I5-(G5/H5)) -> -12.253169 | P5: =+(J5-(G5/H5)) -> -33.578624 | Q5: =+((M5*0.6)-(F5/H5)) -> -18.94812
A6: 2005 | B6: 2 | C6: 86.57 | D6: 85.68 | E6: 96.301999 | F6: 89.15 | G6: 102.15 | H6: 0.82584567 | I6: 112.28545 | J6: 99.58 | K6: 150 | L6: 155 | M6: 152.5 | O6: =+(I6-(G6/H6)) -> -11.405937 | P6: =+(J6-(G6/H6)) -> -24.111392 | Q6: =+((M6*0.6)-(F6/H6)) -> -16.449952
A7: 2005 | B7: 3 | C7: 88.5 | D7: 84.68 | E7: 99.124477 | F7: 89.15 | G7: 102.15 | H7: 0.81698011 | I7: 118.34545 | J7: 101.64 | K7: 147 | L7: 149 | M7: 148 | O7: =+(I7-(G7/H7)) -> -6.6881885 | P7: =+(J7-(G7/H7)) -> -23.393643 | Q7: =+((M7*0.6)-(F7/H7)) -> -20.321383
A8: 2005 | B8: 4 | C8: 89.12 | D8: 86.16 | E8: 103.31212 | F8: 87.9 | G8: 101.25 | H8: 0.80987398 | I8: 122.00545 | J8: 103.6 | K8: 153 | L8: 156 | M8: 154.5 | O8: =+(I8-(G8/H8)) -> -3.0139955 | P8: =+(J8-(G8/H8)) -> -21.41945 | Q8: =+((M8*0.6)-(F8/H8)) -> -15.835404
A9: 2005 | B9: 5 | C9: 88.06 | D9: 85.77 | E9: 103.76846 | F9: 87.67 | G9: 100.22 | H9: 0.80504927 | I9: 125.07545 | J9: 100.69 | M9: 0 | O9: =+(I9-(G9/H9)) -> 0.58617935 | P9: =+(J9-(G9/H9)) -> -23.799275 | Q9: =+((M9*0.6)-(F9/H9)) -> -108.90017
A10: 2005 | B10: 6 | C10: 88.53 | D10: 87.68 | E10: 105.76948 | F10: 86.82 | G10: 99.35 | H10: 0.8020018 | I10: 125.23545 | J10: 105.63 | K10: 151 | L10: 155 | M10: 153 | O10: =+(I10-(G10/H10)) -> 1.3579265 | P10: =+(J10-(G10/H10)) -> -18.247528 | Q10: =+((M10*0.6)-(F10/H10)) -> -16.454122
A11: 2005 | B11: 7 | C11: 93.93 | D11: 91.7 | E11: 109.57123 | F11: 85.45 | G11: 98.3 | H11: 0.81032024 | I11: 128.78545 | J11: 100.37 | K11: 158 | L11: 160 | M11: 159 | O11: =+(I11-(G11/H11)) -> 7.4753905 | P11: =+(J11-(G11/H11)) -> -20.940064 | Q11: =+((M11*0.6)-(F11/H11)) -> -10.052136
A12: 2005 | B12: 8 | C12: 93.31 | D12: 91.81 | E12: 106.33177 | F12: 85.45 | G12: 97.85 | H12: 0.80848587 | I12: 127.94545 | J12: 103.82 | K12: 160 | L12: 162 | M12: 161 | O12: =+(I12-(G12/H12)) -> 6.9167465 | P12: =+(J12-(G12/H12)) -> -17.208708 | Q12: =+((M12*0.6)-(F12/H12)) -> -9.091396
A13: 2005 | B13: 9 | C13: 92.43 | D13: 91.84 | E13: 104.18292 | F13: 89.02 | G13: 102.67 | H13: 0.80733708 | I13: 123.44545 | J13: 99.34 | K13: 158 | L13: 160 | M13: 159 | O13: =+(I13-(G13/H13)) -> -3.7257143 | P13: =+(J13-(G13/H13)) -> -27.831169 | Q13: =+((M13*0.6)-(F13/H13)) -> -14.863733
A14: 2005 | B14: 10 | C14: 85.37 | D14: 82.76 | E14: 95.956875 | F14: 89.1 | G14: 104.9 | H14: 0.82487833 | I14: 113.03545 | J14: 94.06 | K14: 148 | L14: 149 | M14: 148.5 | O14: =+(I14-(G14/H14)) -> -14.134815 | P14: =+(J14-(G14/H14)) -> -33.11027 | Q14: =+((M14*0.6)-(F14/H14)) -> -18.91593
A15: 2005 | B15: 11 | C15: 79.5 | D15: 77.69 | E15: 92.070144 | F15: 87.4 | G15: 105.62 | H15: 0.8297378 | I15: 112.11545 | J15: 89.06 | K15: 138 | L15: 145 | M15: 141.5 | O15: =+(I15-(G15/H15)) -> -15.177769 | P15: =+(J15-(G15/H15)) -> -38.233224 | Q15: =+((M15*0.6)-(F15/H15)) -> -20.43448
A16: 2005 | B16: 12 | C16: 83.91 | D16: 79.41 | E16: 95.375077 | F16: 88.35 | G16: 104.92 | H16: 0.82601962 | I16: 115.23545 | J16: 94.77 | K16: 138 | L16: 145 | M16: 141.5 | O16: =+(I16-(G16/H16)) -> -11.78332 | P16: =+(J16-(G16/H16)) -> -32.248775 | Q16: =+((M16*0.6)-(F16/H16)) -> -22.058719
A17: 2005 | B17: 13 | C17: 90.1 | D17: 87.31 | E17: 97.614477 | G17: 104.92 | H17: 0.82263903 | I17: 116.94545 | J17: 96.94 | K17: 149 | L17: 153 | M17: 151 | O17: =+(I17-(G17/H17)) -> -10.595297 | P17: =+(J17-(G17/H17)) -> -30.600752 | Q17: =+((M17*0.6)-(F17/H17)) -> 90.6
A18: 2005 | B18: 14 | C18: 88.78 | D18: 86.26 | E18: 100.13414 | F18: 88.27 | G18: 108.42 | H18: 0.81863877 | I18: 123.62545 | J18: 94.83 | K18: 152 | L18: 154 | M18: 153 | O18: =+(I18-(G18/H18)) -> -8.8139123 | P18: =+(J18-(G18/H18)) -> -37.609367 | Q18: =+((M18*0.6)-(F18/H18)) -> -16.025336
A19: 2005 | B19: 15 | C19: 83.61 | D19: 79.92 | E19: 100.34428 | F19: 84.42 | G19: 106.22 | H19: 0.80721977 | I19: 120.15545 | J19: 93.35 | K19: 142 | L19: 150 | M19: 146 | O19: =+(I19-(G19/H19)) -> -11.432006 | P19: =+(J19-(G19/H19)) -> -38.23746 | Q19: =+((M19*0.6)-(F19/H19)) -> -16.981184
A20: 2005 | B20: 16 | C20: 85.22 | D20: 77.77 | E20: 95.200881 | F20: 85.72 | G20: 106.9 | H20: 0.80623055 | I20: 115.07545 | J20: 92.7 | K20: 142 | L20: 144 | M20: 143 | O20: =+(I20-(G20/H20)) -> -17.516891 | P20: =+(J20-(G20/H20)) -> -39.892346 | Q20: =+((M20*0.6)-(F20/H20)) -> -20.521945
A21: 2005 | B21: 17 | C21: 88.53 | D21: 84.12 | E21: 96.933608 | F21: 85.62 | G21: 108.67 | H21: 0.80151326 | I21: 114.53545 | J21: 90.34 | M21: 0 | O21: =+(I21-(G21/H21)) -> -21.045584 | P21: =+(J21-(G21/H21)) -> -45.241039 | Q21: =+((M21*0.6)-(F21/H21)) -> -106.82294
A22: 2005 | B22: 18 | C22: 87.59 | D22: 84.88 | E22: 98.873049 | F22: 85.05 | G22: 109.55 | H22: 0.80014082 | I22: 115.45545 | J22: 92.91 | K22: 149 | L22: 152 | M22: 150.5 | O22: =+(I22-(G22/H22)) -> -21.457944 | P22: =+(J22-(G22/H22)) -> -44.003399 | Q22: =+((M22*0.6)-(F22/H22)) -> -15.993789
A23: 2005 | B23: 19 | C23: 88.2 | D23: 84.8 | E23: 100.36032 | F23: 86.57 | G23: 112.32 | H23: 0.80201466 | I23: 116.58545 | J23: 91.25 | K23: 148 | L23: 151 | M23: 149.5 | O23: =+(I23-(G23/H23)) -> -23.461861 | P23: =+(J23-(G23/H23)) -> -48.797315 | Q23: =+((M23*0.6)-(F23/H23)) -> -18.24067
A24: 2005 | B24: 20 | C24: 85.62 | D24: 84.05 | E24: 99.973779 | F24: 85.62 | G24: 111.55 | H24: 0.79062633 | I24: 116.59545 | J24: 95.77 | M24: 0 | O24: =+(I24-(G24/H24)) -> -24.495216 | P24: =+(J24-(G24/H24)) -> -45.320671 | Q24: =+((M24*0.6)-(F24/H24)) -> -108.29389
A25: 2005 | B25: 21 | C25: 85.21 | D25: 82.03 | E25: 98.435689 | F25: 84.07 | G25: 111.45 | H25: 0.79180325 | I25: 117.95545 | J25: 97.06 | K25: 146 | L25: 148 | M25: 147 | O25: =+(I25-(G25/H25)) -> -22.799208 | P25: =+(J25-(G25/H25)) -> -43.694663 | Q25: =+((M25*0.6)-(F25/H25)) -> -17.975366
A26: 2005 | B26: 22 | C26: 86.9 | D26: 81.09 | E26: 98.155457 | F26: 83.42 | G26: 111.7 | H26: 0.7999872 | I26: 118.00545 | J26: 95.14 | K26: 145 | L26: 147 | M26: 146 | O26: =+(I26-(G26/H26)) -> -21.621779 | P26: =+(J26-(G26/H26)) -> -44.487234 | Q26: =+((M26*0.6)-(F26/H26)) -> -16.676668
A27: 2005 | B27: 23 | C27: 87.34 | D27: 83.72 | E27: 98.472063 | F27: 82.12 | G27: 111.25 | H27: 0.80124353 | I27: 118.52545 | J27: 96.96 | M27: 0 | O27: =+(I27-(G27/H27)) -> -20.32122 | P27: =+(J27-(G27/H27)) -> -41.886675 | Q27: =+((M27*0.6)-(F27/H27)) -> -102.49069
A28: 2005 | B28: 24 | C28: 86.25 | D28: 83.58 | E28: 95.465468 | F28: 79.9 | G28: 107.57 | H28: 0.80278728 | I28: 110.22545 | J28: 94.2 | K28: 147 | L28: 150 | M28: 148.5 | O28: =+(I28-(G28/H28)) -> -23.770192 | P28: =+(J28-(G28/H28)) -> -39.795646 | Q28: =+((M28*0.6)-(F28/H28)) -> -10.428234
A29: 2005 | B29: 25 | C29: 86.97 | D29: 82.7 | E29: 97.777246 | F29: 79.87 | G29: 108.45 | H29: 0.81142486 | I29: 108.04545 | J29: 98.49 | K29: 146 | L29: 148 | M29: 147 | O29: =+(I29-(G29/H29)) -> -25.608325 | P29: =+(J29-(G29/H29)) -> -35.16378 | Q29: =+((M29*0.6)-(F29/H29)) -> -10.231788
A30: 2005 | B30: 26 | C30: 89.19 | D30: 85.62 | E30: 94.72758 | F30: 79.3 | G30: 109.42 | H30: 0.81439857 | I30: 110.63545 | J30: 96.92 | M30: 0 | O30: =+(I30-(G30/H30)) -> -23.721363 | P30: =+(J30-(G30/H30)) -> -37.436818 | Q30: =+((M30*0.6)-(F30/H30)) -> -97.37247
A31: 2005 | B31: 27 | C31: 90.28 | D31: 88.44 | E31: 97.85347 | F31: 79.35 | G31: 111.97 | H31: 0.81050413 | I31: 114.11545 | J31: 99.48 | K31: 149 | L31: 158 | M31: 153.5 | O31: =+(I31-(G31/H31)) -> -24.033131 | P31: =+(J31-(G31/H31)) -> -38.668586 | Q31: =+((M31*0.6)-(F31/H31)) -> -5.80203
A32: 2005 | B32: 28 | C32: 93 | D32: 90.06 | E32: 101.18911 | F32: 78.52 | G32: 106.15 | H32: 0.82622777 | I32: 115.98545 | J32: 100.33 | K32: 157 | L32: 159 | M32: 158 | O32: =+(I32-(G32/H32)) -> -12.490013 | P32: =+(J32-(G32/H32)) -> -28.145468 | Q32: =+((M32*0.6)-(F32/H32)) -> -0.2343264
A33: 2005 | B33: 29 | C33: 95.28 | D33: 92.36 | E33: 103.77208 | F33: 79.25 | G33: 107.65 | H33: 0.82081589 | I33: 123.51545 | J33: 102.3 | K33: 160 | L33: 163 | M33: 161.5 | O33: =+(I33-(G33/H33)) -> -7.6345405 | P33: =+(J33-(G33/H33)) -> -28.849995 | Q33: =+((M33*0.6)-(F33/H33)) -> 0.349725
A34: 2005 | B34: 30 | C34: 91.51 | D34: 87.07 | E34: 104.6531 | F34: 80.57 | G34: 110.4 | H34: 0.81396106 | I34: 120.17545 | J34: 105.51 | K34: 157 | L34: 161 | M34: 159 | O34: =+(I34-(G34/H34)) -> -15.457569 | P34: =+(J34-(G34/H34)) -> -30.123024 | Q34: =+((M34*0.6)-(F34/H34)) -> -3.5850792
A35: 2005 | B35: 31 | C35: 92.35 | D35: 89.95 | E35: 106.28771 | F35: 81.92 | G35: 108.57 | H35: 0.82209799 | I35: 120.42545 | J35: 106.12 | K35: 155 | L35: 162 | M35: 158.5 | O35: =+(I35-(G35/H35)) -> -11.639093 | P35: =+(J35-(G35/H35)) -> -25.944548 | Q35: =+((M35*0.6)-(F35/H35)) -> -4.547488
A36: 2005 | B36: 32 | C36: 94.33 | D36: 90.14 | E36: 108.23654 | F36: 80.07 | G36: 106.62 | H36: 0.82833571 | I36: 125.50545 | J36: 104.06 | K36: 159 | L36: 163 | M36: 161 | O36: =+(I36-(G36/H36)) -> -3.2104743 | P36: =+(J36-(G36/H36)) -> -24.655929 | Q36: =+((M36*0.6)-(F36/H36)) -> -0.0637068
A37: 2005 | B37: 33 | C37: 92.42 | D37: 87.1 | E37: 110.30621 | F37: 82.1 | G37: 108.97 | H37: 0.8285416 | I37: 125.92545 | J37: 106.35 | K37: 158 | L37: 160 | M37: 159 | O37: =+(I37-(G37/H37)) -> -5.5947973 | P37: =+(J37-(G37/H37)) -> -25.170252 | Q37: =+((M37*0.6)-(F37/H37)) -> -3.689774
A38: 2005 | B38: 34 | C38: 90.88 | D38: 84.8 | E38: 109.38054 | F38: 83.05 | G38: 109.87 | H38: 0.83557546 | I38: 123.70545 | J38: 106.5 | K38: 156 | L38: 158 | M38: 157 | O38: =+(I38-(G38/H38)) -> -7.7847641 | P38: =+(J38-(G38/H38)) -> -24.990219 | Q38: =+((M38*0.6)-(F38/H38)) -> -5.192579
A39: 2005 | B39: 35 | C39: 90.96 | D39: 88.18 | E39: 112.55559 | F39: 81.2 | G39: 108.57 | H39: 0.84013845 | I39: 123.43545 | J39: 109.95 | K39: 158 | L39: 160 | M39: 159 | O39: =+(I39-(G39/H39)) -> -5.7932451 | P39: =+(J39-(G39/H39)) -> -19.2787 | Q39: =+((M39*0.6)-(F39/H39)) -> -1.250736
A40: 2005 | B40: 36 | C40: 91.3 | D40: 88.83 | E40: 112.57565 | F40: 87.8 | G40: 113.17 | H40: 0.84534427 | I40: 127.59545 | J40: 108.11 | M40: 0 | O40: =+(I40-(G40/H40)) -> -6.278997 | P40: =+(J40-(G40/H40)) -> -25.764451 | Q40: =+((M40*0.6)-(F40/H40)) -> -103.86301
A41: 2005 | B41: 37 | C41: 92.41 | D41: 88.27 | E41: 114.99756 | F41: 88.27 | G41: 112.35 | H41: 0.84510851 | I41: 130.75545 | J41: 110.86 | K41: 157 | L41: 163 | M41: 160 | O41: =+(I41-(G41/H41)) -> -2.1860535 | P41: =+(J41-(G41/H41)) -> -22.081508 | Q41: =+((M41*0.6)-(F41/H41)) -> -8.4481256
A42: 2005 | B42: 38 | C42: 93.01 | D42: 91.47 | E42: 116.63987 | F42: 88.77 | G42: 113.97 | H42: 0.85511014 | I42: 131.77545 | J42: 119.45 | K42: 161 | L42: 164 | M42: 162.5 | O42: =+(I42-(G42/H42)) -> -1.5056223 | P42: =+(J42-(G42/H42)) -> -13.831077 | Q42: =+((M42*0.6)-(F42/H42)) -> -6.3111888
A43: 2005 | B43: 39 | C43: 90.62 | D43: 86.37 | E43: 118.21159 | F43: 90 | G43: 114.95 | H43: 0.8531113 | I43: 133.24545 | J43: 119.06 | K43: 160 | L43: 162 | M43: 161 | O43: =+(I43-(G43/H43)) -> -1.4966365 | P43: =+(J43-(G43/H43)) -> -15.682091 | Q43: =+((M43*0.6)-(F43/H43)) -> -8.8962
A44: 2005 | B44: 40 | C44: 91.34 | D44: 90.88 | E44: 116.42575 | F44: 91.1 | G44: 116.65 | H44: 0.85113627 | I44: 132.46545 | J44: 117.04 | K44: 157 | L44: 161 | M44: 159 | O44: =+(I44-(G44/H44)) -> -4.5866305 | P44: =+(J44-(G44/H44)) -> -20.012085 | Q44: =+((M44*0.6)-(F44/H44)) -> -11.63339
A45: 2005 | B45: 41 | C45: 91.7 | D45: 86.37 | E45: 117.19578 | F45: 88.27 | G45: 112.35 | H45: 0.8488532 | I45: 136.24545 | J45: 118.33 | K45: 157 | L45: 160 | M45: 158.5 | O45: =+(I45-(G45/H45)) -> 3.8904135 | P45: =+(J45-(G45/H45)) -> -14.025041 | Q45: =+((M45*0.6)-(F45/H45)) -> -8.8873562
A46: 2005 | B46: 42 | C46: 90.4 | D46: 83.03 | E46: 118.69532 | F46: 89.92 | G46: 114.42 | H46: 0.84765877 | I46: 137.83545 | J46: 119.34 | K46: 157 | L46: 160 | M46: 158.5 | O46: =+(I46-(G46/H46)) -> 2.8518921 | P46: =+(J46-(G46/H46)) -> -15.643562 | Q46: =+((M46*0.6)-(F46/H46)) -> -10.980422
A47: 2005 | B47: 43 | C47: 90.86 | D47: 88.88 | E47: 118.39562 | F47: 91.3 | G47: 113.52 | H47: 0.8499354 | I47: 139.48545 | J47: 110.66 | K47: 157 | L47: 160 | M47: 158.5 | O47: =+(I47-(G47/H47)) -> 5.9223633 | P47: =+(J47-(G47/H47)) -> -22.903091 | Q47: =+((M47*0.6)-(F47/H47)) -> -12.319928
A48: 2005 | B48: 44 | C48: 93.08 | D48: 90.01 | E48: 116.50894 | F48: 91.47 | G48: 114.65 | H48: 0.84747199 | I48: 138.43545 | J48: 105.68 | K48: 157 | L48: 160 | M48: 158.5 | O48: =+(I48-(G48/H48)) -> 3.1507475 | P48: =+(J48-(G48/H48)) -> -29.604707 | Q48: =+((M48*0.6)-(F48/H48)) -> -12.832771
A49: 2005 | B49: 45 | C49: 94.18 | D49: 93.26 | E49: 118.26755 | F49: 93.45 | G49: 112.97 | H49: 0.84173667 | I49: 139.57545 | J49: 108.76 | K49: 158 | L49: 163 | M49: 160.5 | O49: =+(I49-(G49/H49)) -> 5.3648351 | P49: =+(J49-(G49/H49)) -> -25.450619 | Q49: =+((M49*0.6)-(F49/H49)) -> -14.720469
A50: 2005 | B50: 46 | C50: 96.12 | D50: 94.08 | E50: 112.94508 | F50: 93.75 | G50: 111.75 | H50: 0.83915145 | I50: 127.20545 | J50: 121.76 | K50: 161 | L50: 165 | M50: 163 | O50: =+(I50-(G50/H50)) -> -5.9647855 | P50: =+(J50-(G50/H50)) -> -11.41024 | Q50: =+((M50*0.6)-(F50/H50)) -> -13.92
A51: 2005 | B51: 47 | C51: 96.47 | D51: 95.25 | E51: 112.54087 | F51: 94.85 | G51: 114.4 | H51: 0.85155665 | I51: 127.65545 | J51: 112.81 | K51: 164 | L51: 167 | M51: 165.5 | O51: =+(I51-(G51/H51)) -> -6.6867535 | P51: =+(J51-(G51/H51)) -> -21.532208 | Q51: =+((M51*0.6)-(F51/H51)) -> -12.084252
A52: 2005 | B52: 48 | C52: 96.85 | D52: 94.26 | E52: 105.47602 | F52: 95.82 | G52: 115 | H52: 0.85736822 | I52: 122.05545 | J52: 110.12 | K52: 166 | L52: 168 | M52: 167 | O52: =+(I52-(G52/H52)) -> -12.075945 | P52: =+(J52-(G52/H52)) -> -24.0114 | Q52: =+((M52*0.6)-(F52/H52)) -> -11.560615
... A55: 2005 | B55: 51 | C55: 104.12 | D55: 101.94 | E55: 111.42865 | F55: 95.72 | G55: 113.42 | H55: 0.85645769 | I55: 131.53545 | J55: 115.16 | K55: 168 | L55: 172 | M55: 170 | O55: =+(I55-(G55/H55)) -> -0.89373745 | P55: =+(J55-(G55/H55)) -> -17.269192 | Q55: =+((M55*0.6)-(F55/H55)) -> -9.762672
A56: 2005 | B56: 52 | C56: 106.14 | D56: 104.66 | E56: 109.86 | H56: 0.85851648 | I56: 126.01545 | J56: 120.97 | M56: 0 | Q56: =+((M56*0.6)-(F56/H56)) -> 0
A57: 2006 | B57: 1 | C57: 102.39 | D57: 100.27 | E57: 113.35438 | F57: 94.55 | G57: 113.97 | H57: 0.8629803 | I57: 127.99545 | J57: 118.35 | K57: 173 | L57: 178 | M57: 175.5 | O57: =+(I57-(G57/H57)) -> -4.0701322 | P57: =+(J57-(G57/H57)) -> -13.715587 | Q57: =+((M57*0.6)-(F57/H57)) -> -4.2621762
A58: 2006 | B58: 2 | C58: 101.11 | D58: 99.85 | E58: 111.47701 | F58: 94.4 | G58: 111.97 | H58: 0.85993396 | I58: 130.24545 | J58: 115.59 | K58: 173 | L58: 177 | M58: 175 | O58: =+(I58-(G58/H58)) -> 0.037780945 | P58: =+(J58-(G58/H58)) -> -14.617674 | Q58: =+((M58*0.6)-(F58/H58)) -> -4.775872
A59: 2006 | B59: 3 | C59: 102.2 | D59: 99.55 | E59: 113.54364 | F59: 94.4 | G59: 111.97 | H59: 0.85910653 | I59: 133.94545 | J59: 111.58 | K59: 172 | L59: 176 | M59: 174 | O59: =+(I59-(G59/H59)) -> 3.6123745 | P59: =+(J59-(G59/H59)) -> -18.75308 | Q59: =+((M59*0.6)-(F59/H59)) -> -5.4816
A60: 2006 | B60: 4 | C60: 101.86 | D60: 101.28 | E60: 115.40555 | F60: 94.12 | G60: 111.47 | H60: 0.86924775 | I60: 135.29545 | J60: 116.61 | K60: 172 | L60: 176 | M60: 174 | O60: =+(I60-(G60/H60)) -> 7.0581371 | P60: =+(J60-(G60/H60)) -> -11.627317 | Q60: =+((M60*0.6)-(F60/H60)) -> -3.8775304
A61: 2006 | B61: 5 | C61: 99.23 | D61: 98.36 | E61: 113.39727 | F61: 89.85 | G61: 107.82 | H61: 0.87432458 | I61: 133.28545 | J61: 109.17 | K61: 168 | L61: 175 | M61: 171.5 | O61: =+(I61-(G61/H61)) -> 9.9674077 | P61: =+(J61-(G61/H61)) -> -14.148047 | Q61: =+((M61*0.6)-(F61/H61)) -> 0.134961
A62: 2006 | B62: 6 | C62: 97.03 | D62: 93.44 | E62: 112.6569 | F62: 90.6 | G62: 110.65 | H62: 0.86988291 | I62: 133.04545 | J62: 111.55 | K62: 163 | L62: 169 | M62: 166 | O62: =+(I62-(G62/H62)) -> 5.8444275 | P62: =+(J62-(G62/H62)) -> -15.651027 | Q62: =+((M62*0.6)-(F62/H62)) -> -4.551948
A63: 2006 | B63: 7 | C63: 94.3 | D63: 92.28 | E63: 110.89264 | F63: 87.7 | G63: 107.32 | H63: 0.86599581 | I63: 133.79545 | J63: 106.92 | K63: 161 | L63: 167 | M63: 164 | O63: =+(I63-(G63/H63)) -> 9.8687577 | P63: =+(J63-(G63/H63)) -> -17.006697 | Q63: =+((M63*0.6)-(F63/H63)) -> -2.870698
A64: 2006 | B64: 8 | C64: 93.62 | D64: 92.62 | E64: 107.05275 | F64: 87 | G64: 106.2 | H64: 0.87000022 | I64: 126.44545 | J64: 105.91 | K64: 161 | L64: 167 | M64: 164 | O64: =+(I64-(G64/H64)) -> 4.3765195 | P64: =+(J64-(G64/H64)) -> -16.158935 | Q64: =+((M64*0.6)-(F64/H64)) -> -1.599975
A65: 2006 | B65: 9 | C65: 96.13 | D65: 93.98 | E65: 109.14615 | F65: 86.02 | G65: 106.32 | H65: 0.87961578 | I65: 133.10545 | J65: 109.57 | K65: 165 | L65: 167 | M65: 166 | O65: =+(I65-(G65/H65)) -> 12.234499 | P65: =+(J65-(G65/H65)) -> -11.300955 | Q65: =+((M65*0.6)-(F65/H65)) -> 1.8073028
A66: 2006 | B66: 10 | C66: 94.5 | D66: 93.3 | E66: 110.72998 | F66: 83.45 | G66: 101.57 | H66: 0.86736287 | I66: 133.92545 | J66: 108.53 | K66: 164 | L66: 167 | M66: 165.5 | O66: =+(I66-(G66/H66)) -> 16.82337 | P66: =+(J66-(G66/H66)) -> -8.5720844 | Q66: =+((M66*0.6)-(F66/H66)) -> 3.088826
A67: 2006 | B67: 11 | C67: 91.81 | D67: 90.01 | E67: 109.39391 | F67: 83.02 | G67: 104.47 | H67: 0.864364 | I67: 132.52545 | J67: 102.87 | K67: 164 | L67: 167 | M67: 165.5 | O67: =+(I67-(G67/H67)) -> 11.662022 | P67: =+(J67-(G67/H67)) -> -17.993432 | Q67: =+((M67*0.6)-(F67/H67)) -> 3.2525016
A68: 2006 | B68: 12 | C68: 93.67 | D68: 91.84 | E68: 111.77237 | F68: 82.47 | G68: 104.97 | H68: 0.85820703 | I68: 135.94545 | J68: 104.47 | K68: 164 | L68: 167 | M68: 165.5 | O68: =+(I68-(G68/H68)) -> 13.632311 | P68: =+(J68-(G68/H68)) -> -17.843143 | Q68: =+((M68*0.6)-(F68/H68)) -> 3.2043066
... A107: 2006 | B107: 51 | C107: 85.78 | D107: 83.58 | E107: 100.29446 | F107: 89.82 | G107: 95.2 | H107: 0.86611582 | I107: 117.20545 | J107: 96.39 | K107: 147 | L107: 151 | M107: 149 | O107: =+(I107-(G107/H107)) -> 7.2894385 | P107: =+(J107-(G107/H107)) -> -13.526016 | Q107: =+((M107*0.6)-(F107/H107)) -> -14.304376
A108: 2006 | B108: 52 | C108: 88.7 | D108: 88.04 | E108: 101.32 | H108: 0.8612894 | I108: 121.75545 | J108: 96.81 | Q108: =+((M108*0.6)-(F108/H108)) -> 0
A109: 2007 | B109: 1 | C109: 89.95 | D109: 89.31 | E109: 99.958131 | F109: 94.12 | G109: 97.65 | H109: 0.85342437 | I109: 110.02 | J109: 94.4 | K109: 152 | L109: 156 | M109: 154 | O109: =+(I109-(G109/H109)) -> -4.4013875 | P109: =+(J109-(G109/H109)) -> -20.021387 | Q109: =+((M109*0.6)-(F109/H109)) -> -17.88511
A110: 2007 | B110: 2 | C110: 90.58 | D110: 90.73 | E110: 105.01605 | F110: 93.87 | G110: 92.95 | H110: 0.85038352 | I110: 118.52 | J110: 105.74 | K110: 154 | L110: 160 | M110: 157 | O110: =+(I110-(G110/H110)) -> 9.216377 | P110: =+(J110-(G110/H110)) -> -3.563623 | Q110: =+((M110*0.6)-(F110/H110)) -> -16.185488
A111: 2007 | B111: 3 | C111: 90.27 | D111: 90.09 | E111: 102.20567 | F111: 93.07 | G111: 93.57 | H111: 0.85271847 | I111: 114.12 | J111: 101.25 | K111: 157 | L111: 161 | M111: 159 | O111: =+(I111-(G111/H111)) -> 4.3885896 | P111: =+(J111-(G111/H111)) -> -8.4814104 | Q111: =+((M111*0.6)-(F111/H111)) -> -13.74505
A112: 2007 | B112: 4 | C112: 89.78 | D112: 88.39 | E112: 96.443444 | F112: 93.07 | G112: 93.57 | H112: 0.847745 | I112: 109.5 | J112: 97.3 | K112: 155 | L112: 160 | M112: 157.5 | O112: =+(I112-(G112/H112)) -> -0.875172 | P112: =+(J112-(G112/H112)) -> -13.075172 | Q112: =+((M112*0.6)-(F112/H112)) -> -15.285372
A113: 2007 | B113: 5 | C113: 90 | D113: 88.25 | E113: 97.020833 | F113: 94.47 | G113: 97.75 | H113: 0.84724223 | I113: 112.27 | J113: 100.61 | K113: 154 | L113: 159 | M113: 156.5 | O113: =+(I113-(G113/H113)) -> -3.104325 | P113: =+(J113-(G113/H113)) -> -14.764325 | Q113: =+((M113*0.6)-(F113/H113)) -> -17.602941
A114: 2007 | B114: 6 | C114: 91.68 | D114: 90.99 | E114: 102.77763 | F114: 94.8 | G114: 98.77 | H114: 0.84628144 | I114: 117.13 | J114: 106.76 | K114: 154 | L114: 159 | M114: 156.5 | O114: =+(I114-(G114/H114)) -> 0.4194172 | P114: =+(J114-(G114/H114)) -> -9.9505828 | Q114: =+((M114*0.6)-(F114/H114)) -> -18.119472
A115: 2007 | B115: 7 | C115: 94.2 | D115: 93.86 | E115: 105.73875 | F115: 96.55 | G115: 100.17 | H115: 0.85625235 | I115: 121.2 | J115: 104.92 | K115: 154 | L115: 162 | M115: 158 | O115: =+(I115-(G115/H115)) -> 4.2134604 | P115: =+(J115-(G115/H115)) -> -12.06654 | Q115: =+((M115*0.6)-(F115/H115)) -> -17.958814
A116: 2007 | B116: 8 | C116: 98.14 | D116: 95.69 | E116: 106.57425 | F116: 96.17 | G116: 101.92 | H116: 0.85984523 | I116: 125.3 | J116: 105.21 | K116: 157 | L116: 167 | M116: 162 | O116: =+(I116-(G116/H116)) -> 6.76704 | P116: =+(J116-(G116/H116)) -> -13.32296 | Q116: =+((M116*0.6)-(F116/H116)) -> -14.64571
A117: 2007 | B117: 9 | C117: 99.55 | D117: 97.71 | E117: 105.05148 | F117: 97.65 | G117: 103.9 | H117: 0.85609109 | I117: 121.18 | J117: 103.74 | K117: 160 | L117: 167 | M117: 163.5 | O117: =+(I117-(G117/H117)) -> -0.18559 | P117: =+(J117-(G117/H117)) -> -17.62559 | Q117: =+((M117*0.6)-(F117/H117)) -> -15.964965
A118: 2007 | B118: 10 | C118: 103.81 | D118: 101.95 | E118: 107.38249 | F118: 101.45 | G118: 105.15 | H118: 0.84932903 | I118: 121.22 | J118: 104.79 | K118: 165 | L118: 175 | M118: 170 | O118: =+(I118-(G118/H118)) -> -2.58361 | P118: =+(J118-(G118/H118)) -> -19.01361 | Q118: =+((M118*0.6)-(F118/H118)) -> -17.44723
A119: 2007 | B119: 11 | C119: 106.9 | D119: 105.69 | E119: 108.73551 | F119: 97.1 | G119: 104.82 | H119: 0.85279119 | I119: 123.24 | J119: 107.99 | K119: 168 | L119: 183 | M119: 175.5 | O119: =+(I119-(G119/H119)) -> 0.3259716 | P119: =+(J119-(G119/H119)) -> -14.924028 | Q119: =+((M119*0.6)-(F119/H119)) -> -8.561402
A120: 2007 | B120: 12 | C120: 104.02 | D120: 101.96 | E120: 108.44716 | F120: 98.1 | G120: 104.35 | H120: 0.85991917 | I120: 123.57 | J120: 106.63 | K120: 179 | L120: 184 | M120: 181.5 | O120: =+(I120-(G120/H120)) -> 2.221385 | P120: =+(J120-(G120/H120)) -> -14.718615 | Q120: =+((M120*0.6)-(F120/H120)) -> -5.18049
... A159: 2007 | B159: 51 | C159: 76.85 | D159: 74.69 | E159: 88.215677 | F159: 95.52 | G159: 106.27 | H159: 0.99679034 | I159: 94.8 | J159: 94.07 | K159: 134 | L159: 137 | M159: 135.5 | O159: =+(I159-(G159/H159)) -> -11.812189 | P159: =+(J159-(G159/H159)) -> -12.542189 | Q159: =+((M159*0.6)-(F159/H159)) -> -14.527574
A160: 2007 | B160: 52 | C160: 74.16 | D160: 73.92 | E160: 87.041805 | H160: 1.0168285 | I160: 98.73 | J160: 87.52 | Q160: =+((M160*0.6)-(F160/H160)) -> 0
A161: 2008 | B161: 1 | C161: 78.08 | D161: 78.14 | E161: 84.621207 | F161: 96.65 | G161: 103.35 | H161: 1.0074552 | I161: 92.96 | J161: 87.85 | K161: 131 | L161: 136 | M161: 133.5 | O161: =+(I161-(G161/H161)) -> -9.62521 | P161: =+(J161-(G161/H161)) -> -14.73521 | Q161: =+((M161*0.6)-(F161/H161)) -> -15.83479
A162: 2008 | B162: 2 | C162: 79.55 | D162: 80.9 | E162: 86.575195 | F162: 95.5 | G162: 102.5 | H162: 0.99088387 | I162: 97.13 | J162: 90.14 | K162: 131 | L162: 138 | M162: 134.5 | O162: =+(I162-(G162/H162)) -> -6.313 | P162: =+(J162-(G162/H162)) -> -13.303 | Q162: =+((M162*0.6)-(F162/H162)) -> -15.6786
A163: 2008 | B163: 3 | C163: 77.95 | D163: 79.54 | E163: 85.257317 | F163: 94.25 | G163: 102.3 | H163: 0.976429 | I163: 96.57 | J163: 85.77 | K163: 131 | L163: 138 | M163: 134.5 | O163: =+(I163-(G163/H163)) -> -8.199522 | P163: =+(J163-(G163/H163)) -> -18.999522 | Q163: =+((M163*0.6)-(F163/H163)) -> -15.825195
A164: 2008 | B164: 4 | C164: 78.74 | D164: 80.57 | E164: 85.757979 | F164: 94.37 | G164: 102.1 | H164: 0.98079601 | I164: 96.41 | J164: 85.79 | K164: 131 | L164: 137 | M164: 134 | O164: =+(I164-(G164/H164)) -> -7.689118 | P164: =+(J164-(G164/H164)) -> -18.309118 | Q164: =+((M164*0.6)-(F164/H164)) -> -15.817765
A165: 2008 | B165: 5 | C165: 78.01 | D165: 79.38 | E165: 88.605765 | F165: 94.05 | G165: 105.45 | H165: 1.0004802 | I165: 101.54 | J165: 87.67 | K165: 131 | L165: 137 | M165: 134 | O165: =+(I165-(G165/H165)) -> -3.859384 | P165: =+(J165-(G165/H165)) -> -17.729384 | Q165: =+((M165*0.6)-(F165/H165)) -> -13.604856
A166: 2008 | B166: 6 | C166: 79.96 | D166: 80.82 | E166: 88.602003 | F166: 95.1 | G166: 109.45 | H166: 0.99788448 | I166: 104.44 | J166: 91.83 | K166: 131 | L166: 137 | M166: 134 | O166: =+(I166-(G166/H166)) -> -5.242034 | P166: =+(J166-(G166/H166)) -> -17.852034 | Q166: =+((M166*0.6)-(F166/H166)) -> -14.901612
A167: 2008 | B167: 7 | C167: 82.85 | D167: 83.98 | E167: 90.599274 | F167: 93.97 | G167: 104.62 | H167: 1.0009008 | I167: 108.02 | J167: 87.92 | K167: 134 | L167: 139 | M167: 136.5 | O167: =+(I167-(G167/H167)) -> 3.494158 | P167: =+(J167-(G167/H167)) -> -16.605842 | Q167: =+((M167*0.6)-(F167/H167)) -> -11.985427
A168: 2008 | B168: 8 | C168: 83.56 | D168: 83.6 | E168: 90.438755 | F168: 93.97 | G168: 103.92 | H168: 0.98539157 | I168: 101.1 | J168: 92.68 | K168: 137 | L168: 142 | M168: 139.5 | O168: =+(I168-(G168/H168)) -> -4.360614 | P168: =+(J168-(G168/H168)) -> -12.780614 | Q168: =+((M168*0.6)-(F168/H168)) -> -11.663105
A169: 2008 | B169: 9 | C169: 83.88 | D169: 83.46 | E169: 91.019774 | F169: 92.65 | G169: 101.67 | H169: 1.0176253 | I169: 105.89 | J169: 92.66 | K169: 140 | L169: 145 | M169: 142.5 | O169: =+(I169-(G169/H169)) -> 5.9809244 | P169: =+(J169-(G169/H169)) -> -7.2490756 | Q169: =+((M169*0.6)-(F169/H169)) -> -5.545302
A170: 2008 | B170: 10 | C170: 84.12 | D170: 84.68 | E170: 92.041306 | F170: 90.5 | G170: 99.3 | H170: 1.0126582 | I170: 104.41 | J170: 92.23 | K170: 140 | L170: 145 | M170: 142.5 | O170: =+(I170-(G170/H170)) -> 6.35125 | P170: =+(J170-(G170/H170)) -> -5.82875 | Q170: =+((M170*0.6)-(F170/H170)) -> -3.86875
A171: 2008 | B171: 11 | C171: 81.72 | D171: 82.45 | E171: 92.066601 | F171: 90.67 | G171: 99.12 | H171: 1.0093262 | I171: 109.87 | J171: 91.07 | K171: 141 | L171: 146 | M171: 143.5 | O171: =+(I171-(G171/H171)) -> 11.665869 | P171: =+(J171-(G171/H171)) -> -7.1341312 | Q171: =+((M171*0.6)-(F171/H171)) -> -3.7322092
A172: 2008 | B172: 12 | C172: 81.15 | D172: 81.67 | E172: 87.678476 | F172: 90.42 | G172: 103.27 | H172: 0.99470321 | I172: 98.96 | J172: 88.32 | K172: 139 | L172: 144 | M172: 141.5 | O172: =+(I172-(G172/H172)) -> -4.8599128 | P172: =+(J172-(G172/H172)) -> -15.499913 | Q172: =+((M172*0.6)-(F172/H172)) -> -6.0014865
... A211: 2008 | B211: 51 | C211: 98.1 | D211: 94.65 | E211: 97.116692 | F211: 86.77 | G211: 93.22 | H211: 0.82116638 | I211: 102.4 | J211: 104.94 | K211: 166 | L211: 172 | M211: 169 | O211: =+(I211-(G211/H211)) -> -11.121452 | P211: =+(J211-(G211/H211)) -> -8.5814516 | Q211: =+((M211*0.6)-(F211/H211)) -> -4.2667706
A212: 2008 | B212: 52 | C212: 93.97 | D212: 89.02 | E212: 97.452231 | H212: 0.82297753 | I212: 103.19 | J212: 98.46 | Q212: =+((M212*0.6)-(F212/H212)) -> 0
A213: 2009 | B213: 1 | C213: 101.94 | D213: 102.23 | E213: 96.289359 | F213: 87.1 | G213: 95.6 | H213: 0.82073168 | I213: 82.72 | J213: 106.51 | K213: 166 | L213: 173 | M213: 169.5 | O213: =+(I213-(G213/H213)) -> -33.76143 | P213: =+(J213-(G213/H213)) -> -9.97143 | Q213: =+((M213*0.6)-(F213/H213)) -> -4.4248175
A214: 2009 | B214: 2 | C214: 103.3 | D214: 99.81 | E214: 99.438493 | F214: 83.1 | G214: 94.1 | H214: 0.84173667 | I214: 103.59 | J214: 105.79 | K214: 168 | L214: 176 | M214: 172 | O214: =+(I214-(G214/H214)) -> -8.202682 | P214: =+(J214-(G214/H214)) -> -6.002682 | Q214: =+((M214*0.6)-(F214/H214)) -> 4.475538
A215: 2009 | B215: 3 | C215: 99.11 | D215: 98.09 | E215: 100.79445 | F215: 82.67 | G215: 93.65 | H215: 0.80796329 | I215: 111.65 | J215: 104.33 | K215: 167 | L215: 176 | M215: 171.5 | O215: =+(I215-(G215/H215)) -> -4.258732 | P215: =+(J215-(G215/H215)) -> -11.578732 | Q215: =+((M215*0.6)-(F215/H215)) -> 0.5809944
A216: 2009 | B216: 4 | C216: 98.33 | D216: 98.61 | E216: 103.66587 | F216: 82 | G216: 91 | H216: 0.79394064 | I216: 115.21 | J216: 105.5 | K216: 167 | L216: 175 | M216: 171 | O216: =+(I216-(G216/H216)) -> 0.59186 | P216: =+(J216-(G216/H216)) -> -9.11814 | Q216: =+((M216*0.6)-(F216/H216)) -> -0.68228
...

Sheet Steer price comp
D1: Comparison of Fed Steer Carcass Weight Price Options
D2: CANFAX Reported Fed Steer Price - farmers report price based on carcass weight and CANFAX converts to liveweight including a transport cost to packer | G2: BFO Reported Average | H2: Comparison | K2: Ontario Auction Large and medium Frame Fed Steers over 1250 lb | L2: CANFAX Reported Fed Steer Price -plus transport cost
C3: - | D3: CANFAX $/cwt live weight | E3: Transport Cost $/cwt carcass weight | F3: CANFAX $/cwt Carcass Weight adjusted for transport cost | G3: BFO $/cwt Average Fed Steer Carcass Weight | H3: Weekly Difference in Carcass Weight Price Options - $/cwt Carcass Weight | I3: Average Difference since Jan 2020 | K3: Ontario Auction $/cwt liveweight | L3: CANFAX - plus transport cost $/cwt liveweight | M3: Weekly Difference between CANFAX Liveweight Fed Steer Price (plus transport cost) and Ontario Auction Fed Steer Price | N3: Average Difference since Jan 2020
A4: 2020 | B4: 1 | C4: =CONCATENATE(A4,$C$3,B4) -> 2020-1 | D4: 148.46 | E4: 2 | F4: =D4/0.6+2 -> 249.43333 | G4: 247 | H4: =F4-G4 -> 2.4333333 | I4: =AVERAGE(H4:H211) -> 1.5052764 | K4: 137.13 | L4: =F4*0.6 -> 149.66 | M4: 12.53 | N4: =AVERAGE(M4:M211) -> 4.7566834
A5: 2020 | B5: 2 | C5: =CONCATENATE(A5,$C$3,B5) -> 2020-2 | D5: 149.1 | E5: 2 | F5: =D5/0.6+2 -> 250.5 | G5: 247.5 | H5: =F5-G5 -> 3 | K5: 139.71 | L5: =F5*0.6 -> 150.3 | M5: =L5-K5 -> 10.59
A6: 2020 | B6: 3 | C6: =CONCATENATE(A6,$C$3,B6) -> 2020-3 | D6: 150.9 | E6: 2 | F6: =D6/0.6+2 -> 253.5 | G6: 252.5 | H6: =F6-G6 -> 1 | K6: 143.12 | L6: =F6*0.6 -> 152.1 | M6: =L6-K6 -> 8.98
A7: 2020 | B7: 4 | C7: =CONCATENATE(A7,$C$3,B7) -> 2020-4 | D7: 151.99 | E7: 2 | F7: =D7/0.6+2 -> 255.31667 | G7: 252.5 | H7: =F7-G7 -> 2.8166667 | K7: 143.82 | L7: =F7*0.6 -> 153.19 | M7: =L7-K7 -> 9.37
A8: 2020 | B8: 5 | C8: =CONCATENATE(A8,$C$3,B8) -> 2020-5 | D8: 152.1 | E8: 2 | F8: =D8/0.6+2 -> 255.5 | G8: 253 | H8: =F8-G8 -> 2.5 | K8: 143.43 | L8: =F8*0.6 -> 153.3 | M8: =L8-K8 -> 9.87
A9: 2020 | B9: 6 | C9: =CONCATENATE(A9,$C$3,B9) -> 2020-6 | D9: 151.95 | E9: 2 | F9: =D9/0.6+2 -> 255.25 | G9: 254.5 | H9: =F9-G9 -> 0.75 | K9: 138.85 | L9: =F9*0.6 -> 153.15 | M9: =L9-K9 -> 14.3
A10: 2020 | B10: 7 | C10: =CONCATENATE(A10,$C$3,B10) -> 2020-7 | D10: 150.86 | E10: 2 | F10: =D10/0.6+2 -> 253.43333 | G10: 253 | H10: =F10-G10 -> 0.43333333 | K10: 138.93 | L10: =F10*0.6 -> 152.06 | M10: =L10-K10 -> 13.13
A11: 2020 | B11: 8 | C11: =CONCATENATE(A11,$C$3,B11) -> 2020-8 | D11: 150.19 | E11: 2 | F11: =D11/0.6+2 -> 252.31667 | G11: 252.5 | H11: =F11-G11 -> -0.18333333 | K11: 139.96 | L11: =F11*0.6 -> 151.39 | M11: =L11-K11 -> 11.43
A12: 2020 | B12: 9 | C12: =CONCATENATE(A12,$C$3,B12) -> 2020-9 | D12: 147.55 | E12: 2 | F12: =D12/0.6+2 -> 247.91667 | G12: 247.5 | H12: =F12-G12 -> 0.41666667 | K12: 143.84 | L12: =F12*0.6 -> 148.75 | M12: =L12-K12 -> 4.91
A13: 2020 | B13: 10 | C13: =CONCATENATE(A13,$C$3,B13) -> 2020-10 | D13: 145.92 | E13: 2 | F13: =D13/0.6+2 -> 245.2 | G13: 245 | H13: =F13-G13 -> 0.2 | K13: 143.58 | L13: =F13*0.6 -> 147.12 | M13: =L13-K13 -> 3.54
A14: 2020 | B14: 11 | C14: =CONCATENATE(A14,$C$3,B14) -> 2020-11 | D14: 145.92 | E14: 2 | F14: =D14/0.6+2 -> 245.2 | G14: 245 | H14: =F14-G14 -> 0.2 | K14: 135.87 | L14: =F14*0.6 -> 147.12 | M14: =L14-K14 -> 11.25
A15: 2020 | B15: 12 | C15: =CONCATENATE(A15,$C$3,B15) -> 2020-12 | D15: 140.1 | E15: 2 | F15: =D15/0.6+2 -> 235.5 | G15: 235 | H15: =F15-G15 -> 0.5 | K15: 135.68 | L15: =F15*0.6 -> 141.3 | M15: =L15-K15 -> 5.62
A16: 2020 | B16: 13 | C16: =CONCATENATE(A16,$C$3,B16) -> 2020-13 | D16: 140.1 | E16: 2 | F16: =D16/0.6+2 -> 235.5 | G16: 235 | H16: =F16-G16 -> 0.5 | K16: 138.46 | L16: =F16*0.6 -> 141.3 | M16: =L16-K16 -> 2.84
... A54: 2020 | B54: 51 | C54: =CONCATENATE(A54,$C$3,B54) -> 2020-51 | D54: 138.3 | E54: 2 | F54: =D54/0.6+2 -> 232.5 | G54: 232 | H54: =F54-G54 -> 0.5 | K54: 115.31 | L54: =F54*0.6 -> 139.5 | M54: =L54-K54 -> 24.19
A55: 2020 | B55: 52 | C55: =CONCATENATE(A55,$C$3,B55) -> 2020-52 | D55: 138.3 | E55: 2 | F55: =D55/0.6+2 -> 232.5 | G55: 232 | H55: =F55-G55 -> 0.5 | K55: =+K54 -> 115.31 | L55: =F55*0.6 -> 139.5 | M55: =+M54 -> 24.19
A56: 2021 | B56: 1 | C56: =CONCATENATE(A56,$C$3,B56) -> 2021-1 | D56: 139.97 | E56: 2 | F56: =D56/0.6+2 -> 235.28333 | G56: 234 | H56: =F56-G56 -> 1.2833333 | K56: 129.23 | L56: =F56*0.6 -> 141.17 | M56: =L56-K56 -> 11.94
A57: 2021 | B57: 2 | C57: =CONCATENATE(A57,$C$3,B57) -> 2021-2 | D57: 140.7 | E57: 2 | F57: =D57/0.6+2 -> 236.5 | G57: 236 | H57: =F57-G57 -> 0.5 | K57: 129.98 | L57: =F57*0.6 -> 141.9 | M57: =L57-K57 -> 11.92
A58: 2021 | B58: 3 | C58: =CONCATENATE(A58,$C$3,B58) -> 2021-3 | D58: 140.92 | E58: 2 | F58: =D58/0.6+2 -> 236.86667 | G58: 236 | H58: =F58-G58 -> 0.86666667 | K58: 133.5 | L58: =F58*0.6 -> 142.12 | M58: =L58-K58 -> 8.62
A59: 2021 | B59: 4 | C59: =CONCATENATE(A59,$C$3,B59) -> 2021-4 | D59: 140.7 | E59: 2 | F59: =D59/0.6+2 -> 236.5 | G59: 236 | H59: =F59-G59 -> 0.5 | K59: 134.16 | L59: =F59*0.6 -> 141.9 | M59: =L59-K59 -> 7.74
A60: 2021 | B60: 5 | C60: =CONCATENATE(A60,$C$3,B60) -> 2021-5 | D60: 140.84 | E60: 2 | F60: =D60/0.6+2 -> 236.73333 | G60: 237 | H60: =F60-G60 -> -0.26666667 | K60: 138.07 | L60: =F60*0.6 -> 142.04 | M60: =L60-K60 -> 3.97
A61: 2021 | B61: 6 | C61: =CONCATENATE(A61,$C$3,B61) -> 2021-6 | D61: 143.1 | E61: 2 | F61: =D61/0.6+2 -> 240.5 | G61: 240 | H61: =F61-G61 -> 0.5 | K61: 135.93 | L61: =F61*0.6 -> 144.3 | M61: =L61-K61 -> 8.37
A62: 2021 | B62: 7 | C62: =CONCATENATE(A62,$C$3,B62) -> 2021-7 | D62: 143.14 | E62: 2 | F62: =D62/0.6+2 -> 240.56667 | G62: 240.5 | H62: =F62-G62 -> 0.066666667 | K62: 131.7 | L62: =F62*0.6 -> 144.34 | M62: =L62-K62 -> 12.64
A63: 2021 | B63: 8 | C63: =CONCATENATE(A63,$C$3,B63) -> 2021-8 | D63: 144.17 | E63: 2 | F63: =D63/0.6+2 -> 242.28333 | G63: 241 | H63: =F63-G63 -> 1.2833333 | K63: 136.79 | L63: =F63*0.6 -> 145.37 | M63: =L63-K63 -> 8.58
A64: 2021 | B64: 9 | C64: =CONCATENATE(A64,$C$3,B64) -> 2021-9 | D64: 144.16 | E64: 2 | F64: =D64/0.6+2 -> 242.26667 | G64: 241 | H64: =F64-G64 -> 1.2666667 | K64: 140.1 | L64: =F64*0.6 -> 145.36 | M64: =L64-K64 -> 5.26
A65: 2021 | B65: 10 | C65: =CONCATENATE(A65,$C$3,B65) -> 2021-10 | D65: 143.49 | E65: 2 | F65: =D65/0.6+2 -> 241.15 | G65: 241.5 | H65: =F65-G65 -> -0.35 | K65: 141.07 | L65: =F65*0.6 -> 144.69 | M65: =L65-K65 -> 3.62
A66: 2021 | B66: 11 | C66: =CONCATENATE(A66,$C$3,B66) -> 2021-11 | D66: 143.46 | E66: 2 | F66: =D66/0.6+2 -> 241.1 | G66: 241.5 | H66: =F66-G66 -> -0.4 | K66: 140.79 | L66: =F66*0.6 -> 144.66 | M66: =L66-K66 -> 3.87
A67: 2021 | B67: 12 | C67: =CONCATENATE(A67,$C$3,B67) -> 2021-12 | D67: 143.1 | E67: 2 | F67: =D67/0.6+2 -> 240.5 | G67: 240 | H67: =F67-G67 -> 0.5 | K67: 140.3 | L67: =F67*0.6 -> 144.3 | M67: =L67-K67 -> 4
... A107: 2021 | B107: 52 | C107: =CONCATENATE(A107,$C$3,B107) -> 2021-52 | D107: 173.05 | E107: 2 | F107: =D107/0.6+2 -> 290.41667 | G107: 276 | H107: =F107-G107 -> 14.416667 | K107: 167.13 | L107: =F107*0.6 -> 174.25 | M107: =L107-K107 -> 7.12
A108: 2022 | B108: 1 | C108: =CONCATENATE(A108,$C$3,B108) -> 2022-1 | D108: =+_xlfn.IFNA('[2]weekly-canfax-data'!AM8,"") -> 173.4 | E108: 2 | F108: =D108/0.6+2 -> 291 | G108: =+CttlePrices_Basis!M889 -> 291.5 | H108: =IFERROR(F108-G108,"") -> -0.5 | K108: =+_xlfn.IFNA(CttlePrices_Basis!C889,"") -> 171.37 | L108: =IFERROR(F108*0.6,"") -> 174.6 | M108: =IFERROR(L108-K108,"") -> 3.23
A109: 2022 | B109: 2 | C109: =CONCATENATE(A109,$C$3,B109) -> 2022-2 | D109: =+_xlfn.IFNA('[2]weekly-canfax-data'!AM9,"") -> 173.04 | E109: 2 | F109: =D109/0.6+2 -> 290.4 | G109: =CttlePrices_Basis!M890 -> 290 | H109: =IFERROR(F109-G109,"") -> 0.4 | K109: =+_xlfn.IFNA(CttlePrices_Basis!C890,"") -> 169.2 | L109: =IFERROR(F109*0.6,"") -> 174.24 | M109: =IFERROR(L109-K109,"") -> 5.04
A110: 2022 | B110: 3 | C110: =CONCATENATE(A110,$C$3,B110) -> 2022-3 | D110: =+_xlfn.IFNA('[2]weekly-canfax-data'!AM10,"") -> 173.1 | E110: 2 | F110: =D110/0.6+2 -> 290.5 | G110: =CttlePrices_Basis!M891 -> 290 | H110: =IFERROR(F110-G110,"") -> 0.5 | K110: =+_xlfn.IFNA(CttlePrices_Basis!C891,"") -> 169.71 | L110: =IFERROR(F110*0.6,"") -> 174.3 | M110: =IFERROR(L110-K110,"") -> 4.59
A111: 2022 | B111: 4 | C111: =CONCATENATE(A111,$C$3,B111) -> 2022-4 | D111: =+_xlfn.IFNA('[2]weekly-canfax-data'!AM11,"") -> 173.1 | E111: 2 | F111: =D111/0.6+2 -> 290.5 | G111: =CttlePrices_Basis!M892 -> 290 | H111: =IFERROR(F111-G111,"") -> 0.5 | K111: =+_xlfn.IFNA(CttlePrices_Basis!C892,"") -> 166.91 | L111: =IFERROR(F111*0.6,"") -> 174.3 | M111: =IFERROR(L111-K111,"") -> 7.39
A112: 2022 | B112: 5 | C112: =CONCATENATE(A112,$C$3,B112) -> 2022-5 | D112: =+_xlfn.IFNA('[2]weekly-canfax-data'!AM12,"") -> 173.1 | E112: 2 | F112: =D112/0.6+2 -> 290.5 | G112: =CttlePrices_Basis!M893 -> 290 | H112: =IFERROR(F112-G112,"") -> 0.5 | K112: =+_xlfn.IFNA(CttlePrices_Basis!C893,"") -> 171.93 | L112: =IFERROR(F112*0.6,"") -> 174.3 | M112: =IFERROR(L112-K112,"") -> 2.37
A113: 2022 | B113: 6 | C113: =CONCATENATE(A113,$C$3,B113) -> 2022-6 | D113: =+_xlfn.IFNA('[2]weekly-canfax-data'!AM13,"") -> 173.1 | E113: 2 | F113: =D113/0.6+2 -> 290.5 | G113: =CttlePrices_Basis!M894 -> 290 | H113: =IFERROR(F113-G113,"") -> 0.5 | K113: =+_xlfn.IFNA(CttlePrices_Basis!C894,"") -> 169.26 | L113: =IFERROR(F113*0.6,"") -> 174.3 | M113: =IFERROR(L113-K113,"") -> 5.04
A114: 2022 | B114: 7 | C114: =CONCATENATE(A114,$C$3,B114) -> 2022-7 | D114: =+_xlfn.IFNA('[2]weekly-canfax-data'!AM14,"") -> 173.1 | E114: 2 | F114: =D114/0.6+2 -> 290.5 | G114: =CttlePrices_Basis!M895 -> 290 | H114: =IFERROR(F114-G114,"") -> 0.5 | K114: =+_xlfn.IFNA(CttlePrices_Basis!C895,"") -> 165.89 | L114: =IFERROR(F114*0.6,"") -> 174.3 | M114: =IFERROR(L114-K114,"") -> 8.41
A115: 2022 | B115: 8 | C115: =CONCATENATE(A115,$C$3,B115) -> 2022-8 | D115: =+_xlfn.IFNA('[2]weekly-canfax-data'!AM15,"") -> 173.1 | E115: 2 | F115: =D115/0.6+2 -> 290.5 | G115: =CttlePrices_Basis!M896 -> 290 | H115: =IFERROR(F115-G115,"") -> 0.5 | K115: =+_xlfn.IFNA(CttlePrices_Basis!C896,"") -> 165.31 | L115: =IFERROR(F115*0.6,"") -> 174.3 | M115: =IFERROR(L115-K115,"") -> 8.99
A116: 2022 | B116: 9 | C116: =CONCATENATE(A116,$C$3,B116) -> 2022-9 | D116: =+_xlfn.IFNA('[2]weekly-canfax-data'!AM16,"") -> 173.1 | E116: 2 | F116: =D116/0.6+2 -> 290.5 | G116: =CttlePrices_Basis!M897 -> 290 | H116: =IFERROR(F116-G116,"") -> 0.5 | K116: =+_xlfn.IFNA(CttlePrices_Basis!C897,"") -> 169.08 | L116: =IFERROR(F116*0.6,"") -> 174.3 | M116: =IFERROR(L116-K116,"") -> 5.22
A117: 2022 | B117: 10 | C117: =CONCATENATE(A117,$C$3,B117) -> 2022-10 | D117: =+_xlfn.IFNA('[2]weekly-canfax-data'!AM17,"") -> 173.18 | E117: 2 | F117: =D117/0.6+2 -> 290.63333 | G117: =CttlePrices_Basis!M898 -> 290 | H117: =IFERROR(F117-G117,"") -> 0.63333333 | K117: =+_xlfn.IFNA(CttlePrices_Basis!C898,"") -> 168.13 | L117: =IFERROR(F117*0.6,"") -> 174.38 | M117: =IFERROR(L117-K117,"") -> 6.25
A118: 2022 | B118: 11 | C118: =CONCATENATE(A118,$C$3,B118) -> 2022-11 | D118: =+_xlfn.IFNA('[2]weekly-canfax-data'!AM18,"") -> 173.78 | E118: 2 | F118: =D118/0.6+2 -> 291.63333 | G118: =CttlePrices_Basis!M899 -> 290 | H118: =IFERROR(F118-G118,"") -> 1.6333333 | K118: =+_xlfn.IFNA(CttlePrices_Basis!C899,"") -> 170.55 | L118: =IFERROR(F118*0.6,"") -> 174.98 | M118: =IFERROR(L118-K118,"") -> 4.43
A119: 2022 | B119: 12 | C119: =CONCATENATE(A119,$C$3,B119) -> 2022-12 | D119: =+_xlfn.IFNA('[2]weekly-canfax-data'!AM19,"") -> 173.31 | E119: 2 | F119: =D119/0.6+2 -> 290.85 | G119: =CttlePrices_Basis!M900 -> 290 | H119: =IFERROR(F119-G119,"") -> 0.85 | K119: =+_xlfn.IFNA(CttlePrices_Basis!C900,"") -> 172.08 | L119: =IFERROR(F119*0.6,"") -> 174.51 | M119: =IFERROR(L119-K119,"") -> 2.43
A120: 2022 | B120: 13 | C120: =CONCATENATE(A120,$C$3,B120) -> 2022-13 | D120: =+_xlfn.IFNA('[2]weekly-canfax-data'!AM20,"") -> 173.1 | E120: 2 | F120: =D120/0.6+2 -> 290.5 | G120: =CttlePrices_Basis!M901 -> 290 | H120: =IFERROR(F120-G120,"") -> 0.5 | K120: =+_xlfn.IFNA(CttlePrices_Basis!C901,"") -> 169.08 | L120: =IFERROR(F120*0.6,"") -> 174.3 | M120: =IFERROR(L120-K120,"") -> 5.22
... A137: 2022 | B137: 30 | C137: =CONCATENATE(A137,$C$3,B137) -> 2022-30 | D137: =+_xlfn.IFNA('[2]weekly-canfax-data'!AM37,"") -> 183.36 | E137: 2 | F137: =D137/0.6+2 -> 307.6 | G137: =CttlePrices_Basis!M918 -> 306 | H137: =IFERROR(F137-G137,"") -> 1.6 | K137: =+_xlfn.IFNA(CttlePrices_Basis!C918,"") -> 178.71 | L137: =IFERROR(F137*0.6,"") -> 184.56 | M137: =IFERROR(L137-K137,"") -> 5.85
A138: 2022 | B138: 31 | C138: =CONCATENATE(A138,$C$3,B138) -> 2022-31 | D138: =+_xlfn.IFNA('[2]weekly-canfax-data'!AM38,"") -> 182.7 | E138: 2 | F138: =IF(D138>0,D138/0.6+2,"") -> 306.5 | G138: =CttlePrices_Basis!M919 -> 306 | H138: =IFERROR(F138-G138,"") -> 0.5 | K138: =+_xlfn.IFNA(CttlePrices_Basis!C919,"") -> 178.38 | L138: =+F138*0.6 -> 183.9 | M138: =IFERROR(L138-K138,"") -> 5.52
A139: 2022 | B139: 32 | C139: =CONCATENATE(A139,$C$3,B139) -> 2022-32 | D139: =+D138 -> 182.7 | E139: 2 | F139: =IF(D139>0,D139/0.6+2,"") -> 306.5 | G139: =_xlfn.IFNA(CttlePrices_Basis!M920,"") -> 306 | H139: =IFERROR(F139-G139,"") -> 0.5 | K139: =+_xlfn.IFNA(CttlePrices_Basis!C920,"") -> 181.5 | L139: =+L138 -> 183.9 | M139: =IFERROR(L139-K139,"") -> 2.4
A140: 2022 | B140: 33 | C140: =CONCATENATE(A140,$C$3,B140) -> 2022-33 | D140: =+D139 -> 182.7 | E140: 2 | F140: =IF(D140>0,D140/0.6+2,"") -> 306.5 | G140: =+G139 -> 306 | H140: =IFERROR(F140-G140,"") -> 0.5 | K140: =+_xlfn.IFNA(CttlePrices_Basis!C921,"") -> 182.94 | L140: =+L139 -> 183.9 | M140: =IFERROR(L140-K140,"") -> 0.96
A141: 2022 | B141: 34 | C141: =CONCATENATE(A141,$C$3,B141) -> 2022-34 | D141: =+_xlfn.IFNA('[2]weekly-canfax-data'!AM41,"") -> 182.7 | E141: 2 | F141: =IF(D141>0,D141/0.6+2,"") -> 306.5 | G141: =_xlfn.IFNA(CttlePrices_Basis!M922,"") -> 306 | H141: =IFERROR(F141-G141,"") -> 0.5 | K141: =+_xlfn.IFNA(CttlePrices_Basis!C922,"") -> 179.91 | L141: =IFERROR(F141*0.6,"") -> 183.9 | M141: =IFERROR(L141-K141,"") -> 3.99
A142: 2022 | B142: 35 | C142: =CONCATENATE(A142,$C$3,B142) -> 2022-35 | D142: =+_xlfn.IFNA('[2]weekly-canfax-data'!AM42,"") -> 182.7 | E142: 2 | F142: =IF(D142>0,D142/0.6+2,"") -> 306.5 | G142: =_xlfn.IFNA(CttlePrices_Basis!M923,"") -> 306 | H142: =IFERROR(F142-G142,"") -> 0.5 | K142: =+_xlfn.IFNA(CttlePrices_Basis!C923,"") -> 180.64 | L142: =IFERROR(F142*0.6,"") -> 183.9 | M142: =IFERROR(L142-K142,"") -> 3.26
A143: 2022 | B143: 36 | C143: =CONCATENATE(A143,$C$3,B143) -> 2022-36 | D143: =+_xlfn.IFNA('[2]weekly-canfax-data'!AM43,"") -> 182.7 | E143: 2 | F143: =IF(D143>0,D143/0.6+2,"") -> 306.5 | G143: =_xlfn.IFNA(CttlePrices_Basis!M924,"") -> 306 | H143: =IFERROR(F143-G143,"") -> 0.5 | K143: =+_xlfn.IFNA(CttlePrices_Basis!C924,"") -> 181.05 | L143: =IFERROR(F143*0.6,"") -> 183.9 | M143: =IFERROR(L143-K143,"") -> 2.85
A144: 2022 | B144: 37 | C144: =CONCATENATE(A144,$C$3,B144) -> 2022-37 | D144: =+_xlfn.IFNA('[2]weekly-canfax-data'!AM44,"") -> 182.02 | E144: 2 | F144: =IF(D144>0,D144/0.6+2,"") -> 305.36667 | G144: =_xlfn.IFNA(CttlePrices_Basis!M925,"") -> 304.5 | H144: =IFERROR(F144-G144,"") -> 0.86666667 | K144: =+_xlfn.IFNA(CttlePrices_Basis!C925,"") -> 181.31 | L144: =IFERROR(F144*0.6,"") -> 183.22 | M144: =IFERROR(L144-K144,"") -> 1.91
A145: 2022 | B145: 38 | C145: =CONCATENATE(A145,$C$3,B145) -> 2022-38 | D145: =+_xlfn.IFNA('[2]weekly-canfax-data'!AM45,"") -> 181.38 | E145: 2 | F145: =IF(D145>0,D145/0.6+2,"") -> 304.3 | G145: =_xlfn.IFNA(CttlePrices_Basis!M926,"") -> 303 | H145: =IFERROR(F145-G145,"") -> 1.3 | K145: =+_xlfn.IFNA(CttlePrices_Basis!C926,"") -> 183.44 | L145: =IFERROR(F145*0.6,"") -> 182.58 | M145: =IFERROR(L145-K145,"") -> -0.86
A146: 2022 | B146: 39 | C146: =CONCATENATE(A146,$C$3,B146) -> 2022-39 | D146: =+_xlfn.IFNA('[2]weekly-canfax-data'!AM46,"") -> 180.9 | E146: 2 | F146: =IF(D146>0,D146/0.6+2,"") -> 303.5 | G146: =_xlfn.IFNA(CttlePrices_Basis!M927,"") -> 303 | H146: =IFERROR(F146-G146,"") -> 0.5 | K146: =+_xlfn.IFNA(CttlePrices_Basis!C927,"") -> 179.59 | L146: =IFERROR(F146*0.6,"") -> 182.1 | M146: =IFERROR(L146-K146,"") -> 2.51
A147: 2022 | B147: 40 | C147: =CONCATENATE(A147,$C$3,B147) -> 2022-40 | D147: =+_xlfn.IFNA('[2]weekly-canfax-data'!AM47,"") -> 180.9 | E147: 2 | F147: =IF(D147>0,D147/0.6+2,"") -> 303.5 | G147: =_xlfn.IFNA(CttlePrices_Basis!M928,"") -> 303 | H147: =IFERROR(F147-G147,"") -> 0.5 | K147: =+_xlfn.IFNA(CttlePrices_Basis!C928,"") -> 181.17 | L147: =IFERROR(F147*0.6,"") -> 182.1 | M147: =IFERROR(L147-K147,"") -> 0.93
A148: 2022 | B148: 41 | C148: =CONCATENATE(A148,$C$3,B148) -> 2022-41 | D148: =+D147 -> 180.9 | E148: 2 | F148: =IF(D148>0,D148/0.6+2,"") -> 303.5 | G148: =_xlfn.IFNA(CttlePrices_Basis!M929,"") -> 303 | H148: =IFERROR(F148-G148,"") -> 0.5 | K148: =+_xlfn.IFNA(CttlePrices_Basis!C929,"") -> 182.17 | L148: =+L147 -> 182.1 | M148: =IFERROR(L148-K148,"") -> -0.07
A149: 2022 | B149: 42 | C149: =CONCATENATE(A149,$C$3,B149) -> 2022-42 | D149: =+_xlfn.IFNA('[2]weekly-canfax-data'!AM49,"") -> 181.04 | E149: 2 | F149: =IF(D149>0,D149/0.6+2,"") -> 303.73333 | G149: =_xlfn.IFNA(CttlePrices_Basis!M930,"") -> 303 | H149: =IFERROR(F149-G149,"") -> 0.73333333 | K149: =+_xlfn.IFNA(CttlePrices_Basis!C930,"") -> 177.66 | L149: =IFERROR(F149*0.6,"") -> 182.24 | M149: =IFERROR(L149-K149,"") -> 4.58
A150: 2022 | B150: 43 | C150: =CONCATENATE(A150,$C$3,B150) -> 2022-43 | D150: =+_xlfn.IFNA('[2]weekly-canfax-data'!AM50,"") -> 182.5 | E150: 2 | F150: =IF(D150>0,D150/0.6+2,"") -> 306.16667 | G150: =_xlfn.IFNA(CttlePrices_Basis!M931,"") -> 303 | H150: =IFERROR(F150-G150,"") -> 3.1666667 | K150: =+_xlfn.IFNA(CttlePrices_Basis!C931,"") -> 178.94 | L150: =IFERROR(F150*0.6,"") -> 183.7 | M150: =IFERROR(L150-K150,"") -> 4.76
A151: 2022 | B151: 44 | C151: =CONCATENATE(A151,$C$3,B151) -> 2022-44 | D151: =+_xlfn.IFNA('[2]weekly-canfax-data'!AM51,"") -> 182.39 | E151: 2 | F151: =IF(D151>0,D151/0.6+2,"") -> 305.98333 | G151: =_xlfn.IFNA(CttlePrices_Basis!M932,"") -> 304.5 | H151: =IFERROR(F151-G151,"") -> 1.4833333 | K151: =+_xlfn.IFNA(CttlePrices_Basis!C932,"") -> 181.73 | L151: =IFERROR(F151*0.6,"") -> 183.59 | M151: =IFERROR(L151-K151,"") -> 1.86
A152: 2022 | B152: 45 | C152: =CONCATENATE(A152,$C$3,B152) -> 2022-45 | D152: 182.39 | E152: 2 | F152: =IF(D152>0,D152/0.6+2,"") -> 305.98333 | G152: =_xlfn.IFNA(CttlePrices_Basis!M933,"") -> 306 | H152: =IFERROR(F152-G152,"") -> -0.016666667 | K152: =+_xlfn.IFNA(CttlePrices_Basis!C933,"") -> 184.35 | L152: =IFERROR(F152*0.6,"") -> 183.59 | M152: =IFERROR(L152-K152,"") -> -0.76
A153: 2022 | B153: 46 | C153: =CONCATENATE(A153,$C$3,B153) -> 2022-46 | D153: =+_xlfn.IFNA('[2]weekly-canfax-data'!AM53,"") -> 184.94 | E153: 2 | F153: =IF(D153>0,D153/0.6+2,"") -> 310.23333 | G153: =_xlfn.IFNA(CttlePrices_Basis!M934,"") -> 308 | H153: =IFERROR(F153-G153,"") -> 2.2333333 | K153: =+_xlfn.IFNA(CttlePrices_Basis!C934,"") -> 184.62 | L153: =IFERROR(F153*0.6,"") -> 186.14 | M153: =IFERROR(L153-K153,"") -> 1.52
A154: 2022 | B154: 47 | C154: =CONCATENATE(A154,$C$3,B154) -> 2022-47 | D154: =+_xlfn.IFNA('[2]weekly-canfax-data'!AM54,"") -> 188.1 | E154: 2 | F154: =IF(D154>0,D154/0.6+2,"") -> 315.5 | G154: =_xlfn.IFNA(CttlePrices_Basis!M935,"") -> 312.5 | H154: =IFERROR(F154-G154,"") -> 3 | K154: =+_xlfn.IFNA(CttlePrices_Basis!C935,"") -> 185.04 | L154: =IFERROR(F154*0.6,"") -> 189.3 | M154: =IFERROR(L154-K154,"") -> 4.26
A155: 2022 | B155: 48 | C155: =CONCATENATE(A155,$C$3,B155) -> 2022-48 | D155: =+_xlfn.IFNA('[2]weekly-canfax-data'!AM55,"") -> 190.84 | E155: 2 | F155: =IF(D155>0,D155/0.6+2,"") -> 320.06667 | G155: =_xlfn.IFNA(CttlePrices_Basis!M936,"") -> 320 | H155: =IFERROR(F155-G155,"") -> 0.066666667 | K155: =+_xlfn.IFNA(CttlePrices_Basis!C936,"") -> 189.86 | L155: =IFERROR(F155*0.6,"") -> 192.04 | M155: =IFERROR(L155-K155,"") -> 2.18
A156: 2022 | B156: 49 | C156: =CONCATENATE(A156,$C$3,B156) -> 2022-49 | D156: =+_xlfn.IFNA('[2]weekly-canfax-data'!AM56,"") -> 191.1 | E156: 2 | F156: =IF(D156>0,D156/0.6+2,"") -> 320.5 | G156: =_xlfn.IFNA(CttlePrices_Basis!M937,"") -> 320 | H156: =IFERROR(F156-G156,"") -> 0.5 | K156: =+_xlfn.IFNA(CttlePrices_Basis!C937,"") -> 187.58 | L156: =IFERROR(F156*0.6,"") -> 192.3 | M156: =IFERROR(L156-K156,"") -> 4.72
A157: 2022 | B157: 50 | C157: =CONCATENATE(A157,$C$3,B157) -> 2022-50 | D157: =+_xlfn.IFNA('[2]weekly-canfax-data'!AM57,"") -> 190.98 | E157: 2 | F157: =IF(D157>0,D157/0.6+2,"") -> 320.3 | G157: =_xlfn.IFNA(CttlePrices_Basis!M938,"") -> 320 | H157: =IFERROR(F157-G157,"") -> 0.3 | K157: =+_xlfn.IFNA(CttlePrices_Basis!C938,"") -> 188.6 | L157: =IFERROR(F157*0.6,"") -> 192.18 | M157: =IFERROR(L157-K157,"") -> 3.58
A158: 2022 | B158: 51 | C158: =CONCATENATE(A158,$C$3,B158) -> 2022-51 | D158: =+_xlfn.IFNA('[2]weekly-canfax-data'!AM58,"") -> 191.1 | E158: 2 | F158: =IF(D158>0,D158/0.6+2,"") -> 320.5 | G158: =_xlfn.IFNA(CttlePrices_Basis!M939,"") -> 320 | H158: =IFERROR(F158-G158,"") -> 0.5 | K158: =+_xlfn.IFNA(CttlePrices_Basis!C939,"") -> 190.11 | L158: =IFERROR(F158*0.6,"") -> 192.3 | M158: =IFERROR(L158-K158,"") -> 2.19
A159: 2022 | B159: 52 | C159: =CONCATENATE(A159,$C$3,B159) -> 2022-52 | D159: =+_xlfn.IFNA('[2]weekly-canfax-data'!AM59,"") -> 0 | E159: 2 | F159: =IF(D159>0,D159/0.6+2,"") | G159: =_xlfn.IFNA(CttlePrices_Basis!M940,"") -> 320 | H159: =IFERROR(F159-G159,"") | K159: =+_xlfn.IFNA(CttlePrices_Basis!C940,"") -> 198.98 | L159: =IFERROR(F159*0.6,"") | M159: =IFERROR(L159-K159,"")
A160: 2023 | B160: 1 | C160: =CONCATENATE(A160,$C$3,B160) -> 2023-1 | D160: =+_xlfn.IFNA('[3]weekly-canfax-data'!AN8,"") -> 192.96 | E160: 2 | F160: =IF(D160>0,D160/0.6+2,"") -> 323.6 | G160: =+CttlePrices_Basis!M941 -> 323 | H160: =IFERROR(F160-G160,"") -> 0.6 | K160: =+_xlfn.IFNA(CttlePrices_Basis!C941,"") -> 192.38 | L160: =IFERROR(F160*0.6,"") -> 194.16 | M160: =IFERROR(L160-K160,"") -> 1.78
A161: 2023 | B161: 2 | C161: =CONCATENATE(A161,$C$3,B161) -> 2023-2 | D161: =+_xlfn.IFNA('[3]weekly-canfax-data'!AN9,"") -> 194.78 | E161: 2 | F161: =IF(D161>0,D161/0.6+2,"") -> 326.63333 | G161: =CttlePrices_Basis!M942 -> 326 | H161: =IFERROR(F161-G161,"") -> 0.63333333 | K161: =+_xlfn.IFNA(CttlePrices_Basis!C942,"") -> 189.22 | L161: =IFERROR(F161*0.6,"") -> 195.98 | M161: =IFERROR(L161-K161,"") -> 6.76
A162: 2023 | B162: 3 | C162: =CONCATENATE(A162,$C$3,B162) -> 2023-3 | D162: =+_xlfn.IFNA('[3]weekly-canfax-data'!AN10,"") -> 195.9 | E162: 2 | F162: =IF(D162>0,D162/0.6+2,"") -> 328.5 | G162: =CttlePrices_Basis!M943 -> 327 | H162: =IFERROR(F162-G162,"") -> 1.5 | K162: =+_xlfn.IFNA(CttlePrices_Basis!C943,"") -> 191.06 | L162: =IFERROR(F162*0.6,"") -> 197.1 | M162: =IFERROR(L162-K162,"") -> 6.04
A163: 2023 | B163: 4 | C163: =CONCATENATE(A163,$C$3,B163) -> 2023-4 | D163: =+_xlfn.IFNA('[3]weekly-canfax-data'!AN11,"") -> 0 | E163: 2 | F163: =IF(D163>0,D163/0.6+2,"") | G163: =CttlePrices_Basis!M944 -> 328 | H163: =IFERROR(F163-G163,"") | K163: =+_xlfn.IFNA(CttlePrices_Basis!C944,"") -> 191.92 | L163: =IFERROR(F163*0.6,"") | M163: =IFERROR(L163-K163,"")
A164: 2023 | B164: 5 | C164: =CONCATENATE(A164,$C$3,B164) -> 2023-5 | D164: =+_xlfn.IFNA('[3]weekly-canfax-data'!AN12,"") -> 195.9 | E164: 2 | F164: =IF(D164>0,D164/0.6+2,"") -> 328.5 | G164: =CttlePrices_Basis!M945 -> 328 | H164: =IFERROR(F164-G164,"") -> 0.5 | K164: =+_xlfn.IFNA(CttlePrices_Basis!C945,"") -> 192.45 | L164: =IFERROR(F164*0.6,"") -> 197.1 | M164: =IFERROR(L164-K164,"") -> 4.65
A165: 2023 | B165: 6 | C165: =CONCATENATE(A165,$C$3,B165) -> 2023-6 | D165: =+_xlfn.IFNA('[3]weekly-canfax-data'!AN13,"") -> 196.74 | E165: 2 | F165: =IF(D165>0,D165/0.6+2,"") -> 329.9 | G165: =CttlePrices_Basis!M946 -> 329 | H165: =IFERROR(F165-G165,"") -> 0.9 | K165: =+_xlfn.IFNA(CttlePrices_Basis!C946,"") -> 197.92 | L165: =IFERROR(F165*0.6,"") -> 197.94 | M165: =IFERROR(L165-K165,"") -> 0.02
A166: 2023 | B166: 7 | C166: =CONCATENATE(A166,$C$3,B166) -> 2023-7 | D166: =+_xlfn.IFNA('[3]weekly-canfax-data'!AN14,"") -> 198.3 | E166: 2 | F166: =IF(D166>0,D166/0.6+2,"") -> 332.5 | G166: =CttlePrices_Basis!M947 -> 332 | H166: =IFERROR(F166-G166,"") -> 0.5 | K166: =+_xlfn.IFNA(CttlePrices_Basis!C947,"") -> 196.71 | L166: =IFERROR(F166*0.6,"") -> 199.5 | M166: =IFERROR(L166-K166,"") -> 2.79
A167: 2023 | B167: 8 | C167: =CONCATENATE(A167,$C$3,B167) -> 2023-8 | D167: =+_xlfn.IFNA('[3]weekly-canfax-data'!AN15,"") -> 201.86 | E167: 2 | F167: =IF(D167>0,D167/0.6+2,"") -> 338.43333 | G167: =CttlePrices_Basis!M948 -> 338 | H167: =IFERROR(F167-G167,"") -> 0.43333333 | K167: =+_xlfn.IFNA(CttlePrices_Basis!C948,"") -> 196.23 | L167: =IFERROR(F167*0.6,"") -> 203.06 | M167: =IFERROR(L167-K167,"") -> 6.83
A168: 2023 | B168: 9 | C168: =CONCATENATE(A168,$C$3,B168) -> 2023-9 | D168: =+_xlfn.IFNA('[3]weekly-canfax-data'!AN16,"") -> 204.3 | E168: 2 | F168: =IF(D168>0,D168/0.6+2,"") -> 342.5 | G168: =CttlePrices_Basis!M949 -> 342 | H168: =IFERROR(F168-G168,"") -> 0.5 | K168: =+_xlfn.IFNA(CttlePrices_Basis!C949,"") -> 205.02 | L168: =IFERROR(F168*0.6,"") -> 205.5 | M168: =IFERROR(L168-K168,"") -> 0.48
A169: 2023 | B169: 10 | C169: =CONCATENATE(A169,$C$3,B169) -> 2023-10 | D169: =+_xlfn.IFNA('[3]weekly-canfax-data'!AN17,"") -> 210.13 | E169: 2 | F169: =IF(D169>0,D169/0.6+2,"") -> 352.21667 | G169: =CttlePrices_Basis!M950 -> 351 | H169: =IFERROR(F169-G169,"") -> 1.2166667 | K169: =+_xlfn.IFNA(CttlePrices_Basis!C950,"") -> 206.22 | L169: =IFERROR(F169*0.6,"") -> 211.33 | M169: =IFERROR(L169-K169,"") -> 5.11
A170: 2023 | B170: 11 | C170: =CONCATENATE(A170,$C$3,B170) -> 2023-11 | D170: =+_xlfn.IFNA('[3]weekly-canfax-data'!AN18,"") -> 211.59 | E170: 2 | F170: =IF(D170>0,D170/0.6+2,"") -> 354.65 | G170: =CttlePrices_Basis!M951 -> 354 | H170: =IFERROR(F170-G170,"") -> 0.65 | K170: =+_xlfn.IFNA(CttlePrices_Basis!C951,"") -> 207.62 | L170: =IFERROR(F170*0.6,"") -> 212.79 | M170: =IFERROR(L170-K170,"") -> 5.17
A171: 2023 | B171: 12 | C171: =CONCATENATE(A171,$C$3,B171) -> 2023-12 | D171: =+_xlfn.IFNA('[3]weekly-canfax-data'!AN19,"") -> 215.1 | E171: 2 | F171: =IF(D171>0,D171/0.6+2,"") -> 360.5 | G171: =CttlePrices_Basis!M952 -> 357.5 | H171: =IFERROR(F171-G171,"") -> 3 | K171: =+_xlfn.IFNA(CttlePrices_Basis!C952,"") -> 209.54 | L171: =IFERROR(F171*0.6,"") -> 216.3 | M171: =IFERROR(L171-K171,"") -> 6.76
A172: 2023 | B172: 13 | C172: =CONCATENATE(A172,$C$3,B172) -> 2023-13 | D172: =+_xlfn.IFNA('[3]weekly-canfax-data'!AN20,"") -> 215.1 | E172: 2 | F172: =IF(D172>0,D172/0.6+2,"") -> 360.5 | G172: =CttlePrices_Basis!M953 -> 360 | H172: =IFERROR(F172-G172,"") -> 0.5 | K172: =+_xlfn.IFNA(CttlePrices_Basis!C953,"") -> 208.66 | L172: =IFERROR(F172*0.6,"") -> 216.3 | M172: =IFERROR(L172-K172,"") -> 7.64
... A190: 2023 | B190: 31 | C190: =CONCATENATE(A190,$C$3,B190) -> 2023-31 | D190: =+_xlfn.IFNA('[3]weekly-canfax-data'!AN38,"") -> 232.5 | E190: 2 | F190: =IF(D190>0,D190/0.6+2,"") -> 389.5 | G190: =CttlePrices_Basis!M971 -> 389 | H190: =IFERROR(F190-G190,"") -> 0.5 | K190: =+_xlfn.IFNA(CttlePrices_Basis!C971,"") -> 232.3 | L190: =IFERROR(F190*0.6,"") -> 233.7 | M190: =IFERROR(L190-K190,"") -> 1.4
A191: 2023 | B191: 32 | C191: =CONCATENATE(A191,$C$3,B191) -> 2023-32 | D191: =+_xlfn.IFNA('[3]weekly-canfax-data'!AN39,"") -> 232.5 | E191: 2 | F191: =IF(D191>0,D191/0.6+2,"") -> 389.5 | G191: =_xlfn.IFNA(CttlePrices_Basis!M972,"") -> 389 | H191: =IFERROR(F191-G191,"") -> 0.5 | K191: =+_xlfn.IFNA(CttlePrices_Basis!C972,"") -> 230.92 | L191: =IFERROR(F191*0.6,"") -> 233.7 | M191: =IFERROR(L191-K191,"") -> 2.78
A192: 2023 | B192: 33 | C192: =CONCATENATE(A192,$C$3,B192) -> 2023-33 | D192: =+_xlfn.IFNA('[3]weekly-canfax-data'!AN40,"") -> 0 | E192: 2 | F192: =IF(D192>0,D192/0.6+2,"") | G192: =+G191 -> 389 | H192: =IFERROR(F192-G192,"") | K192: =+_xlfn.IFNA(CttlePrices_Basis!C973,"") -> 228.43 | L192: =IFERROR(F192*0.6,"") | M192: =IFERROR(L192-K192,"")
A193: 2023 | B193: 34 | C193: =CONCATENATE(A193,$C$3,B193) -> 2023-34 | D193: =+_xlfn.IFNA('[3]weekly-canfax-data'!AN41,"") -> 232.5 | E193: 2 | F193: =IF(D193>0,D193/0.6+2,"") -> 389.5 | G193: =_xlfn.IFNA(CttlePrices_Basis!M974,"") -> 389 | H193: =IFERROR(F193-G193,"") -> 0.5 | K193: =+_xlfn.IFNA(CttlePrices_Basis!C974,"") -> 232.77 | L193: =IFERROR(F193*0.6,"") -> 233.7 | M193: =IFERROR(L193-K193,"") -> 0.93
A194: 2023 | B194: 35 | C194: =CONCATENATE(A194,$C$3,B194) -> 2023-35 | D194: =+_xlfn.IFNA('[3]weekly-canfax-data'!AN42,"") -> 232.5 | E194: 2 | F194: =IF(D194>0,D194/0.6+2,"") -> 389.5 | G194: =_xlfn.IFNA(CttlePrices_Basis!M975,"") -> 389 | H194: =IFERROR(F194-G194,"") -> 0.5 | K194: =+_xlfn.IFNA(CttlePrices_Basis!C975,"") -> 235.09 | L194: =IFERROR(F194*0.6,"") -> 233.7 | M194: =IFERROR(L194-K194,"") -> -1.39
A195: 2023 | B195: 36 | C195: =CONCATENATE(A195,$C$3,B195) -> 2023-36 | D195: =+_xlfn.IFNA('[3]weekly-canfax-data'!AN43,"") -> 232.5 | E195: 2 | F195: =IF(D195>0,D195/0.6+2,"") -> 389.5 | G195: =_xlfn.IFNA(CttlePrices_Basis!M976,"") -> 389 | H195: =IFERROR(F195-G195,"") -> 0.5 | K195: =+_xlfn.IFNA(CttlePrices_Basis!C976,"") -> 229.88 | L195: =IFERROR(F195*0.6,"") -> 233.7 | M195: =IFERROR(L195-K195,"") -> 3.82
A196: 2023 | B196: 37 | C196: =CONCATENATE(A196,$C$3,B196) -> 2023-37 | D196: =+_xlfn.IFNA('[3]weekly-canfax-data'!AN44,"") -> 234.3 | E196: 2 | F196: =IF(D196>0,D196/0.6+2,"") -> 392.5 | G196: =_xlfn.IFNA(CttlePrices_Basis!M977,"") -> 392 | H196: =IFERROR(F196-G196,"") -> 0.5 | K196: =+_xlfn.IFNA(CttlePrices_Basis!C977,"") -> 230.3 | L196: =IFERROR(F196*0.6,"") -> 235.5 | M196: =IFERROR(L196-K196,"") -> 5.2
A197: 2023 | B197: 38 | C197: =CONCATENATE(A197,$C$3,B197) -> 2023-38 | D197: =+_xlfn.IFNA('[3]weekly-canfax-data'!AN45,"") -> 236.08 | E197: 2 | F197: =IF(D197>0,D197/0.6+2,"") -> 395.46667 | G197: =_xlfn.IFNA(CttlePrices_Basis!M978,"") -> 395 | H197: =IFERROR(F197-G197,"") -> 0.46666667 | K197: =+_xlfn.IFNA(CttlePrices_Basis!C978,"") -> 235.12 | L197: =IFERROR(F197*0.6,"") -> 237.28 | M197: =IFERROR(L197-K197,"") -> 2.16
A198: 2023 | B198: 39 | C198: =CONCATENATE(A198,$C$3,B198) -> 2023-39 | D198: =+_xlfn.IFNA('[3]weekly-canfax-data'!AN46,"") -> 235.89 | E198: 2 | F198: =IF(D198>0,D198/0.6+2,"") -> 395.15 | G198: =_xlfn.IFNA(CttlePrices_Basis!M979,"") -> 395 | H198: =IFERROR(F198-G198,"") -> 0.15 | K198: =+_xlfn.IFNA(CttlePrices_Basis!C979,"") -> 232.69 | L198: =IFERROR(F198*0.6,"") -> 237.09 | M198: =IFERROR(L198-K198,"") -> 4.4
A199: 2023 | B199: 40 | C199: =CONCATENATE(A199,$C$3,B199) -> 2023-40 | D199: =+_xlfn.IFNA('[3]weekly-canfax-data'!AN47,"") -> 236.94 | E199: 2 | F199: =IF(D199>0,D199/0.6+2,"") -> 396.9 | G199: =_xlfn.IFNA(CttlePrices_Basis!M980,"") -> 395 | H199: =IFERROR(F199-G199,"") -> 1.9 | K199: =+_xlfn.IFNA(CttlePrices_Basis!C980,"") -> 231.97 | L199: =IFERROR(F199*0.6,"") -> 238.14 | M199: =IFERROR(L199-K199,"") -> 6.17
A200: 2023 | B200: 41 | C200: =CONCATENATE(A200,$C$3,B200) -> 2023-41 | D200: =+_xlfn.IFNA('[3]weekly-canfax-data'!AN48,"") -> 236.1 | E200: 2 | F200: =IF(D200>0,D200/0.6+2,"") -> 395.5 | G200: =_xlfn.IFNA(CttlePrices_Basis!M981,"") -> 395 | H200: =IFERROR(F200-G200,"") -> 0.5 | K200: =+_xlfn.IFNA(CttlePrices_Basis!C981,"") -> 233.69 | L200: =IFERROR(F200*0.6,"") -> 237.3 | M200: =IFERROR(L200-K200,"") -> 3.61
A201: 2023 | B201: 42 | C201: =CONCATENATE(A201,$C$3,B201) -> 2023-42 | D201: =+_xlfn.IFNA('[3]weekly-canfax-data'!AN49,"") -> 236.1 | E201: 2 | F201: =IF(D201>0,D201/0.6+2,"") -> 395.5 | G201: =_xlfn.IFNA(CttlePrices_Basis!M982,"") -> 395 | H201: =IFERROR(F201-G201,"") -> 0.5 | K201: =+_xlfn.IFNA(CttlePrices_Basis!C982,"") -> 233.77 | L201: =IFERROR(F201*0.6,"") -> 237.3 | M201: =IFERROR(L201-K201,"") -> 3.53
A202: 2023 | B202: 43 | C202: =CONCATENATE(A202,$C$3,B202) -> 2023-43 | D202: =+_xlfn.IFNA('[3]weekly-canfax-data'!AN50,"") -> 236.1 | E202: 2 | F202: =IF(D202>0,D202/0.6+2,"") -> 395.5 | G202: =_xlfn.IFNA(CttlePrices_Basis!M983,"") -> 395 | H202: =IFERROR(F202-G202,"") -> 0.5 | K202: =+_xlfn.IFNA(CttlePrices_Basis!C983,"") -> 230.51 | L202: =IFERROR(F202*0.6,"") -> 237.3 | M202: =IFERROR(L202-K202,"") -> 6.79
A203: 2023 | B203: 44 | C203: =CONCATENATE(A203,$C$3,B203) -> 2023-44 | D203: =+_xlfn.IFNA('[3]weekly-canfax-data'!AN51,"") -> 236.1 | E203: 2 | F203: =IF(D203>0,D203/0.6+2,"") -> 395.5 | G203: =_xlfn.IFNA(CttlePrices_Basis!M984,"") -> 395 | H203: =IFERROR(F203-G203,"") -> 0.5 | K203: =+_xlfn.IFNA(CttlePrices_Basis!C984,"") -> 230.68 | L203: =IFERROR(F203*0.6,"") -> 237.3 | M203: =IFERROR(L203-K203,"") -> 6.62
A204: 2023 | B204: 45 | C204: =CONCATENATE(A204,$C$3,B204) -> 2023-45 | D204: =+_xlfn.IFNA('[3]weekly-canfax-data'!AN52,"") -> 236.1 | E204: 2 | F204: =IF(D204>0,D204/0.6+2,"") -> 395.5 | G204: =_xlfn.IFNA(CttlePrices_Basis!M985,"") -> 394 | H204: =IFERROR(F204-G204,"") -> 1.5 | K204: =+_xlfn.IFNA(CttlePrices_Basis!C985,"") -> 234.36 | L204: =IFERROR(F204*0.6,"") -> 237.3 | M204: =IFERROR(L204-K204,"") -> 2.94
... A211: 2023 | B211: 52 | C211: =CONCATENATE(A211,$C$3,B211) -> 2023-52 | D211: =+_xlfn.IFNA('[3]weekly-canfax-data'!AN59,"") -> 0 | E211: 2 | F211: =IF(D211>0,D211/0.6+2,"") | G211: =_xlfn.IFNA(CttlePrices_Basis!M992,"") | H211: =IFERROR(F211-G211,"") | K211: =+_xlfn.IFNA(CttlePrices_Basis!C992,"") -> 217.21 | L211: =IFERROR(F211*0.6,"") | M211: =IFERROR(L211-K211,"")
A212: 2024 | B212: 1 | C212: =CONCATENATE(A212,$C$3,B212) -> 2024-1 | D212: =+'[4]weekly-canfax-data'!AO11 -> 224.08 | E212: 2 | F212: =IF(D212>0,D212/0.6+2,"") -> 375.46667 | G212: =_xlfn.IFNA(CttlePrices_Basis!M993,"") -> 375 | H212: =IFERROR(F212-G212,"") -> 0.46666667 | K212: =+_xlfn.IFNA(CttlePrices_Basis!C993,"") -> 216.51 | L212: =IFERROR(F212*0.6,"") -> 225.28 | M212: =IFERROR(L212-K212,"") -> 8.77
A213: 2024 | B213: 2 | C213: =CONCATENATE(A213,$C$3,B213) -> 2024-2 | D213: =+'[4]weekly-canfax-data'!AO12 -> 224.09 | E213: 2 | F213: =IF(D213>0,D213/0.6+2,"") -> 375.48333 | G213: =_xlfn.IFNA(CttlePrices_Basis!M994,"") -> 375 | H213: =IFERROR(F213-G213,"") -> 0.48333333 | K213: =+_xlfn.IFNA(CttlePrices_Basis!C994,"") -> 222.03 | L213: =IFERROR(F213*0.6,"") -> 225.29 | M213: =IFERROR(L213-K213,"") -> 3.26
A214: 2024 | B214: 3 | C214: =CONCATENATE(A214,$C$3,B214) -> 2024-3 | D214: =+'[4]weekly-canfax-data'!AO13 -> 224.1 | E214: 2 | F214: =IF(D214>0,D214/0.6+2,"") -> 375.5 | G214: =_xlfn.IFNA(CttlePrices_Basis!M995,"") -> 375 | H214: =IFERROR(F214-G214,"") -> 0.5 | K214: =+_xlfn.IFNA(CttlePrices_Basis!C995,"") -> 223.08 | L214: =IFERROR(F214*0.6,"") -> 225.3 | M214: =IFERROR(L214-K214,"") -> 2.22
A215: 2024 | B215: 4 | C215: =CONCATENATE(A215,$C$3,B215) -> 2024-4 | D215: =+'[4]weekly-canfax-data'!AO14 -> 228.58 | E215: 2 | F215: =IF(D215>0,D215/0.6+2,"") -> 382.96667 | G215: =_xlfn.IFNA(CttlePrices_Basis!M996,"") -> 382.5 | H215: =IFERROR(F215-G215,"") -> 0.46666667 | K215: =+_xlfn.IFNA(CttlePrices_Basis!C996,"") -> 224.5 | L215: =IFERROR(F215*0.6,"") -> 229.78 | M215: =IFERROR(L215-K215,"") -> 5.28
...

Sheet Market Price
D1: OCA Large & medium frame steers - 900-999 | E1: OCA Large & Medium Farm Steer over 1250+ price
A2: Year | B2: Week | C2: Week Ending | D2: Steer Price $ per cwt | E2: Steer Price $ per cwt
A3: 1999 | B3: 1 | C3: 36168 | D3: 91.56 | E3: 87.94
A4: 1999 | B4: 2 | C4: =C3+7 -> 36175 | D4: 98.4 | E4: 89.38
A5: 1999 | B5: 3 | C5: =C4+7 -> 36182 | D5: 101.88 | E5: 90.68
A6: 1999 | B6: 4 | C6: =C5+7 -> 36189 | D6: 99.18 | E6: 90.32
A7: 1999 | B7: 5 | C7: =C6+7 -> 36196 | D7: 101.97 | E7: 91.1
A8: 1999 | B8: 6 | C8: =C7+7 -> 36203 | D8: 103.57 | E8: 91.19
A9: 1999 | B9: 7 | C9: =C8+7 -> 36210 | D9: 100.32 | E9: 90.62
A10: 1999 | B10: 8 | C10: =C9+7 -> 36217 | D10: 101.27 | E10: 90.86
A11: 1999 | B11: 9 | C11: =C10+7 -> 36224 | D11: 102.58 | E11: 91.89
A12: 1999 | B12: 10 | C12: =C11+7 -> 36231 | D12: 103.58 | E12: 92.68
A13: 1999 | B13: 11 | C13: =C12+7 -> 36238 | D13: 100.99 | E13: 93.34
A14: 1999 | B14: 12 | C14: =C13+7 -> 36245 | D14: 102.19 | E14: 92.54
A15: 1999 | B15: 13 | C15: =C14+7 -> 36252 | D15: 98.8 | E15: 92.58
... A1150: 2020 | B1150: 53 | C1150: =C1149+7 -> 44197 | D1150: 164.98 | E1150: 115.31
A1151: 2021 | B1151: 1 | C1151: =C1150+7 -> 44204 | D1151: =+[1]fedcat!$CS5 -> 176.39 | E1151: =+[1]fedcat!$AB5 -> 129.23
A1152: 2021 | B1152: 2 | C1152: =C1151+7 -> 44211 | D1152: =+[1]fedcat!$CS6 -> 178.45 | E1152: =+[1]fedcat!$AB6 -> 129.98
A1153: 2021 | B1153: 3 | C1153: =C1152+7 -> 44218 | D1153: =+[1]fedcat!$CS7 -> 172.73 | E1153: =+[1]fedcat!$AB7 -> 133.5
A1154: 2021 | B1154: 4 | C1154: =C1153+7 -> 44225 | D1154: =+[1]fedcat!$CS8 -> 175.62 | E1154: =+[1]fedcat!$AB8 -> 134.16
A1155: 2021 | B1155: 5 | C1155: =C1154+7 -> 44232 | D1155: =+[1]fedcat!$CS9 -> 179.09 | E1155: =+[1]fedcat!$AB9 -> 138.07
A1156: 2021 | B1156: 6 | C1156: =C1155+7 -> 44239 | D1156: =+[1]fedcat!$CS10 -> 180.48 | E1156: =+[1]fedcat!$AB10 -> 135.93
A1157: 2021 | B1157: 7 | C1157: =C1156+7 -> 44246 | D1157: =+[1]fedcat!$CS11 -> 181.67 | E1157: =+[1]fedcat!$AB11 -> 131.7
A1158: 2021 | B1158: 8 | C1158: =C1157+7 -> 44253 | D1158: =+[1]fedcat!$CS12 -> 174.87 | E1158: =+[1]fedcat!$AB12 -> 136.79
A1159: 2021 | B1159: 9 | C1159: =C1158+7 -> 44260 | D1159: =+[1]fedcat!$CS13 -> 172.84 | E1159: =+[1]fedcat!$AB13 -> 140.1
A1160: 2021 | B1160: 10 | C1160: =C1159+7 -> 44267 | D1160: =+[1]fedcat!$CS14 -> 172.62 | E1160: =+[1]fedcat!$AB14 -> 141.07
A1161: 2021 | B1161: 11 | C1161: =C1160+7 -> 44274 | D1161: =+[1]fedcat!$CS15 -> 167.37 | E1161: =+[1]fedcat!$AB15 -> 140.79
A1162: 2021 | B1162: 12 | C1162: =C1161+7 -> 44281 | D1162: =+[1]fedcat!$CS16 -> 170.08 | E1162: =+[1]fedcat!$AB16 -> 140.3
... A1168: 2021 | B1168: 18 | C1168: =C1167+7 -> 44323 | D1168: =+[1]fedcat!$CS22 -> 167.62 | E1168: =+[1]fedcat!$AB22 -> 145.72
A1169: 2021 | B1169: 19 | C1169: =C1168+7 -> 44330 | D1169: =+[1]fedcat!$CS$23 -> 166.57 | E1169: =+[1]fedcat!$AB$23 -> 147.25
A1170: 2021 | B1170: 20 | C1170: =C1169+7 -> 44337 | D1170: =+[1]fedcat!$CS24 -> 170.6 | E1170: =+[1]fedcat!$AB24 -> 147.21
A1171: 2021 | B1171: 21 | C1171: =C1170+7 -> 44344 | D1171: =+[1]fedcat!$CS25 -> 171.91 | E1171: =+[1]fedcat!$AB25 -> 151.65
A1172: 2021 | B1172: 22 | C1172: =C1171+7 -> 44351 | D1172: =+[1]fedcat!$CS26 -> 176.78 | E1172: =+[1]fedcat!$AB26 -> 155.18
A1173: 2021 | B1173: 23 | C1173: =C1172+7 -> 44358 | D1173: =+[1]fedcat!$CS27 -> 174.92 | E1173: =+[1]fedcat!$AB27 -> 160.81
A1174: 2021 | B1174: 24 | C1174: =C1173+7 -> 44365 | D1174: =+[1]fedcat!$CS28 -> 177.21 | E1174: =+[1]fedcat!$AB28 -> 158.79
A1175: 2021 | B1175: 25 | C1175: =C1174+7 -> 44372 | D1175: =+[1]fedcat!$CS29 -> 177.25 | E1175: =+[1]fedcat!$AB29 -> 160.48
A1176: 2021 | B1176: 26 | C1176: =C1175+7 -> 44379 | D1176: =+[1]fedcat!$CS30 -> 183.77 | E1176: =+[1]fedcat!$AB30 -> 159.17
A1177: 2021 | B1177: 27 | C1177: =C1176+7 -> 44386 | D1177: =+[1]fedcat!$CS31 -> 171.98 | E1177: =+[1]fedcat!$AB31 -> 155.8
A1178: 2021 | B1178: 28 | C1178: =C1177+7 -> 44393 | D1178: =+[1]fedcat!$CS32 -> 181.25 | E1178: =+[1]fedcat!$AB32 -> 157.65
A1179: 2021 | B1179: 29 | C1179: =C1178+7 -> 44400 | D1179: =+[1]fedcat!$CS33 -> 176.98 | E1179: =+[1]fedcat!$AB33 -> 156.99
A1180: 2021 | B1180: 30 | C1180: =C1179+7 -> 44407 | D1180: =+[1]fedcat!$CS34 -> 184.68 | E1180: =+[1]fedcat!$AB34 -> 154.54
A1181: 2021 | B1181: 31 | C1181: =C1180+7 -> 44414 | D1181: =+[1]fedcat!$CS35 -> 188.24 | E1181: =+[1]fedcat!$AB35 -> 152.36
... A1201: 2021 | B1201: 51 | C1201: =C1200+7 -> 44554 | D1201: =+[1]fedcat!$CS55 -> 194.24 | E1201: =+[1]fedcat!$AB55 -> 159.26
A1202: 2021 | B1202: 52 | C1202: =C1201+7 -> 44561 | D1202: =+[2]fedcat!$BZ5 -> 218.69 | E1202: =+[2]fedcat!$T5 -> 171.37
A1203: 2022 | B1203: 1 | C1203: =C1202+7 -> 44568 | D1203: =+[2]fedcat!$BZ5 -> 218.69 | E1203: =+[2]fedcat!$T5 -> 171.37
A1204: 2022 | B1204: 2 | C1204: =C1203+7 -> 44575 | D1204: =+[2]fedcat!$BZ6 -> 208.92 | E1204: =+[2]fedcat!$T6 -> 169.2
A1205: 2022 | B1205: 3 | C1205: =C1204+7 -> 44582 | D1205: =+[2]fedcat!$BZ7 -> 201.12 | E1205: =+[2]fedcat!$T7 -> 169.71
A1206: 2022 | B1206: 4 | C1206: =C1205+7 -> 44589 | D1206: =+[2]fedcat!$BZ8 -> 203.39 | E1206: =+[2]fedcat!$T8 -> 166.91
A1207: 2022 | B1207: 5 | C1207: =C1206+7 -> 44596 | D1207: =+[2]fedcat!$BZ9 -> 204.91 | E1207: =+[2]fedcat!$T9 -> 171.93
A1208: 2022 | B1208: 6 | C1208: =C1207+7 -> 44603 | D1208: =+[2]fedcat!$BZ10 -> 204.86 | E1208: =+[2]fedcat!$T10 -> 169.26
A1209: 2022 | B1209: 7 | C1209: =C1208+7 -> 44610 | D1209: =+[2]fedcat!$BZ11 -> 206.45 | E1209: =+[2]fedcat!$T11 -> 165.89
A1210: 2022 | B1210: 8 | C1210: =C1209+7 -> 44617 | D1210: =+[2]fedcat!$BZ12 -> 195.4 | E1210: =+[2]fedcat!$T12 -> 165.31
A1211: 2022 | B1211: 9 | C1211: =C1210+7 -> 44624 | D1211: =+[2]fedcat!$BZ13 -> 192.51 | E1211: =+[2]fedcat!$T13 -> 169.08
A1212: 2022 | B1212: 10 | C1212: =C1211+7 -> 44631 | D1212: =+[2]fedcat!$BZ14 -> 193.1 | E1212: =+[2]fedcat!$T14 -> 168.13
A1213: 2022 | B1213: 11 | C1213: =C1212+7 -> 44638 | D1213: =+[2]fedcat!$BZ15 -> 193.16 | E1213: =+[2]fedcat!$T15 -> 170.55
A1214: 2022 | B1214: 12 | C1214: =C1213+7 -> 44645 | D1214: =+[2]fedcat!$BZ16 -> 186.09 | E1214: =+[2]fedcat!$T16 -> 172.08
... A1254: 2022 | B1254: 52 | C1254: =C1253+7 -> 44925 | D1254: =+[2]fedcat!$BZ56 -> 240.32 | E1254: =+[2]fedcat!$T56 -> 198.98
A1255: 2023 | B1255: 1 | C1255: =C1254+7 -> 44932 | D1255: =+[3]fedcat!$CD5 -> 253.21 | E1255: =+[3]fedcat!$AK5 -> 192.38
A1256: 2023 | B1256: 2 | C1256: =C1255+7 -> 44939 | D1256: =+[3]fedcat!$CD6 -> 246.5 | E1256: =+[3]fedcat!$AK6 -> 189.22
A1257: 2023 | B1257: 3 | C1257: =C1256+7 -> 44946 | D1257: =+[3]fedcat!$CD7 -> 247.8 | E1257: =+[3]fedcat!$AK7 -> 191.06
A1258: 2023 | B1258: 4 | C1258: =C1257+7 -> 44953 | D1258: =+[3]fedcat!$CD8 -> 242.12 | E1258: =+[3]fedcat!$AK8 -> 191.92
A1259: 2023 | B1259: 5 | C1259: =C1258+7 -> 44960 | D1259: =+[3]fedcat!$CD9 -> 250.99 | E1259: =+[3]fedcat!$AK9 -> 192.45
A1260: 2023 | B1260: 6 | C1260: =C1259+7 -> 44967 | D1260: =+[3]fedcat!$CD10 -> 256.79 | E1260: =+[3]fedcat!$AK10 -> 197.92
A1261: 2023 | B1261: 7 | C1261: =C1260+7 -> 44974 | D1261: =+[3]fedcat!$CD11 -> 257.87 | E1261: =+[3]fedcat!$AK11 -> 196.71
A1262: 2023 | B1262: 8 | C1262: =C1261+7 -> 44981 | D1262: =+[3]fedcat!$CD12 -> 254.68 | E1262: =+[3]fedcat!$AK12 -> 196.23
A1263: 2023 | B1263: 9 | C1263: =C1262+7 -> 44988 | D1263: =+[3]fedcat!$CD13 -> 267.02 | E1263: =+[3]fedcat!$AK13 -> 205.02
A1264: 2023 | B1264: 10 | C1264: =C1263+7 -> 44995 | D1264: =+[3]fedcat!$CD14 -> 264.18 | E1264: =+[3]fedcat!$AK14 -> 206.22
A1265: 2023 | B1265: 11 | C1265: =C1264+7 -> 45002 | D1265: =+[3]fedcat!$CD15 -> 267.72 | E1265: =+[3]fedcat!$AK15 -> 207.62
A1266: 2023 | B1266: 12 | C1266: =C1265+7 -> 45009 | D1266: =+[3]fedcat!$CD16 -> 258.02 | E1266: =+[3]fedcat!$AK16 -> 209.54
... A1306: 2023 | B1306: 52 | C1306: =C1305+7 -> 45289 | D1306: =+[3]fedcat!$CD56 -> 311.03 | E1306: =+[3]fedcat!$AK56 -> 217.21
A1307: 2024 | B1307: 1 | C1307: =C1306+7 -> 45296 | D1307: =[4]fedcat!CH5 -> 266.61 | E1307: =[4]fedcat!AM5 -> 216.51
A1308: 2024 | B1308: 2 | C1308: =C1307+7 -> 45303 | D1308: =[4]fedcat!CH6 -> 281.13 | E1308: =[4]fedcat!AM6 -> 222.03
A1309: 2024 | B1309: 3 | C1309: =C1308+7 -> 45310 | D1309: =[4]fedcat!CH7 -> 303.39 | E1309: =[4]fedcat!AM7 -> 223.08
A1310: 2024 | B1310: 4 | C1310: =C1309+7 -> 45317 | D1310: =[4]fedcat!CH8 -> 301.44 | E1310: =[4]fedcat!AM8 -> 224.5
A1311: 2024 | B1311: 5 | C1311: =C1310+7 -> 45324 | D1311: =[4]fedcat!CH9 -> 308.85 | E1311: =[4]fedcat!AM9 -> 231.03
A1312: 2024 | B1312: 6 | C1312: =C1311+7 -> 45331 | D1312: =[4]fedcat!CH10 -> 314.35 | E1312: =[4]fedcat!AM10 -> 231.84
A1313: 2024 | B1313: 7 | C1313: =C1312+7 -> 45338 | D1313: =[4]fedcat!CH11 -> 309.52 | E1313: =[4]fedcat!AM11 -> 232.98
A1314: 2024 | B1314: 8 | C1314: =C1313+7 -> 45345 | D1314: =[4]fedcat!CH12 -> 323.22 | E1314: =[4]fedcat!AM12 -> 239.25
A1315: 2024 | B1315: 9 | C1315: =C1314+7 -> 45352 | D1315: =[4]fedcat!CH13 -> 311.49 | E1315: =[4]fedcat!AM13 -> 227.51
A1316: 2024 | B1316: 10 | C1316: =C1315+7 -> 45359 | D1316: =[4]fedcat!CH14 -> 307.32 | E1316: =[4]fedcat!AM14 -> 239.34
A1317: 2024 | B1317: 11 | C1317: =C1316+7 -> 45366 | D1317: =[4]fedcat!CH15 -> 312.26 | E1317: =[4]fedcat!AM15 -> 240.15
A1318: 2024 | B1318: 12 | C1318: =C1317+7 -> 45373 | D1318: =[4]fedcat!CH16 -> 318.45 | E1318: =[4]fedcat!AM16 -> 242.6
... A1358: 2024 | B1358: 52 | C1358: =C1357+7 -> 45653 | D1358: =[4]fedcat!CH56 -> #N/A | E1358: =[4]fedcat!AM56 -> #N/A
A1359: ='[5]Market Price'!A1359 -> 2025 | B1359: ='[5]Market Price'!B1359 -> 1 | C1359: =C1358+7 -> 45660 | D1359: ='[5]Market Price'!D1359 -> 357.08 | E1359: ='[5]Market Price'!E1359 -> 256.13
A1360: ='[5]Market Price'!A1360 -> 2025 | B1360: ='[5]Market Price'!B1360 -> 2 | C1360: =C1359+7 -> 45667 | D1360: ='[5]Market Price'!D1360 -> 362.75 | E1360: ='[5]Market Price'!E1360 -> 261.08
A1361: ='[5]Market Price'!A1361 -> 2025 | B1361: ='[5]Market Price'!B1361 -> 3 | C1361: =C1360+7 -> 45674 | D1361: ='[5]Market Price'!D1361 -> 374.9 | E1361: ='[5]Market Price'!E1361 -> 270.22
A1362: ='[5]Market Price'!A1362 -> 2025 | B1362: ='[5]Market Price'!B1362 -> 4 | C1362: =C1361+7 -> 45681 | D1362: ='[5]Market Price'!D1362 -> 367.43 | E1362: ='[5]Market Price'!E1362 -> 272.8
A1363: ='[5]Market Price'!A1363 -> 2025 | B1363: ='[5]Market Price'!B1363 -> 5 | C1363: =C1362+7 -> 45688 | D1363: ='[5]Market Price'!D1363 -> 381.62 | E1363: ='[5]Market Price'!E1363 -> 278.04
A1364: ='[5]Market Price'!A1364 -> 2025 | B1364: ='[5]Market Price'!B1364 -> 6 | C1364: =C1363+7 -> 45695 | D1364: ='[5]Market Price'!D1364 -> 375.94 | E1364: ='[5]Market Price'!E1364 -> 277.81
A1365: ='[5]Market Price'!A1365 -> 2025 | B1365: ='[5]Market Price'!B1365 -> 7 | C1365: =C1364+7 -> 45702 | D1365: ='[5]Market Price'!D1365 -> 371.98 | E1365: ='[5]Market Price'!E1365 -> 274.86
A1366: ='[5]Market Price'!A1366 -> 2025 | B1366: ='[5]Market Price'!B1366 -> 8 | C1366: =C1365+7 -> 45709 | D1366: ='[5]Market Price'!D1366 -> 363.52 | E1366: ='[5]Market Price'!E1366 -> 277.01
A1367: ='[5]Market Price'!A1367 -> 2025 | B1367: ='[5]Market Price'!B1367 -> 9 | C1367: =C1366+7 -> 45716 | D1367: ='[5]Market Price'!D1367 -> 366.02 | E1367: ='[5]Market Price'!E1367 -> 267.56
A1368: ='[5]Market Price'!A1368 -> 2025 | B1368: ='[5]Market Price'!B1368 -> 10 | C1368: =C1367+7 -> 45723 | D1368: ='[5]Market Price'!D1368 -> 348.54 | E1368: ='[5]Market Price'!E1368 -> 231.01
A1369: ='[5]Market Price'!A1369 -> 2025 | B1369: ='[5]Market Price'!B1369 -> 11 | C1369: =C1368+7 -> 45730 | D1369: ='[5]Market Price'!D1369 -> 353.01 | E1369: ='[5]Market Price'!E1369 -> 271.49
A1370: ='[5]Market Price'!A1370 -> 2025 | B1370: ='[5]Market Price'!B1370 -> 12 | C1370: =C1369+7 -> 45737 | D1370: ='[5]Market Price'!D1370 -> 364.4 | E1370: ='[5]Market Price'!E1370 -> 267.57
... A1469: ='[5]Market Price'!A1469 -> 0 | B1469: ='[5]Market Price'!B1469 -> 0 | C1469: =C1468+7 -> 46430 | D1469: ='[5]Market Price'!D1469 -> 0 | E1469: ='[5]Market Price'!E1469 -> 0

Sheet Feed Cost
H1: Feedlot - Steer
B2: Corn | D2: Corn Silage | E2: Distillers Dried Grain | F2: Soymeal | G2: Concentrate | H2: Feed Cost
A3: Source | B3: Farm Market News | D3: OMAFRA 5 year Historicl % of Corn Price | E3: Farm Market News | F3: Farm Market News | G3: RMP produced % of Soymeal Price | H3: Based on RMP
A4: Assumptions | B4: Includes $15 per tonne for delivery to farm since most producers don’t truck the feed themselves | D4: Corn silage is worht 16.16% the value of a tonne of grain corn | H4: 1802.4lbs of silage, 3715.4lbs of corn, 964.9lbs of DDGS, 272.4lbs of concentrate to take 900lb steer to 1500lb at 3.25lbs per day of gain
A5: Units | B5: $/bu | C5: $/tonne | D5: $/tonne | E5: $/tonne | F5: $/tonne | G5: $/tonne | H5: $ per 1500lb Steer | I5: =1500-900 -> 600 | J5: =+I5/3.25 -> 184.61538 | K5: =+J5/7 -> 26.373626
A6: =A7-7 -> 36168 | B6: 2.7925 | C6: =B6*39.368+15 -> 124.93514 | D6: =C6*0.1616 -> 20.189519 | E6: 119.18002 | F6: 258.121 | G6: =F6*1.43 -> 369.11303 | H6: =($D6/2204.62)*1802.4+($C6/2204.62)*3715.4+($E6/2204.62)*964.9+(G6/2204.62)*272.4 -> 324.8255
A7: =A8-7 -> 36175 | B7: 2.73 | C7: =B7*39.368+15 -> 122.47464 | D7: =C7*0.1616 -> 19.791902 | E7: 120.97163 | F7: 248.708 | G7: =F7*1.43 -> 355.65244 | H7: =($D7/2204.62)*1802.4+($C7/2204.62)*3715.4+($E7/2204.62)*964.9+(G7/2204.62)*272.4 -> 319.47476
A8: =A9-7 -> 36182 | B8: 2.7625 | C8: =B8*39.368+15 -> 123.7541 | D8: =C8*0.1616 -> 19.998663 | E8: 120.0311 | F8: 244.497 | G8: =F8*1.43 -> 349.63071 | H8: =($D8/2204.62)*1802.4+($C8/2204.62)*3715.4+($E8/2204.62)*964.9+(G8/2204.62)*272.4 -> 320.64437
A9: =A10-7 -> 36189 | B9: 2.77 | C9: =B9*39.368+15 -> 124.04936 | D9: =C9*0.1616 -> 20.046377 | E9: 119.81681 | F9: 242.796 | G9: =F9*1.43 -> 347.19828 | H9: =($D9/2204.62)*1802.4+($C9/2204.62)*3715.4+($E9/2204.62)*964.9+(G9/2204.62)*272.4 -> 320.78664
A10: =A11-7 -> 36196 | B10: 2.81 | C10: =B10*39.368+15 -> 125.62408 | D10: =C10*0.1616 -> 20.300851 | E10: 118.69094 | F10: 248.465 | G10: =F10*1.43 -> 355.30495 | H10: =($D10/2204.62)*1802.4+($C10/2204.62)*3715.4+($E10/2204.62)*964.9+(AVERAGE(G1:G9)/2204.62)*272.4 -> 324.16899
A11: =A12-7 -> 36203 | B11: 2.775 | C11: =B11*39.368+15 -> 124.2462 | D11: =C11*0.1616 -> 20.078186 | E11: 119.67452 | F11: 240.926 | G11: =F11*1.43 -> 344.52418 | H11: =($D11/2204.62)*1802.4+($C11/2204.62)*3715.4+($E11/2204.62)*964.9+(AVERAGE(G2:G10)/2204.62)*272.4 -> 322.093
A12: =A13-7 -> 36210 | B12: 2.775 | C12: =B12*39.368+15 -> 124.2462 | D12: =C12*0.1616 -> 20.078186 | E12: 119.67452 | F12: 238.874 | G12: =F12*1.43 -> 341.58982 | H12: =($D12/2204.62)*1802.4+($C12/2204.62)*3715.4+($E12/2204.62)*964.9+(AVERAGE(G3:G11)/2204.62)*272.4 -> 321.86945
A13: =A14-7 -> 36217 | B13: 2.6775 | C13: =B13*39.368+15 -> 120.40782 | D13: =C13*0.1616 -> 19.457904 | E13: 122.53318 | F13: 229.021 | G13: =F13*1.43 -> 327.50003 | H13: =($D13/2204.62)*1802.4+($C13/2204.62)*3715.4+($E13/2204.62)*964.9+(AVERAGE(G4:G12)/2204.62)*272.4 -> 315.93327
A14: =A15-7 -> 36224 | B14: 2.76 | C14: =B14*39.368+15 -> 123.65568 | D14: =C14*0.1616 -> 19.982758 | E14: 120.10276 | F14: 232.176 | G14: =F14*1.43 -> 332.01168 | H14: =($D14/2204.62)*1802.4+($C14/2204.62)*3715.4+($E14/2204.62)*964.9+(AVERAGE(G5:G13)/2204.62)*272.4 -> 320.39597
A15: =A16-7 -> 36231 | B15: 2.8775 | C15: =B15*39.368+15 -> 128.28142 | D15: =C15*0.1616 -> 20.730277 | E15: 116.85372 | F15: 236.736 | G15: =F15*1.43 -> 338.53248 | H15: =($D15/2204.62)*1802.4+($C15/2204.62)*3715.4+($E15/2204.62)*964.9+(AVERAGE(G6:G14)/2204.62)*272.4 -> 327.15008
A16: =A17-7 -> 36238 | B16: 2.94 | C16: =B16*39.368+15 -> 130.74192 | D16: =C16*0.1616 -> 21.127894 | E16: 115.21917 | F16: 235.942 | G16: =F16*1.43 -> 337.39706 | H16: =($D16/2204.62)*1802.4+($C16/2204.62)*3715.4+($E16/2204.62)*964.9+($G16/2204.62)*272.4 -> 329.72639
A17: =A18-7 -> 36245 | B17: 2.9975 | C17: =B17*39.368+15 -> 133.00558 | D17: =C17*0.1616 -> 21.493702 | E17: 113.7688 | F17: 239.757 | G17: =F17*1.43 -> 342.85251 | H17: =($D17/2204.62)*1802.4+($C17/2204.62)*3715.4+($E17/2204.62)*964.9+($G17/2204.62)*272.4 -> 333.87964
A18: =A19-7 -> 36252 | B18: 2.92 | C18: =B18*39.368+15 -> 129.95456 | D18: =C18*0.1616 -> 21.000657 | E18: 115.73549 | F18: 237.794 | G18: =F18*1.43 -> 340.04542 | H18: =($D18/2204.62)*1802.4+($C18/2204.62)*3715.4+($E18/2204.62)*964.9+($G18/2204.62)*272.4 -> 328.84865
A19: =A20-7 -> 36259 | B19: 2.84 | C19: =B19*39.368+15 -> 126.80512 | D19: =C19*0.1616 -> 20.491707 | E19: 117.86489 | F19: 238.521 | G19: =F19*1.43 -> 341.08503 | H19: =($D19/2204.62)*1802.4+($C19/2204.62)*3715.4+($E19/2204.62)*964.9+($G19/2204.62)*272.4 -> 324.1853
A20: =A21-7 -> 36266 | B20: 2.91 | C20: =B20*39.368+15 -> 129.56088 | D20: =C20*0.1616 -> 20.937038 | E20: 115.99601 | F20: 235.81 | G20: =F20*1.43 -> 337.2083 | H20: =($D20/2204.62)*1802.4+($C20/2204.62)*3715.4+($E20/2204.62)*964.9+($G20/2204.62)*272.4 -> 327.89664
A21: =A22-7 -> 36273 | B21: 3.0025 | C21: =B21*39.368+15 -> 133.20242 | D21: =C21*0.1616 -> 21.525511 | E21: 113.64501 | F21: 221.47 | G21: =F21*1.43 -> 316.7021 | H21: =($D21/2204.62)*1802.4+($C21/2204.62)*3715.4+($E21/2204.62)*964.9+($G21/2204.62)*272.4 -> 330.95208
A22: =A23-7 -> 36280 | B22: 2.9125 | C22: =B22*39.368+15 -> 129.6593 | D22: =C22*0.1616 -> 20.952943 | E22: 115.93073 | F22: 227.874 | G22: =F22*1.43 -> 325.85982 | H22: =($D22/2204.62)*1802.4+($C22/2204.62)*3715.4+($E22/2204.62)*964.9+($G22/2204.62)*272.4 -> 326.64474
A23: =A24-7 -> 36287 | B23: 2.91 | C23: =B23*39.368+15 -> 129.56088 | D23: =C23*0.1616 -> 20.937038 | E23: 115.99601 | F23: 230.982 | G23: =F23*1.43 -> 330.30426 | H23: =($D23/2204.62)*1802.4+($C23/2204.62)*3715.4+($E23/2204.62)*964.9+($G23/2204.62)*272.4 -> 327.04359
A24: =A25-7 -> 36294 | B24: 2.9175 | C24: =B24*39.368+15 -> 129.85614 | D24: =C24*0.1616 -> 20.984752 | E24: 115.80047 | F24: 235.811 | G24: =F24*1.43 -> 337.20973 | H24: =($D24/2204.62)*1802.4+($C24/2204.62)*3715.4+($E24/2204.62)*964.9+($G24/2204.62)*272.4 -> 328.34785
A25: =A26-7 -> 36301 | B25: 2.885 | C25: =B25*39.368+15 -> 128.57668 | D25: =C25*0.1616 -> 20.777991 | E25: 116.65427 | F25: 231.248 | G25: =F25*1.43 -> 330.68464 | H25: =($D25/2204.62)*1802.4+($C25/2204.62)*3715.4+($E25/2204.62)*964.9+($G25/2204.62)*272.4 -> 325.59001
A26: =A27-7 -> 36308 | B26: 2.845 | C26: =B26*39.368+15 -> 127.00196 | D26: =C26*0.1616 -> 20.523517 | E26: 117.72871 | F26: 232.99 | G26: =F26*1.43 -> 333.1757 | H26: =($D26/2204.62)*1802.4+($C26/2204.62)*3715.4+($E26/2204.62)*964.9+($G26/2204.62)*272.4 -> 323.50617
A27: =A28-7 -> 36315 | B27: 2.8075 | C27: =B27*39.368+15 -> 125.52566 | D27: =C27*0.1616 -> 20.284947 | E27: 118.76048 | F27: 238.258 | G27: =F27*1.43 -> 340.70894 | H27: =($D27/2204.62)*1802.4+($C27/2204.62)*3715.4+($E27/2204.62)*964.9+($G27/2204.62)*272.4 -> 322.20552
... A32: =A33-7 -> 36350 | B32: 2.4525 | C32: =B32*39.368+15 -> 111.55002 | D32: =C32*0.1616 -> 18.026483 | E32: 129.88092 | F32: 228.404 | G32: =F32*1.43 -> 326.61772 | H32: =($D32/2204.62)*1802.4+($C32/2204.62)*3715.4+($E32/2204.62)*964.9+($G32/2204.62)*272.4 -> 299.93225
A33: =A34-7 -> 36357 | B33: 2.4525 | C33: =B33*39.368+15 -> 111.55002 | D33: =C33*0.1616 -> 18.026483 | E33: 129.88092 | F33: 237.333 | G33: =F33*1.43 -> 339.38619 | H33: =(AVERAGE(D6:D32)/2204.62)*1802.4+(AVERAGE(C6:C32)/2204.62)*3715.4+(AVERAGE(E6:E32)/2204.62)*964.9+(AVERAGE(G6:G32)/2204.62)*272.4 -> 322.84415
A34: =A35-7 -> 36364 | B34: 2.745 | C34: =B34*39.368+15 -> 123.06516 | D34: =C34*0.1616 -> 19.88733 | E34: 120.53511 | F34: 240.461 | G34: =F34*1.43 -> 343.85923 | H34: =(AVERAGE(D7:D33)/2204.62)*1802.4+(AVERAGE(C7:C33)/2204.62)*3715.4+(AVERAGE(E7:E33)/2204.62)*964.9+(AVERAGE(G7:G33)/2204.62)*272.4 -> 321.98061
A35: =A36-7 -> 36371 | B35: 2.6825 | C35: =B35*39.368+15 -> 120.60466 | D35: =C35*0.1616 -> 19.489713 | E35: 122.38215 | F35: 252.874 | G35: =F35*1.43 -> 361.60982 | H35: =(AVERAGE(D8:D34)/2204.62)*1802.4+(AVERAGE(C8:C34)/2204.62)*3715.4+(AVERAGE(E8:E34)/2204.62)*964.9+(AVERAGE(G8:G34)/2204.62)*272.4 -> 321.95932
A36: =A37-7 -> 36378 | B36: 2.885 | C36: =B36*39.368+15 -> 128.57668 | D36: =C36*0.1616 -> 20.777991 | E36: 116.65427 | F36: 251.221 | G36: =F36*1.43 -> 359.24603 | H36: =(AVERAGE(D9:D35)/2204.62)*1802.4+(AVERAGE(C9:C35)/2204.62)*3715.4+(AVERAGE(E9:E35)/2204.62)*964.9+(AVERAGE(G9:G35)/2204.62)*272.4 -> 321.84025
A37: =A38-7 -> 36385 | B37: 2.76 | C37: =B37*39.368+15 -> 123.65568 | D37: =C37*0.1616 -> 19.982758 | E37: 120.10276 | F37: 243.638 | G37: =F37*1.43 -> 348.40234 | H37: =(AVERAGE(D10:D36)/2204.62)*1802.4+(AVERAGE(C10:C36)/2204.62)*3715.4+(AVERAGE(E10:E36)/2204.62)*964.9+(AVERAGE(G10:G36)/2204.62)*272.4 -> 322.14886
A38: =A39-7 -> 36392 | B38: 2.7725 | C38: =B38*39.368+15 -> 124.14778 | D38: =C38*0.1616 -> 20.062281 | E38: 119.74561 | F38: 238.082 | G38: =F38*1.43 -> 340.45726 | H38: =(AVERAGE(D11:D37)/2204.62)*1802.4+(AVERAGE(C11:C37)/2204.62)*3715.4+(AVERAGE(E11:E37)/2204.62)*964.9+(AVERAGE(G11:G37)/2204.62)*272.4 -> 322.00766
A39: =A40-7 -> 36399 | B39: 2.8025 | C39: =B39*39.368+15 -> 125.32882 | D39: =C39*0.1616 -> 20.253137 | E39: 118.89989 | F39: 243.637 | G39: =F39*1.43 -> 348.40091 | H39: =(AVERAGE(D12:D38)/2204.62)*1802.4+(AVERAGE(C12:C38)/2204.62)*3715.4+(AVERAGE(E12:E38)/2204.62)*964.9+(AVERAGE(G12:G38)/2204.62)*272.4 -> 321.98358
A40: =A41-7 -> 36406 | B40: 2.925 | C40: =B40*39.368+15 -> 130.1514 | D40: =C40*0.1616 -> 21.032466 | E40: 115.60583 | F40: 254.859 | G40: =F40*1.43 -> 364.44837 | H40: =(AVERAGE(D13:D39)/2204.62)*1802.4+(AVERAGE(C13:C39)/2204.62)*3715.4+(AVERAGE(E13:E39)/2204.62)*964.9+(AVERAGE(G13:G39)/2204.62)*272.4 -> 322.07507
A41: =A42-7 -> 36413 | B41: 2.8525 | C41: =B41*39.368+15 -> 127.29722 | D41: =C41*0.1616 -> 20.571231 | E41: 117.52523 | F41: 250.67 | G41: =F41*1.43 -> 358.4581 | H41: =(AVERAGE(D14:D40)/2204.62)*1802.4+(AVERAGE(C14:C40)/2204.62)*3715.4+(AVERAGE(E14:E40)/2204.62)*964.9+(AVERAGE(G14:G40)/2204.62)*272.4 -> 322.78771
A42: =A43-7 -> 36420 | B42: 2.8275 | C42: =B42*39.368+15 -> 126.31302 | D42: =C42*0.1616 -> 20.412184 | E42: 118.2072 | F42: 245.488 | G42: =F42*1.43 -> 351.04784 | H42: =(AVERAGE(D15:D41)/2204.62)*1802.4+(AVERAGE(C15:C41)/2204.62)*3715.4+(AVERAGE(E15:E41)/2204.62)*964.9+(AVERAGE(G15:G41)/2204.62)*272.4 -> 323.11207
A43: =A44-7 -> 36427 | B43: 2.8125 | C43: =B43*39.368+15 -> 125.7225 | D43: =C43*0.1616 -> 20.316756 | E43: 118.62151 | F43: 250.405 | G43: =F43*1.43 -> 358.07915 | H43: =(AVERAGE(D16:D42)/2204.62)*1802.4+(AVERAGE(C16:C42)/2204.62)*3715.4+(AVERAGE(E16:E42)/2204.62)*964.9+(AVERAGE(G16:G42)/2204.62)*272.4 -> 323.05878
A44: =A45-7 -> 36434 | B44: 2.775 | C44: =B44*39.368+15 -> 124.2462 | D44: =C44*0.1616 -> 20.078186 | E44: 119.67452 | F44: 251.684 | G44: =F44*1.43 -> 359.90812 | H44: =(AVERAGE(D17:D43)/2204.62)*1802.4+(AVERAGE(C17:C43)/2204.62)*3715.4+(AVERAGE(E17:E43)/2204.62)*964.9+(AVERAGE(G17:G43)/2204.62)*272.4 -> 322.87072
... A646: =A647-7 -> 40648 | B646: 6.778 | C646: =B646*39.368+15 -> 281.8363 | D646: =C646*0.1616 -> 45.544747 | E646: 260 | F646: 416.99 | G646: =F646*1.43 -> 596.2957 | H646: =(AVERAGE(D619:D645)/2204.62)*1802.4+(AVERAGE(C619:C645)/2204.62)*3715.4+(AVERAGE(E619:E645)/2204.62)*964.9+(AVERAGE(G619:G645)/2204.62)*272.4 -> 591.67473
A647: 40655 | B647: 6.6875 | C647: =B647*39.368+15 -> 278.2735 | D647: =C647*0.1616 -> 44.968998 | E647: 260 | F647: 416.99 | G647: =F647*1.43 -> 596.2957 | H647: =(AVERAGE(D620:D646)/2204.62)*1802.4+(AVERAGE(C620:C646)/2204.62)*3715.4+(AVERAGE(E620:E646)/2204.62)*964.9+(AVERAGE(G620:G646)/2204.62)*272.4 -> 598.39156
A648: =A647+7 -> 40662 | B648: 6.8675 | C648: =B648*39.368+15 -> 285.35974 | D648: =C648*0.1616 -> 46.114134 | E648: 212 | F648: 384.27 | G648: =F648*1.43 -> 549.5061 | H648: =(AVERAGE(D621:D647)/2204.62)*1802.4+(AVERAGE(C621:C647)/2204.62)*3715.4+(AVERAGE(E621:E647)/2204.62)*964.9+(AVERAGE(G621:G647)/2204.62)*272.4 -> 604.52511
A649: =A648+7 -> 40669 | B649: 6.56 | C649: =B649*39.368+15 -> 273.25408 | D649: =C649*0.1616 -> 44.157859 | E649: 230 | F649: 380.575 | G649: =F649*1.43 -> 544.22225 | H649: =(AVERAGE(D622:D648)/2204.62)*1802.4+(AVERAGE(C622:C648)/2204.62)*3715.4+(AVERAGE(E622:E648)/2204.62)*964.9+(AVERAGE(G622:G648)/2204.62)*272.4 -> 609.47932
A650: =A649+7 -> 40676 | B650: 6.414 | C650: =B650*39.368+15 -> 267.50635 | D650: =C650*0.1616 -> 43.229026 | E650: 222.5 | F650: 377.99 | G650: =F650*1.43 -> 540.5257 | H650: =(AVERAGE(D623:D649)/2204.62)*1802.4+(AVERAGE(C623:C649)/2204.62)*3715.4+(AVERAGE(E623:E649)/2204.62)*964.9+(AVERAGE(G623:G649)/2204.62)*272.4 -> 613.75823
A651: =A650+7 -> 40683 | B651: 6.992 | C651: =B651*39.368+15 -> 290.26106 | D651: =C651*0.1616 -> 46.906187 | E651: 222.5 | F651: 400.255 | G651: =F651*1.43 -> 572.36465 | H651: =(AVERAGE(D624:D650)/2204.62)*1802.4+(AVERAGE(C624:C650)/2204.62)*3715.4+(AVERAGE(E624:E650)/2204.62)*964.9+(AVERAGE(G624:G650)/2204.62)*272.4 -> 617.97091
A652: =A651+7 -> 40690 | B652: 7.272 | C652: =B652*39.368+15 -> 301.2841 | D652: =C652*0.1616 -> 48.68751 | E652: 210 | F652: 396.95 | G652: =F652*1.43 -> 567.6385 | H652: =(AVERAGE(D625:D651)/2204.62)*1802.4+(AVERAGE(C625:C651)/2204.62)*3715.4+(AVERAGE(E625:E651)/2204.62)*964.9+(AVERAGE(G625:G651)/2204.62)*272.4 -> 624.5718
A653: =A652+7 -> 40697 | B653: 7.5475 | C653: =B653*39.368+15 -> 312.12998 | D653: =C653*0.1616 -> 50.440205 | E653: 210 | F653: 416.02 | G653: =F653*1.43 -> 594.9086 | H653: =(AVERAGE(D626:D652)/2204.62)*1802.4+(AVERAGE(C626:C652)/2204.62)*3715.4+(AVERAGE(E626:E652)/2204.62)*964.9+(AVERAGE(G626:G652)/2204.62)*272.4 -> 631.29421
A654: =A653+7 -> 40704 | B654: 7.726 | C654: =B654*39.368+15 -> 319.15717 | D654: =C654*0.1616 -> 51.575798 | E654: 215 | F654: 423.625 | G654: =F654*1.43 -> 605.78375 | H654: =(AVERAGE(D627:D653)/2204.62)*1802.4+(AVERAGE(C627:C653)/2204.62)*3715.4+(AVERAGE(E627:E653)/2204.62)*964.9+(AVERAGE(G627:G653)/2204.62)*272.4 -> 638.29921
A655: =A654+7 -> 40711 | B655: 7.484 | C655: =B655*39.368+15 -> 309.63011 | D655: =C655*0.1616 -> 50.036226 | E655: 215 | F655: 402.9 | G655: =F655*1.43 -> 576.147 | H655: =(AVERAGE(D628:D654)/2204.62)*1802.4+(AVERAGE(C628:C654)/2204.62)*3715.4+(AVERAGE(E628:E654)/2204.62)*964.9+(AVERAGE(G628:G654)/2204.62)*272.4 -> 645.59003
A656: =A655+7 -> 40718 | B656: 7.176 | C656: =B656*39.368+15 -> 297.50477 | D656: =C656*0.1616 -> 48.076771 | E656: 220 | F656: 398.385 | G656: =F656*1.43 -> 569.69055 | H656: =(AVERAGE(D629:D655)/2204.62)*1802.4+(AVERAGE(C629:C655)/2204.62)*3715.4+(AVERAGE(E629:E655)/2204.62)*964.9+(AVERAGE(G629:G655)/2204.62)*272.4 -> 651.64378
A657: =A656+7 -> 40725 | B657: 6.946 | C657: =B657*39.368+15 -> 288.45013 | D657: =C657*0.1616 -> 46.613541 | E657: 217.5 | F657: 396.73 | G657: =F657*1.43 -> 567.3239 | H657: =(AVERAGE(D630:D656)/2204.62)*1802.4+(AVERAGE(C630:C656)/2204.62)*3715.4+(AVERAGE(E630:E656)/2204.62)*964.9+(AVERAGE(G630:G656)/2204.62)*272.4 -> 656.34694
A658: =A657+7 -> 40732 | B658: 6.772 | C658: =B658*39.368+15 -> 281.6001 | D658: =C658*0.1616 -> 45.506576 | E658: 217.5 | F658: 402.35 | G658: =F658*1.43 -> 575.3605 | H658: =(AVERAGE(D631:D657)/2204.62)*1802.4+(AVERAGE(C631:C657)/2204.62)*3715.4+(AVERAGE(E631:E657)/2204.62)*964.9+(AVERAGE(G631:G657)/2204.62)*272.4 -> 659.90708
A659: =A658+7 -> 40739 | B659: 7.418 | C659: =B659*39.368+15 -> 307.03182 | D659: =C659*0.1616 -> 49.616343 | E659: 217.5 | F659: 413.7 | G659: =F659*1.43 -> 591.591 | H659: =(AVERAGE(D632:D658)/2204.62)*1802.4+(AVERAGE(C632:C658)/2204.62)*3715.4+(AVERAGE(E632:E658)/2204.62)*964.9+(AVERAGE(G632:G658)/2204.62)*272.4 -> 663.04292
... A1152: =A1151+7 -> 44190 | B1152: 5.77 | C1152: =B1152*39.368+15 -> 242.15336 | D1152: =C1152*0.1616 -> 39.131983 | E1152: 312.5 | F1152: 613.78 | G1152: =F1152*1.43 -> 877.7054 | H1152: =(AVERAGE(D1125:D1151)/2204.62)*1802.4+(AVERAGE(C1125:C1151)/2204.62)*3715.4+(AVERAGE(E1125:E1151)/2204.62)*964.9+(AVERAGE(G1125:G1151)/2204.62)*272.4 -> 594.59659
A1153: =+A1152+7 -> 44197
A1154: =+A1153+7 -> 44204 | B1154: 6.288 | C1154: 262.54598 | D1154: 42.427431 | E1154: 315 | F1154: 638.91 | G1154: 913.6413 | H1154: 599.99969
A1155: =+A1154+7 -> 44211 | B1155: 6.592 | C1155: 274.51386 | D1155: 44.361439 | E1155: 330 | F1155: 670.44 | G1155: 958.7292 | H1155: 602.47352
A1156: =+A1155+7 -> 44218 | B1156: 6.62 | C1156: 275.61616 | D1156: 44.539571 | E1156: 335 | F1156: 630.09 | G1156: 901.0287 | H1156: 609.77277
A1157: =+A1156+7 -> 44225 | B1157: 6.726 | C1157: 279.78917 | D1157: 45.21393 | E1157: 350 | F1157: 640.45 | G1157: 915.8435 | H1157: 623.40885
A1158: =+A1157+7 -> 44232 | B1158: 6.914 | C1158: 287.19035 | D1158: 46.409961 | E1158: 360 | F1158: 639.9 | G1158: 915.057 | H1158: 632.37175
A1159: =+A1158+7 -> 44239 | B1159: 6.92 | C1159: 287.42656 | D1159: 46.448132 | E1159: 360 | F1159: 636.26 | G1159: 909.8518 | H1159: 641.82108
A1160: =+A1159+7 -> 44246 | B1160: 5.5425 | C1160: 233.19714 | D1160: 37.684658 | E1160: 365 | F1160: 627.56 | G1160: 897.4108 | H1160: 651.30405
A1161: =+A1160+7 -> 44253 | B1161: 6.964 | C1161: 289.15875 | D1161: 46.728054 | E1161: 360 | F1161: 620.83 | G1161: 887.7869 | H1161: 657.29558
A1162: =+A1161+7 -> 44260 | B1162: 6.794 | C1162: 282.46619 | D1162: 45.646537 | E1162: 355 | F1162: 615.32 | G1162: 879.9076 | H1162: 666.59007
A1163: =+A1162+7 -> 44267 | B1163: 6.81 | C1163: 283.09608 | D1163: 45.748327 | E1163: 345 | F1163: 590.52 | G1163: 844.4436 | H1163: 674.91011
A1164: =+A1163+7 -> 44274 | B1164: 6.934 | C1164: 287.97771 | D1164: 46.537198 | E1164: 345 | F1164: 592.94 | G1164: 847.9042 | H1164: 682.29457
A1165: =+A1164+7 -> 44281 | B1165: 6.906 | C1165: 286.87541 | D1165: 46.359066 | E1165: 325 | F1165: 583.13 | G1165: 833.8759 | H1165: 689.59539
... A1205: =+A1204+7 -> 44561 | B1205: 7.31 | C1205: 302.78008 | D1205: 48.929261 | E1205: 250 | F1205: 601.98 | G1205: 860.8314 | H1205: 764.93281
A1206: =+A1205+7 -> 44568 | B1206: =_xlfn.IFNA([2]Cor!$W5,"") -> 7.45 | C1206: =IFERROR(B1206*39.368+15,"") -> 308.2916 | D1206: =IFERROR(C1206*0.1616,"") -> 49.819923 | E1206: =_xlfn.IFNA([2]DDG!$F3,"") -> 297.5 | F1206: =_xlfn.IFNA([2]Soymeal!$F3,"") -> 628.33 | G1206: =IFERROR(F1206*1.43,"") -> 898.5119 | H1206: =_xlfn.IFNA((AVERAGE(D1179:D1205)/2204.62)*1802.4+(AVERAGE(C1179:C1205)/2204.62)*3715.4+(AVERAGE(E1179:E1205)/2204.62)*964.9+(AVERAGE(G1179:G1205)/2204.62)*272.4,"") -> 763.69766
A1207: =+A1206+7 -> 44575 | B1207: =_xlfn.IFNA([2]Cor!$W6,"") -> 7.25 | C1207: =IFERROR(B1207*39.368+15,"") -> 300.418 | D1207: =IFERROR(C1207*0.1616,"") -> 48.547549 | E1207: =_xlfn.IFNA([2]DDG!$F4,"") -> 297.5 | F1207: =_xlfn.IFNA([2]Soymeal!$F4,"") -> 603.64 | G1207: =IFERROR(F1207*1.43,"") -> 863.2052 | H1207: =_xlfn.IFNA((AVERAGE(D1180:D1206)/2204.62)*1802.4+(AVERAGE(C1180:C1206)/2204.62)*3715.4+(AVERAGE(E1180:E1206)/2204.62)*964.9+(AVERAGE(G1180:G1206)/2204.62)*272.4,"") -> 761.65518
A1208: =+A1207+7 -> 44582 | B1208: =_xlfn.IFNA([2]Cor!$W7,"") -> 7.41 | C1208: =IFERROR(B1208*39.368+15,"") -> 306.71688 | D1208: =IFERROR(C1208*0.1616,"") -> 49.565448 | E1208: =_xlfn.IFNA([2]DDG!$F5,"") -> 305 | F1208: =_xlfn.IFNA([2]Soymeal!$F5,"") -> 589.42 | G1208: =IFERROR(F1208*1.43,"") -> 842.8706 | H1208: =_xlfn.IFNA((AVERAGE(D1181:D1207)/2204.62)*1802.4+(AVERAGE(C1181:C1207)/2204.62)*3715.4+(AVERAGE(E1181:E1207)/2204.62)*964.9+(AVERAGE(G1181:G1207)/2204.62)*272.4,"") -> 760.85208
A1209: =+A1208+7 -> 44589 | B1209: =_xlfn.IFNA([2]Cor!$W8,"") -> 7.62 | C1209: =IFERROR(B1209*39.368+15,"") -> 314.98416 | D1209: =IFERROR(C1209*0.1616,"") -> 50.90144 | E1209: =_xlfn.IFNA([2]DDG!$F6,"") -> 315 | F1209: =_xlfn.IFNA([2]Soymeal!$F6,"") -> 618.63 | G1209: =IFERROR(F1209*1.43,"") -> 884.6409 | H1209: =_xlfn.IFNA((AVERAGE(D1182:D1208)/2204.62)*1802.4+(AVERAGE(C1182:C1208)/2204.62)*3715.4+(AVERAGE(E1182:E1208)/2204.62)*964.9+(AVERAGE(G1182:G1208)/2204.62)*272.4,"") -> 759.72037
A1210: =+A1209+7 -> 44596 | B1210: =_xlfn.IFNA([2]Cor!$W9,"") -> 7.49 | C1210: =IFERROR(B1210*39.368+15,"") -> 309.86632 | D1210: =IFERROR(C1210*0.1616,"") -> 50.074397 | E1210: =_xlfn.IFNA([2]DDG!$F7,"") -> 315 | F1210: =_xlfn.IFNA([2]Soymeal!$F7,"") -> 654.67 | G1210: =IFERROR(F1210*1.43,"") -> 936.1781 | H1210: =_xlfn.IFNA((AVERAGE(D1183:D1209)/2204.62)*1802.4+(AVERAGE(C1183:C1209)/2204.62)*3715.4+(AVERAGE(E1183:E1209)/2204.62)*964.9+(AVERAGE(G1183:G1209)/2204.62)*272.4,"") -> 759.59339
A1211: =+A1210+7 -> 44603 | B1211: =_xlfn.IFNA([2]Cor!$W10,"") -> 7.8 | C1211: =IFERROR(B1211*39.368+15,"") -> 322.0704 | D1211: =IFERROR(C1211*0.1616,"") -> 52.046577 | E1211: =_xlfn.IFNA([2]DDG!$F8,"") -> 335 | F1211: =_xlfn.IFNA([2]Soymeal!$F8,"") -> 688.52 | G1211: =IFERROR(F1211*1.43,"") -> 984.5836 | H1211: =_xlfn.IFNA((AVERAGE(D1184:D1210)/2204.62)*1802.4+(AVERAGE(C1184:C1210)/2204.62)*3715.4+(AVERAGE(E1184:E1210)/2204.62)*964.9+(AVERAGE(G1184:G1210)/2204.62)*272.4,"") -> 759.41796
A1212: =+A1211+7 -> 44610 | B1212: =_xlfn.IFNA([2]Cor!$W11,"") -> 7.84 | C1212: =IFERROR(B1212*39.368+15,"") -> 323.64512 | D1212: =IFERROR(C1212*0.1616,"") -> 52.301051 | E1212: =_xlfn.IFNA([2]DDG!$F9,"") -> 352.5 | F1212: =_xlfn.IFNA([2]Soymeal!$F9,"") -> 674.52 | G1212: =IFERROR(F1212*1.43,"") -> 964.5636 | H1212: =_xlfn.IFNA((AVERAGE(D1185:D1211)/2204.62)*1802.4+(AVERAGE(C1185:C1211)/2204.62)*3715.4+(AVERAGE(E1185:E1211)/2204.62)*964.9+(AVERAGE(G1185:G1211)/2204.62)*272.4,"") -> 760.34856
A1213: =+A1212+7 -> 44617 | B1213: =_xlfn.IFNA([2]Cor!$W12,"") -> 7.88 | C1213: =IFERROR(B1213*39.368+15,"") -> 325.21984 | D1213: =IFERROR(C1213*0.1616,"") -> 52.555526 | E1213: =_xlfn.IFNA([2]DDG!$F10,"") -> 355 | F1213: =_xlfn.IFNA([2]Soymeal!$F10,"") -> 683.78 | G1213: =IFERROR(F1213*1.43,"") -> 977.8054 | H1213: =_xlfn.IFNA((AVERAGE(D1186:D1212)/2204.62)*1802.4+(AVERAGE(C1186:C1212)/2204.62)*3715.4+(AVERAGE(E1186:E1212)/2204.62)*964.9+(AVERAGE(G1186:G1212)/2204.62)*272.4,"") -> 760.80118
A1214: =+A1213+7 -> 44624 | B1214: =_xlfn.IFNA([2]Cor!$W13,"") -> 8.78 | C1214: =IFERROR(B1214*39.368+15,"") -> 360.65104 | D1214: =IFERROR(C1214*0.1616,"") -> 58.281208 | E1214: =_xlfn.IFNA([2]DDG!$F11,"") -> 360 | F1214: =_xlfn.IFNA([2]Soymeal!$F11,"") -> 689.4 | G1214: =IFERROR(F1214*1.43,"") -> 985.842 | H1214: =_xlfn.IFNA((AVERAGE(D1187:D1213)/2204.62)*1802.4+(AVERAGE(C1187:C1213)/2204.62)*3715.4+(AVERAGE(E1187:E1213)/2204.62)*964.9+(AVERAGE(G1187:G1213)/2204.62)*272.4,"") -> 762.04704
A1215: =+A1214+7 -> 44631 | B1215: =_xlfn.IFNA([2]Cor!$W14,"") -> 8.8 | C1215: =IFERROR(B1215*39.368+15,"") -> 361.4384 | D1215: =IFERROR(C1215*0.1616,"") -> 58.408445 | E1215: =_xlfn.IFNA([2]DDG!$F12,"") -> 360 | F1215: =_xlfn.IFNA([2]Soymeal!$F12,"") -> 702.29 | G1215: =IFERROR(F1215*1.43,"") -> 1004.2747 | H1215: =_xlfn.IFNA((AVERAGE(D1188:D1214)/2204.62)*1802.4+(AVERAGE(C1188:C1214)/2204.62)*3715.4+(AVERAGE(E1188:E1214)/2204.62)*964.9+(AVERAGE(G1188:G1214)/2204.62)*272.4,"") -> 765.11395
A1216: =+A1215+7 -> 44638 | B1216: =_xlfn.IFNA([2]Cor!$W15,"") -> 8.63 | C1216: =IFERROR(B1216*39.368+15,"") -> 354.74584 | D1216: =IFERROR(C1216*0.1616,"") -> 57.326928 | E1216: =_xlfn.IFNA([2]DDG!$F13,"") -> 357.5 | F1216: =_xlfn.IFNA([2]Soymeal!$F13,"") -> 720.92 | G1216: =IFERROR(F1216*1.43,"") -> 1030.9156 | H1216: =_xlfn.IFNA((AVERAGE(D1189:D1215)/2204.62)*1802.4+(AVERAGE(C1189:C1215)/2204.62)*3715.4+(AVERAGE(E1189:E1215)/2204.62)*964.9+(AVERAGE(G1189:G1215)/2204.62)*272.4,"") -> 770.15186
A1217: =+A1216+7 -> 44645 | B1217: =_xlfn.IFNA([2]Cor!$W16,"") -> 8.84 | C1217: =IFERROR(B1217*39.368+15,"") -> 363.01312 | D1217: =IFERROR(C1217*0.1616,"") -> 58.66292 | E1217: =_xlfn.IFNA([2]DDG!$F14,"") -> 367.5 | F1217: =_xlfn.IFNA([2]Soymeal!$F14,"") -> 735.14 | G1217: =IFERROR(F1217*1.43,"") -> 1051.2502 | H1217: =_xlfn.IFNA((AVERAGE(D1190:D1216)/2204.62)*1802.4+(AVERAGE(C1190:C1216)/2204.62)*3715.4+(AVERAGE(E1190:E1216)/2204.62)*964.9+(AVERAGE(G1190:G1216)/2204.62)*272.4,"") -> 779.00883
... A1257: =+A1256+7 -> 44925 | B1257: =_xlfn.IFNA([2]Cor!$W56,"") -> 8.26 | C1257: =IFERROR(B1257*39.368+15,"") -> 340.17968 | D1257: =IFERROR(C1257*0.1616,"") -> 54.973036 | E1257: =_xlfn.IFNA([2]DDG!$F54,"") -> 360 | F1257: =_xlfn.IFNA([2]Soymeal!$F54,"") -> 749.03 | G1257: =IFERROR(F1257*1.43,"") -> 1071.1129 | H1257: =_xlfn.IFNA((AVERAGE(D1230:D1256)/2204.62)*1802.4+(AVERAGE(C1230:C1256)/2204.62)*3715.4+(AVERAGE(E1230:E1256)/2204.62)*964.9+(AVERAGE(G1230:G1256)/2204.62)*272.4,"") -> 889.82531
A1258: =+A1257+7 -> 44932 | B1258: =_xlfn.IFNA([3]Cor!$W5,"") -> 7.97 | C1258: =IFERROR(B1258*39.368+15,"") -> 328.76296 | D1258: =IFERROR(C1258*0.1616,"") -> 53.128094 | E1258: =_xlfn.IFNA([3]DDG!$F3,"") -> 360 | F1258: =_xlfn.IFNA([3]Soymeal!$F3,"") -> 735.92 | G1258: =IFERROR(F1258*1.43,"") -> 1052.3656 | H1258: =_xlfn.IFNA((AVERAGE(D1231:D1257)/2204.62)*1802.4+(AVERAGE(C1231:C1257)/2204.62)*3715.4+(AVERAGE(E1231:E1257)/2204.62)*964.9+(AVERAGE(G1231:G1257)/2204.62)*272.4,"") -> 888.37589
A1259: =+A1258+7 -> 44939 | B1259: =_xlfn.IFNA([3]Cor!$W6,"") -> 8.14 | C1259: =IFERROR(B1259*39.368+15,"") -> 335.45552 | D1259: =IFERROR(C1259*0.1616,"") -> 54.209612 | E1259: =_xlfn.IFNA([3]DDG!$F4,"") -> 370 | F1259: =_xlfn.IFNA([3]Soymeal!$F4,"") -> 739.99 | G1259: =IFERROR(F1259*1.43,"") -> 1058.1857 | H1259: =_xlfn.IFNA((AVERAGE(D1232:D1258)/2204.62)*1802.4+(AVERAGE(C1232:C1258)/2204.62)*3715.4+(AVERAGE(E1232:E1258)/2204.62)*964.9+(AVERAGE(G1232:G1258)/2204.62)*272.4,"") -> 887.72925
A1260: =+A1259+7 -> 44946 | B1260: =_xlfn.IFNA([3]Cor!$W7,"") -> 8.18 | C1260: =IFERROR(B1260*39.368+15,"") -> 337.03024 | D1260: =IFERROR(C1260*0.1616,"") -> 54.464087 | E1260: =_xlfn.IFNA([3]DDG!$F5,"") -> 370 | F1260: =_xlfn.IFNA([3]Soymeal!$F5,"") -> 737.13 | G1260: =IFERROR(F1260*1.43,"") -> 1054.0959 | H1260: =_xlfn.IFNA((AVERAGE(D1233:D1259)/2204.62)*1802.4+(AVERAGE(C1233:C1259)/2204.62)*3715.4+(AVERAGE(E1233:E1259)/2204.62)*964.9+(AVERAGE(G1233:G1259)/2204.62)*272.4,"") -> 887.60559
A1261: =+A1260+7 -> 44953 | B1261: =_xlfn.IFNA([3]Cor!$W8,"") -> 8.21 | C1261: =IFERROR(B1261*39.368+15,"") -> 338.21128 | D1261: =IFERROR(C1261*0.1616,"") -> 54.654943 | E1261: =_xlfn.IFNA([3]DDG!$F6,"") -> 370 | F1261: =_xlfn.IFNA([3]Soymeal!$F6,"") -> 740.21 | G1261: =IFERROR(F1261*1.43,"") -> 1058.5003 | H1261: =_xlfn.IFNA((AVERAGE(D1234:D1260)/2204.62)*1802.4+(AVERAGE(C1234:C1260)/2204.62)*3715.4+(AVERAGE(E1234:E1260)/2204.62)*964.9+(AVERAGE(G1234:G1260)/2204.62)*272.4,"") -> 888.81449
A1262: =+A1261+7 -> 44960 | B1262: =_xlfn.IFNA([3]Cor!$W9,"") -> 8.15 | C1262: =IFERROR(B1262*39.368+15,"") -> 335.8492 | D1262: =IFERROR(C1262*0.1616,"") -> 54.273231 | E1262: =_xlfn.IFNA([3]DDG!$F7,"") -> 360 | F1262: =_xlfn.IFNA([3]Soymeal!$F7,"") -> 778.8 | G1262: =IFERROR(F1262*1.43,"") -> 1113.684 | H1262: =_xlfn.IFNA((AVERAGE(D1235:D1261)/2204.62)*1802.4+(AVERAGE(C1235:C1261)/2204.62)*3715.4+(AVERAGE(E1235:E1261)/2204.62)*964.9+(AVERAGE(G1235:G1261)/2204.62)*272.4,"") -> 891.60905
A1263: =+A1262+7 -> 44967 | B1263: =_xlfn.IFNA([3]Cor!$W10,"") -> 8.17 | C1263: =IFERROR(B1263*39.368+15,"") -> 336.63656 | D1263: =IFERROR(C1263*0.1616,"") -> 54.400468 | E1263: =_xlfn.IFNA([3]DDG!$F8,"") -> 365 | F1263: =_xlfn.IFNA([3]Soymeal!$F8,"") -> 779.79 | G1263: =IFERROR(F1263*1.43,"") -> 1115.0997 | H1263: =_xlfn.IFNA((AVERAGE(D1236:D1262)/2204.62)*1802.4+(AVERAGE(C1236:C1262)/2204.62)*3715.4+(AVERAGE(E1236:E1262)/2204.62)*964.9+(AVERAGE(G1236:G1262)/2204.62)*272.4,"") -> 893.07038
A1264: =+A1263+7 -> 44974 | B1264: =_xlfn.IFNA([3]Cor!$W11,"") -> 8.14 | C1264: =IFERROR(B1264*39.368+15,"") -> 335.45552 | D1264: =IFERROR(C1264*0.1616,"") -> 54.209612 | E1264: =_xlfn.IFNA([3]DDG!$F9,"") -> 375 | F1264: =_xlfn.IFNA([3]Soymeal!$F9,"") -> 770.64 | G1264: =IFERROR(F1264*1.43,"") -> 1102.0152 | H1264: =_xlfn.IFNA((AVERAGE(D1237:D1263)/2204.62)*1802.4+(AVERAGE(C1237:C1263)/2204.62)*3715.4+(AVERAGE(E1237:E1263)/2204.62)*964.9+(AVERAGE(G1237:G1263)/2204.62)*272.4,"") -> 894.87084
A1265: =+A1264+7 -> 44981 | B1265: =_xlfn.IFNA([3]Cor!$W12,"") -> 7.85 | C1265: =IFERROR(B1265*39.368+15,"") -> 324.0388 | D1265: =IFERROR(C1265*0.1616,"") -> 52.36467 | E1265: =_xlfn.IFNA([3]DDG!$F10,"") -> 375 | F1265: =_xlfn.IFNA([3]Soymeal!$F10,"") -> 779.46 | G1265: =IFERROR(F1265*1.43,"") -> 1114.6278 | H1265: =_xlfn.IFNA((AVERAGE(D1238:D1264)/2204.62)*1802.4+(AVERAGE(C1238:C1264)/2204.62)*3715.4+(AVERAGE(E1238:E1264)/2204.62)*964.9+(AVERAGE(G1238:G1264)/2204.62)*272.4,"") -> 896.09939
A1266: =+A1265+7 -> 44988 | B1266: =_xlfn.IFNA([3]Cor!$W13,"") -> 7.75 | C1266: =IFERROR(B1266*39.368+15,"") -> 320.102 | D1266: =IFERROR(C1266*0.1616,"") -> 51.728483 | E1266: =_xlfn.IFNA([3]DDG!$F11,"") -> 365 | F1266: =_xlfn.IFNA([3]Soymeal!$F11,"") -> 790.7 | G1266: =IFERROR(F1266*1.43,"") -> 1130.701 | H1266: =_xlfn.IFNA((AVERAGE(D1239:D1265)/2204.62)*1802.4+(AVERAGE(C1239:C1265)/2204.62)*3715.4+(AVERAGE(E1239:E1265)/2204.62)*964.9+(AVERAGE(G1239:G1265)/2204.62)*272.4,"") -> 897.19615
A1267: =+A1266+7 -> 44995 | B1267: =_xlfn.IFNA([3]Cor!$W14,"") -> 7.56 | C1267: =IFERROR(B1267*39.368+15,"") -> 312.62208 | D1267: =IFERROR(C1267*0.1616,"") -> 50.519728 | E1267: =_xlfn.IFNA([3]DDG!$F12,"") -> 360 | F1267: =_xlfn.IFNA([3]Soymeal!$F12,"") -> 812.31 | G1267: =IFERROR(F1267*1.43,"") -> 1161.6033 | H1267: =_xlfn.IFNA((AVERAGE(D1240:D1266)/2204.62)*1802.4+(AVERAGE(C1240:C1266)/2204.62)*3715.4+(AVERAGE(E1240:E1266)/2204.62)*964.9+(AVERAGE(G1240:G1266)/2204.62)*272.4,"") -> 896.90365
A1268: =+A1267+7 -> 45002 | B1268: =_xlfn.IFNA([3]Cor!$W15,"") -> 7.69 | C1268: =IFERROR(B1268*39.368+15,"") -> 317.73992 | D1268: =IFERROR(C1268*0.1616,"") -> 51.346771 | E1268: =_xlfn.IFNA([3]DDG!$F13,"") -> 360 | F1268: =_xlfn.IFNA([3]Soymeal!$F13,"") -> 772.73 | G1268: =IFERROR(F1268*1.43,"") -> 1105.0039 | H1268: =_xlfn.IFNA((AVERAGE(D1241:D1267)/2204.62)*1802.4+(AVERAGE(C1241:C1267)/2204.62)*3715.4+(AVERAGE(E1241:E1267)/2204.62)*964.9+(AVERAGE(G1241:G1267)/2204.62)*272.4,"") -> 896.36113
A1269: =+A1268+7 -> 45009 | B1269: =_xlfn.IFNA([3]Cor!$W16,"") -> 7.74 | C1269: =IFERROR(B1269*39.368+15,"") -> 319.70832 | D1269: =IFERROR(C1269*0.1616,"") -> 51.664865 | E1269: =_xlfn.IFNA([3]DDG!$F14,"") -> 370 | F1269: =_xlfn.IFNA([3]Soymeal!$F14,"") -> 740.88 | G1269: =IFERROR(F1269*1.43,"") -> 1059.4584 | H1269: =_xlfn.IFNA((AVERAGE(D1242:D1268)/2204.62)*1802.4+(AVERAGE(C1242:C1268)/2204.62)*3715.4+(AVERAGE(E1242:E1268)/2204.62)*964.9+(AVERAGE(G1242:G1268)/2204.62)*272.4,"") -> 895.62548
... A1309: =+A1308+7 -> 45289 | B1309: =_xlfn.IFNA([3]Cor!$W56,"") -> 5.37 | C1309: =IFERROR(B1309*39.368+15,"") -> 226.40616 | D1309: =IFERROR(C1309*0.1616,"") -> 36.587235 | E1309: =_xlfn.IFNA([3]DDG!$F54,"") -> 280 | F1309: =_xlfn.IFNA([3]Soymeal!$F54,"") -> 647.07 | G1309: =IFERROR(F1309*1.43,"") -> 925.3101 | H1309: =_xlfn.IFNA((AVERAGE(D1282:D1308)/2204.62)*1802.4+(AVERAGE(C1282:C1308)/2204.62)*3715.4+(AVERAGE(E1282:E1308)/2204.62)*964.9+(AVERAGE(G1282:G1308)/2204.62)*272.4,"") -> 718.63934
A1310: =+A1309+7 -> 45296 | B1310: =[4]Cor!W5 -> 5.29 | C1310: =IFERROR(B1310*39.368+15,"") -> 223.25672 | D1310: =IFERROR(C1310*0.1616,"") -> 36.078286 | E1310: =[4]DDG!F3 -> 280 | F1310: =[4]Soymeal!$F3 -> 604.52 | G1310: =IFERROR(F1310*1.43,"") -> 864.4636 | H1310: =_xlfn.IFNA((AVERAGE(D1283:D1309)/2204.62)*1802.4+(AVERAGE(C1283:C1309)/2204.62)*3715.4+(AVERAGE(E1283:E1309)/2204.62)*964.9+(AVERAGE(G1283:G1309)/2204.62)*272.4,"") -> 713.27234
A1311: =+A1310+7 -> 45303 | B1311: =[4]Cor!W6 -> 5.17 | C1311: =IFERROR(B1311*39.368+15,"") -> 218.53256 | D1311: =IFERROR(C1311*0.1616,"") -> 35.314862 | E1311: =[4]DDG!F4 -> 280 | F1311: =[4]Soymeal!$F4 -> 582.14 | G1311: =IFERROR(F1311*1.43,"") -> 832.4602 | H1311: =_xlfn.IFNA((AVERAGE(D1284:D1310)/2204.62)*1802.4+(AVERAGE(C1284:C1310)/2204.62)*3715.4+(AVERAGE(E1284:E1310)/2204.62)*964.9+(AVERAGE(G1284:G1310)/2204.62)*272.4,"") -> 710.15024
A1312: =+A1311+7 -> 45310 | B1312: =[4]Cor!W7 -> 5.16 | C1312: =IFERROR(B1312*39.368+15,"") -> 218.13888 | D1312: =IFERROR(C1312*0.1616,"") -> 35.251243 | E1312: =[4]DDG!F5 -> 280 | F1312: =[4]Soymeal!$F5 -> 573.76 | G1312: =IFERROR(F1312*1.43,"") -> 820.4768 | H1312: =_xlfn.IFNA((AVERAGE(D1285:D1311)/2204.62)*1802.4+(AVERAGE(C1285:C1311)/2204.62)*3715.4+(AVERAGE(E1285:E1311)/2204.62)*964.9+(AVERAGE(G1285:G1311)/2204.62)*272.4,"") -> 706.6534
A1313: =+A1312+7 -> 45317 | B1313: =[4]Cor!W8 -> 5.16 | C1313: =IFERROR(B1313*39.368+15,"") -> 218.13888 | D1313: =IFERROR(C1313*0.1616,"") -> 35.251243 | E1313: =[4]DDG!F6 -> 275 | F1313: =[4]Soymeal!$F6 -> 568.8 | G1313: =IFERROR(F1313*1.43,"") -> 813.384 | H1313: =_xlfn.IFNA((AVERAGE(D1286:D1312)/2204.62)*1802.4+(AVERAGE(C1286:C1312)/2204.62)*3715.4+(AVERAGE(E1286:E1312)/2204.62)*964.9+(AVERAGE(G1286:G1312)/2204.62)*272.4,"") -> 702.54063
A1314: =+A1313+7 -> 45324 | B1314: =[4]Cor!W9 -> 5.13 | C1314: =IFERROR(B1314*39.368+15,"") -> 216.95784 | D1314: =IFERROR(C1314*0.1616,"") -> 35.060387 | E1314: =[4]DDG!F7 -> 275 | F1314: =[4]Soymeal!$F7 -> 578.5 | G1314: =IFERROR(F1314*1.43,"") -> 827.255 | H1314: =_xlfn.IFNA((AVERAGE(D1287:D1313)/2204.62)*1802.4+(AVERAGE(C1287:C1313)/2204.62)*3715.4+(AVERAGE(E1287:E1313)/2204.62)*964.9+(AVERAGE(G1287:G1313)/2204.62)*272.4,"") -> 697.41087
...

Sheet Fed Steer Margin
B1: Ontario - 1500lb steers
B2: Ontario 900lb Stocker Steer Price | C2: Feed Cost | D2: Fed Steer Costs | E2: Fed Steer Revenue | F2: Fed Steer Margin
B3: BFO | C3: RMP
A4: Week Ending | B4: $ per 900lb steer | C4: $ per 1500lb steer | D4: $ per 1500lb steer | E4: $ per 1500lb steer | F4: $ per 1500lb steer
A5: =A6-7 -> 36350 | B5: ='[5]Fed Steer Margin'!B5 -> 824.04 | C5: ='[5]Fed Steer Margin'!C5 -> 299.93225 | D5: ='[5]Fed Steer Margin'!D5 -> 1123.9723 | E5: ='[5]Fed Steer Margin'!E5 -> 1335.45 | F5: ='[5]Fed Steer Margin'!F5 -> 211.47775
A6: =A7-7 -> 36357 | B6: ='[5]Fed Steer Margin'!B6 -> 885.6 | C6: ='[5]Fed Steer Margin'!C6 -> 322.84415 | D6: ='[5]Fed Steer Margin'!D6 -> 1208.4442 | E6: ='[5]Fed Steer Margin'!E6 -> 1313.7 | F6: ='[5]Fed Steer Margin'!F6 -> 105.25585
A7: =A8-7 -> 36364 | B7: ='[5]Fed Steer Margin'!B7 -> 916.92 | C7: ='[5]Fed Steer Margin'!C7 -> 321.98061 | D7: ='[5]Fed Steer Margin'!D7 -> 1238.9006 | E7: ='[5]Fed Steer Margin'!E7 -> 1356.15 | F7: ='[5]Fed Steer Margin'!F7 -> 117.24939
A8: =A9-7 -> 36371 | B8: ='[5]Fed Steer Margin'!B8 -> 892.62 | C8: ='[5]Fed Steer Margin'!C8 -> 321.95932 | D8: ='[5]Fed Steer Margin'!D8 -> 1214.5793 | E8: ='[5]Fed Steer Margin'!E8 -> 1362.9 | F8: ='[5]Fed Steer Margin'!F8 -> 148.32068
A9: =A10-7 -> 36378 | B9: ='[5]Fed Steer Margin'!B9 -> 917.73 | C9: ='[5]Fed Steer Margin'!C9 -> 321.84025 | D9: ='[5]Fed Steer Margin'!D9 -> 1239.5703 | E9: ='[5]Fed Steer Margin'!E9 -> 1358.1 | F9: ='[5]Fed Steer Margin'!F9 -> 118.52975
A10: =A11-7 -> 36385 | B10: ='[5]Fed Steer Margin'!B10 -> 932.13 | C10: ='[5]Fed Steer Margin'!C10 -> 322.14886 | D10: ='[5]Fed Steer Margin'!D10 -> 1254.2789 | E10: ='[5]Fed Steer Margin'!E10 -> 1355.85 | F10: ='[5]Fed Steer Margin'!F10 -> 101.57114
A11: =A12-7 -> 36392 | B11: ='[5]Fed Steer Margin'!B11 -> 902.88 | C11: ='[5]Fed Steer Margin'!C11 -> 322.00766 | D11: ='[5]Fed Steer Margin'!D11 -> 1224.8877 | E11: ='[5]Fed Steer Margin'!E11 -> 1349.85 | F11: ='[5]Fed Steer Margin'!F11 -> 124.96234
A12: =A13-7 -> 36399 | B12: ='[5]Fed Steer Margin'!B12 -> 911.43 | C12: ='[5]Fed Steer Margin'!C12 -> 321.98358 | D12: ='[5]Fed Steer Margin'!D12 -> 1233.4136 | E12: ='[5]Fed Steer Margin'!E12 -> 1348.8 | F12: ='[5]Fed Steer Margin'!F12 -> 115.38642
A13: =A14-7 -> 36406 | B13: ='[5]Fed Steer Margin'!B13 -> 923.22 | C13: ='[5]Fed Steer Margin'!C13 -> 322.07507 | D13: ='[5]Fed Steer Margin'!D13 -> 1245.2951 | E13: ='[5]Fed Steer Margin'!E13 -> 1347.3 | F13: ='[5]Fed Steer Margin'!F13 -> 102.00493
A14: =A15-7 -> 36413 | B14: ='[5]Fed Steer Margin'!B14 -> 932.22 | C14: ='[5]Fed Steer Margin'!C14 -> 322.78771 | D14: ='[5]Fed Steer Margin'!D14 -> 1255.0077 | E14: ='[5]Fed Steer Margin'!E14 -> 1348.8 | F14: ='[5]Fed Steer Margin'!F14 -> 93.792293
A15: =A16-7 -> 36420 | B15: ='[5]Fed Steer Margin'!B15 -> 908.91 | C15: ='[5]Fed Steer Margin'!C15 -> 323.11207 | D15: ='[5]Fed Steer Margin'!D15 -> 1232.0221 | E15: ='[5]Fed Steer Margin'!E15 -> 1349.55 | F15: ='[5]Fed Steer Margin'!F15 -> 117.52793
A16: =A17-7 -> 36427 | B16: ='[5]Fed Steer Margin'!B16 -> 919.71 | C16: ='[5]Fed Steer Margin'!C16 -> 323.05878 | D16: ='[5]Fed Steer Margin'!D16 -> 1242.7688 | E16: ='[5]Fed Steer Margin'!E16 -> 1346.7 | F16: ='[5]Fed Steer Margin'!F16 -> 103.93122
... A619: =A620-7 -> 40648 | B619: ='[5]Fed Steer Margin'!B619 -> 989.55 | C619: ='[5]Fed Steer Margin'!C619 -> 591.67473 | D619: ='[5]Fed Steer Margin'!D619 -> 1581.2247 | E619: ='[5]Fed Steer Margin'!E619 -> 1627.05 | F619: ='[5]Fed Steer Margin'!F619 -> 45.825267
A620: 40655 | B620: ='[5]Fed Steer Margin'!B620 -> 953.55 | C620: ='[5]Fed Steer Margin'!C620 -> 598.39156 | D620: ='[5]Fed Steer Margin'!D620 -> 1551.9416 | E620: ='[5]Fed Steer Margin'!E620 -> 1632.75 | F620: ='[5]Fed Steer Margin'!F620 -> 80.808441
A621: =A620+7 -> 40662 | B621: ='[5]Fed Steer Margin'!B621 -> 954.9 | C621: ='[5]Fed Steer Margin'!C621 -> 604.52511 | D621: ='[5]Fed Steer Margin'!D621 -> 1559.4251 | E621: ='[5]Fed Steer Margin'!E621 -> 1639.2 | F621: ='[5]Fed Steer Margin'!F621 -> 79.774892
A622: =A621+7 -> 40669 | B622: ='[5]Fed Steer Margin'!B622 -> 962.73 | C622: ='[5]Fed Steer Margin'!C622 -> 609.47932 | D622: ='[5]Fed Steer Margin'!D622 -> 1572.2093 | E622: ='[5]Fed Steer Margin'!E622 -> 1613.55 | F622: ='[5]Fed Steer Margin'!F622 -> 41.340681
A623: =A622+7 -> 40676 | B623: ='[5]Fed Steer Margin'!B623 -> 1031.4 | C623: ='[5]Fed Steer Margin'!C623 -> 613.75823 | D623: ='[5]Fed Steer Margin'!D623 -> 1645.1582 | E623: ='[5]Fed Steer Margin'!E623 -> 1601.4 | F623: ='[5]Fed Steer Margin'!F623 -> -43.758229
A624: =A623+7 -> 40683 | B624: ='[5]Fed Steer Margin'!B624 -> 992.07 | C624: ='[5]Fed Steer Margin'!C624 -> 617.97091 | D624: ='[5]Fed Steer Margin'!D624 -> 1610.0409 | E624: ='[5]Fed Steer Margin'!E624 -> 1581.6 | F624: ='[5]Fed Steer Margin'!F624 -> -28.440906
A625: =A624+7 -> 40690 | B625: ='[5]Fed Steer Margin'!B625 -> 974.07 | C625: ='[5]Fed Steer Margin'!C625 -> 624.5718 | D625: ='[5]Fed Steer Margin'!D625 -> 1598.6418 | E625: ='[5]Fed Steer Margin'!E625 -> 1584.75 | F625: ='[5]Fed Steer Margin'!F625 -> -13.891802
A626: =A625+7 -> 40697 | B626: ='[5]Fed Steer Margin'!B626 -> 1048.59 | C626: ='[5]Fed Steer Margin'!C626 -> 631.29421 | D626: ='[5]Fed Steer Margin'!D626 -> 1679.8842 | E626: ='[5]Fed Steer Margin'!E626 -> 1552.5 | F626: ='[5]Fed Steer Margin'!F626 -> -127.38421
A627: =A626+7 -> 40704 | B627: ='[5]Fed Steer Margin'!B627 -> 1039.68 | C627: ='[5]Fed Steer Margin'!C627 -> 638.29921 | D627: ='[5]Fed Steer Margin'!D627 -> 1677.9792 | E627: ='[5]Fed Steer Margin'!E627 -> 1545.6 | F627: ='[5]Fed Steer Margin'!F627 -> -132.37921
A628: =A627+7 -> 40711 | B628: ='[5]Fed Steer Margin'!B628 -> 1049.22 | C628: ='[5]Fed Steer Margin'!C628 -> 645.59003 | D628: ='[5]Fed Steer Margin'!D628 -> 1694.81 | E628: ='[5]Fed Steer Margin'!E628 -> 1602.6 | F628: ='[5]Fed Steer Margin'!F628 -> -92.21003
A629: =A628+7 -> 40718 | B629: ='[5]Fed Steer Margin'!B629 -> 1021.86 | C629: ='[5]Fed Steer Margin'!C629 -> 651.64378 | D629: ='[5]Fed Steer Margin'!D629 -> 1673.5038 | E629: ='[5]Fed Steer Margin'!E629 -> 1653.15 | F629: ='[5]Fed Steer Margin'!F629 -> -20.353783
A630: =A629+7 -> 40725 | B630: ='[5]Fed Steer Margin'!B630 -> 1021.86 | C630: ='[5]Fed Steer Margin'!C630 -> 656.34694 | D630: ='[5]Fed Steer Margin'!D630 -> 1678.2069 | E630: ='[5]Fed Steer Margin'!E630 -> 1639.65 | F630: ='[5]Fed Steer Margin'!F630 -> -38.556937
A631: =A630+7 -> 40732 | B631: ='[5]Fed Steer Margin'!B631 -> 1036.8 | C631: ='[5]Fed Steer Margin'!C631 -> 659.90708 | D631: ='[5]Fed Steer Margin'!D631 -> 1696.7071 | E631: ='[5]Fed Steer Margin'!E631 -> 1639.65 | F631: ='[5]Fed Steer Margin'!F631 -> -57.05708
A632: =A631+7 -> 40739 | B632: ='[5]Fed Steer Margin'!B632 -> 1055.34 | C632: ='[5]Fed Steer Margin'!C632 -> 663.04292 | D632: ='[5]Fed Steer Margin'!D632 -> 1718.3829 | E632: ='[5]Fed Steer Margin'!E632 -> 1614.9 | F632: ='[5]Fed Steer Margin'!F632 -> -103.48292
... A1073: =A1072+7 -> 43826 | B1073: ='[5]Fed Steer Margin'!B1073 -> 1470.33 | C1073: ='[5]Fed Steer Margin'!C1073 -> 592.10368 | D1073: ='[5]Fed Steer Margin'!D1073 -> 2062.4337 | E1073: ='[5]Fed Steer Margin'!E1073 -> 2068.95 | F1073: ='[5]Fed Steer Margin'!F1073 -> 6.516319
A1074: =A1073+7 -> 43833 | B1074: ='[5]Fed Steer Margin'!B1074 -> 1445.58 | C1074: ='[5]Fed Steer Margin'!C1074 -> 590.3984 | D1074: ='[5]Fed Steer Margin'!D1074 -> 2035.9784 | E1074: ='[5]Fed Steer Margin'!E1074 -> 2056.95 | F1074: ='[5]Fed Steer Margin'!F1074 -> 20.971604 | G1074: =+(F1074-F1022)/ABS(F1022) -> -0.78892859
A1075: =A1074+7 -> 43840 | B1075: ='[5]Fed Steer Margin'!B1075 -> 1544.67 | C1075: ='[5]Fed Steer Margin'!C1075 -> 588.70352 | D1075: ='[5]Fed Steer Margin'!D1075 -> 2133.3735 | E1075: ='[5]Fed Steer Margin'!E1075 -> 2095.65 | F1075: ='[5]Fed Steer Margin'!F1075 -> -37.723515 | G1075: =+(F1075-F1023)/ABS(F1023) -> -1.7465958
A1076: =A1075+7 -> 43847 | B1076: ='[5]Fed Steer Margin'!B1076 -> 1574.19 | C1076: ='[5]Fed Steer Margin'!C1076 -> 587.31679 | D1076: ='[5]Fed Steer Margin'!D1076 -> 2161.5068 | E1076: ='[5]Fed Steer Margin'!E1076 -> 2146.8 | F1076: ='[5]Fed Steer Margin'!F1076 -> -14.706794 | G1076: =+(F1076-F1024)/ABS(F1024) -> -17.478731
A1077: =A1076+7 -> 43854 | B1077: ='[5]Fed Steer Margin'!B1077 -> 1625.49 | C1077: ='[5]Fed Steer Margin'!C1077 -> 585.24295 | D1077: ='[5]Fed Steer Margin'!D1077 -> 2210.7329 | E1077: ='[5]Fed Steer Margin'!E1077 -> 2157.3 | F1077: ='[5]Fed Steer Margin'!F1077 -> -53.432945 | G1077: =+(F1077-F1025)/ABS(F1025) -> -13.945116
A1078: =A1077+7 -> 43861 | B1078: ='[5]Fed Steer Margin'!B1078 -> 1619.46 | C1078: ='[5]Fed Steer Margin'!C1078 -> 583.20257 | D1078: ='[5]Fed Steer Margin'!D1078 -> 2202.6626 | E1078: ='[5]Fed Steer Margin'!E1078 -> 2151.45 | F1078: ='[5]Fed Steer Margin'!F1078 -> -51.212566 | G1078: =+(F1078-F1026)/ABS(F1026) -> -0.20702459
A1079: =A1078+7 -> 43868 | B1079: ='[5]Fed Steer Margin'!B1079 -> 1645.2 | C1079: ='[5]Fed Steer Margin'!C1079 -> 581.28133 | D1079: ='[5]Fed Steer Margin'!D1079 -> 2226.4813 | E1079: ='[5]Fed Steer Margin'!E1079 -> 2082.75 | F1079: ='[5]Fed Steer Margin'!F1079 -> -143.73133 | G1079: =+(F1079-F1027)/ABS(F1027) -> -41.554488
A1080: =A1079+7 -> 43875 | B1080: ='[5]Fed Steer Margin'!B1080 -> 1669.59 | C1080: ='[5]Fed Steer Margin'!C1080 -> 579.88198 | D1080: ='[5]Fed Steer Margin'!D1080 -> 2249.472 | E1080: ='[5]Fed Steer Margin'!E1080 -> 2083.95 | F1080: ='[5]Fed Steer Margin'!F1080 -> -165.52198 | G1080: =+(F1080-F1028)/ABS(F1028) -> -9.6988799
A1081: =A1080+7 -> 43882 | B1081: ='[5]Fed Steer Margin'!B1081 -> 1656.72 | C1081: ='[5]Fed Steer Margin'!C1081 -> 578.48996 | D1081: ='[5]Fed Steer Margin'!D1081 -> 2235.21 | E1081: ='[5]Fed Steer Margin'!E1081 -> 2099.4 | F1081: ='[5]Fed Steer Margin'!F1081 -> -135.80996 | G1081: =+(F1081-F1029)/ABS(F1029) -> -0.90988664
A1082: =A1081+7 -> 43889 | B1082: ='[5]Fed Steer Margin'!B1082 -> 1684.08 | C1082: ='[5]Fed Steer Margin'!C1082 -> 577.90592 | D1082: ='[5]Fed Steer Margin'!D1082 -> 2261.9859 | E1082: ='[5]Fed Steer Margin'!E1082 -> 2157.6 | F1082: ='[5]Fed Steer Margin'!F1082 -> -104.38592 | G1082: =+(F1082-F1030)/ABS(F1030) -> 0.2082726
A1083: =A1082+7 -> 43896 | B1083: ='[5]Fed Steer Margin'!B1083 -> 1693.17 | C1083: ='[5]Fed Steer Margin'!C1083 -> 577.36751 | D1083: ='[5]Fed Steer Margin'!D1083 -> 2270.5375 | E1083: ='[5]Fed Steer Margin'!E1083 -> 2153.7 | F1083: ='[5]Fed Steer Margin'!F1083 -> -116.83751 | G1083: =+(F1083-F1031)/ABS(F1031) -> 0.35490867
A1084: =A1083+7 -> 43903 | B1084: ='[5]Fed Steer Margin'!B1084 -> 1609.74 | C1084: ='[5]Fed Steer Margin'!C1084 -> 577.20149 | D1084: ='[5]Fed Steer Margin'!D1084 -> 2186.9415 | E1084: ='[5]Fed Steer Margin'!E1084 -> 2038.05 | F1084: ='[5]Fed Steer Margin'!F1084 -> -148.89149 | G1084: =+(F1084-F1032)/ABS(F1032) -> 0.51246835
A1085: =A1084+7 -> 43910 | B1085: ='[5]Fed Steer Margin'!B1085 -> 1622.52 | C1085: ='[5]Fed Steer Margin'!C1085 -> 577.50514 | D1085: ='[5]Fed Steer Margin'!D1085 -> 2200.0251 | E1085: ='[5]Fed Steer Margin'!E1085 -> 2035.2 | F1085: ='[5]Fed Steer Margin'!F1085 -> -164.82514 | G1085: =+(F1085-F1033)/ABS(F1033) -> 0.63620225
... A1125: =A1124+7 -> 44190 | B1125: ='[5]Fed Steer Margin'!B1125 -> 1487.88 | C1125: ='[5]Fed Steer Margin'!C1125 -> 594.59659 | D1125: ='[5]Fed Steer Margin'!D1125 -> 2082.4766 | E1125: ='[5]Fed Steer Margin'!E1125 -> 1729.65 | F1125: ='[5]Fed Steer Margin'!F1125 -> -352.82659 | G1125: =+(F1125-F1073)/ABS(F1073) -> -55.145077
A1126: =A1125+7 -> 44197 | B1126: ='[5]Fed Steer Margin'!B1126 -> 0 | C1126: ='[5]Fed Steer Margin'!C1126 -> 0 | D1126: ='[5]Fed Steer Margin'!D1126 -> 0 | E1126: ='[5]Fed Steer Margin'!E1126 -> 0 | F1126: ='[5]Fed Steer Margin'!F1126 -> 0
A1127: =A1126+7 -> 44204 | B1127: ='[5]Fed Steer Margin'!B1127 -> 1500.12 | C1127: ='[5]Fed Steer Margin'!C1127 -> 599.99969 | D1127: ='[5]Fed Steer Margin'!D1127 -> 2100.1197 | E1127: ='[5]Fed Steer Margin'!E1127 -> 1938.45 | F1127: ='[5]Fed Steer Margin'!F1127 -> -161.66969 | G1127: =+(F1127-F1074)/ABS(F1074) -> -8.7089806
A1128: =A1127+7 -> 44211 | B1128: ='[5]Fed Steer Margin'!B1128 -> 1557.18 | C1128: ='[5]Fed Steer Margin'!C1128 -> 602.47352 | D1128: ='[5]Fed Steer Margin'!D1128 -> 2159.6535 | E1128: ='[5]Fed Steer Margin'!E1128 -> 1949.7 | F1128: ='[5]Fed Steer Margin'!F1128 -> -209.95352 | G1128: =+(F1128-F1075)/ABS(F1075) -> -4.5655874
A1129: =A1128+7 -> 44218 | B1129: ='[5]Fed Steer Margin'!B1129 -> 1614.24 | C1129: ='[5]Fed Steer Margin'!C1129 -> 609.77277 | D1129: ='[5]Fed Steer Margin'!D1129 -> 2224.0128 | E1129: ='[5]Fed Steer Margin'!E1129 -> 2002.5 | F1129: ='[5]Fed Steer Margin'!F1129 -> -221.51277 | G1129: =+(F1129-F1076)/ABS(F1076) -> -14.061935
A1130: =A1129+7 -> 44225 | B1130: ='[5]Fed Steer Margin'!B1130 -> 1604.88 | C1130: ='[5]Fed Steer Margin'!C1130 -> 623.40885 | D1130: ='[5]Fed Steer Margin'!D1130 -> 2228.2888 | E1130: ='[5]Fed Steer Margin'!E1130 -> 2012.4 | F1130: ='[5]Fed Steer Margin'!F1130 -> -215.88885 | G1130: =+(F1130-F1077)/ABS(F1077) -> -3.0403696
A1131: =A1130+7 -> 44232 | B1131: ='[5]Fed Steer Margin'!B1131 -> 1655.55 | C1131: ='[5]Fed Steer Margin'!C1131 -> 632.37175 | D1131: ='[5]Fed Steer Margin'!D1131 -> 2287.9217 | E1131: ='[5]Fed Steer Margin'!E1131 -> 2071.05 | F1131: ='[5]Fed Steer Margin'!F1131 -> -216.87175 | G1131: =+(F1131-F1078)/ABS(F1078) -> -3.234737
A1132: =A1131+7 -> 44239 | B1132: ='[5]Fed Steer Margin'!B1132 -> 1673.28 | C1132: ='[5]Fed Steer Margin'!C1132 -> 641.82108 | D1132: ='[5]Fed Steer Margin'!D1132 -> 2315.1011 | E1132: ='[5]Fed Steer Margin'!E1132 -> 2038.95 | F1132: ='[5]Fed Steer Margin'!F1132 -> -276.15108 | G1132: =+(F1132-F1079)/ABS(F1079) -> -0.92130045
A1133: =A1132+7 -> 44246 | B1133: ='[5]Fed Steer Margin'!B1133 -> 1689.39 | C1133: ='[5]Fed Steer Margin'!C1133 -> 651.30405 | D1133: ='[5]Fed Steer Margin'!D1133 -> 2340.6941 | E1133: ='[5]Fed Steer Margin'!E1133 -> 1975.5 | F1133: ='[5]Fed Steer Margin'!F1133 -> -365.19405 | G1133: =+(F1133-F1080)/ABS(F1080) -> -1.2063176
A1134: =A1133+7 -> 44253 | B1134: ='[5]Fed Steer Margin'!B1134 -> 1686.96 | C1134: ='[5]Fed Steer Margin'!C1134 -> 657.29558 | D1134: ='[5]Fed Steer Margin'!D1134 -> 2344.2556 | E1134: ='[5]Fed Steer Margin'!E1134 -> 2051.85 | F1134: ='[5]Fed Steer Margin'!F1134 -> -292.40558 | G1134: =+(F1134-F1081)/ABS(F1081) -> -1.1530496
A1135: =A1134+7 -> 44260 | B1135: ='[5]Fed Steer Margin'!B1135 -> 1683.81 | C1135: ='[5]Fed Steer Margin'!C1135 -> 666.59007 | D1135: ='[5]Fed Steer Margin'!D1135 -> 2350.4001 | E1135: ='[5]Fed Steer Margin'!E1135 -> 2101.5 | F1135: ='[5]Fed Steer Margin'!F1135 -> -248.90007 | G1135: =+(F1135-F1082)/ABS(F1082) -> -1.3844219
A1136: =A1135+7 -> 44267 | B1136: ='[5]Fed Steer Margin'!B1136 -> 1650.87 | C1136: ='[5]Fed Steer Margin'!C1136 -> 674.91011 | D1136: ='[5]Fed Steer Margin'!D1136 -> 2325.7801 | E1136: ='[5]Fed Steer Margin'!E1136 -> 2116.05 | F1136: ='[5]Fed Steer Margin'!F1136 -> -209.73011 | G1136: =+(F1136-F1083)/ABS(F1083) -> -0.79505808
A1137: =A1136+7 -> 44274 | B1137: ='[5]Fed Steer Margin'!B1137 -> 1695.87 | C1137: ='[5]Fed Steer Margin'!C1137 -> 682.29457 | D1137: ='[5]Fed Steer Margin'!D1137 -> 2378.1646 | E1137: ='[5]Fed Steer Margin'!E1137 -> 2111.85 | F1137: ='[5]Fed Steer Margin'!F1137 -> -266.31457 | G1137: =+(F1137-F1084)/ABS(F1084) -> -0.78864874
A1138: =A1137+7 -> 44281 | B1138: ='[5]Fed Steer Margin'!B1138 -> 1672.92 | C1138: ='[5]Fed Steer Margin'!C1138 -> 689.59539 | D1138: ='[5]Fed Steer Margin'!D1138 -> 2362.5154 | E1138: ='[5]Fed Steer Margin'!E1138 -> 2104.5 | F1138: ='[5]Fed Steer Margin'!F1138 -> -258.01539 | G1138: =+(F1138-F1085)/ABS(F1085) -> -0.56538853
... A1178: =A1177+7 -> 44561 | B1178: ='[5]Fed Steer Margin'!B1178 -> 1595.25 | C1178: ='[5]Fed Steer Margin'!C1178 -> 764.93281 | D1178: ='[5]Fed Steer Margin'!D1178 -> 2360.1828 | E1178: ='[5]Fed Steer Margin'!E1178 -> 2570.55 | F1178: ='[5]Fed Steer Margin'!F1178 -> 210.36719 | G1178: =+(F1178-F1125)/ABS(F1125) -> 1.5962339
A1179: =A1178+7 -> 44568 | B1179: ='[5]Fed Steer Margin'!B1179 -> 1653.93 | C1179: ='[5]Fed Steer Margin'!C1179 -> 763.69766 | D1179: ='[5]Fed Steer Margin'!D1179 -> 2417.6277 | E1179: ='[5]Fed Steer Margin'!E1179 -> 2570.55 | F1179: ='[5]Fed Steer Margin'!F1179 -> 152.92234 | G1179: =+(F1179-F1127)/ABS(F1127) -> 1.9458937
A1180: =A1179+7 -> 44575 | B1180: ='[5]Fed Steer Margin'!B1180 -> 1547.82 | C1180: ='[5]Fed Steer Margin'!C1180 -> 761.65518 | D1180: ='[5]Fed Steer Margin'!D1180 -> 2309.4752 | E1180: ='[5]Fed Steer Margin'!E1180 -> 2538 | F1180: ='[5]Fed Steer Margin'!F1180 -> 228.52482 | G1180: =+(F1180-F1128)/ABS(F1128) -> 2.0884543
A1181: =A1180+7 -> 44582 | B1181: ='[5]Fed Steer Margin'!B1181 -> 1631.25 | C1181: ='[5]Fed Steer Margin'!C1181 -> 760.85208 | D1181: ='[5]Fed Steer Margin'!D1181 -> 2392.1021 | E1181: ='[5]Fed Steer Margin'!E1181 -> 2545.65 | F1181: ='[5]Fed Steer Margin'!F1181 -> 153.54792 | G1181: =+(F1181-F1129)/ABS(F1129) -> 1.6931786
A1182: =A1181+7 -> 44589 | B1182: ='[5]Fed Steer Margin'!B1182 -> 1592.82 | C1182: ='[5]Fed Steer Margin'!C1182 -> 759.72037 | D1182: ='[5]Fed Steer Margin'!D1182 -> 2352.5404 | E1182: ='[5]Fed Steer Margin'!E1182 -> 2503.65 | F1182: ='[5]Fed Steer Margin'!F1182 -> 151.10963 | G1182: =+(F1182-F1130)/ABS(F1130) -> 1.6999418
A1183: =A1182+7 -> 44596 | B1183: ='[5]Fed Steer Margin'!B1183 -> 1662.12 | C1183: ='[5]Fed Steer Margin'!C1183 -> 759.59339 | D1183: ='[5]Fed Steer Margin'!D1183 -> 2421.7134 | E1183: ='[5]Fed Steer Margin'!E1183 -> 2578.95 | F1183: ='[5]Fed Steer Margin'!F1183 -> 157.23661 | G1183: =+(F1183-F1131)/ABS(F1131) -> 1.7250212
A1184: =A1183+7 -> 44603 | B1184: ='[5]Fed Steer Margin'!B1184 -> 1694.16 | C1184: ='[5]Fed Steer Margin'!C1184 -> 759.41796 | D1184: ='[5]Fed Steer Margin'!D1184 -> 2453.578 | E1184: ='[5]Fed Steer Margin'!E1184 -> 2538.9 | F1184: ='[5]Fed Steer Margin'!F1184 -> 85.322042 | G1184: =+(F1184-F1132)/ABS(F1132) -> 1.3089687
A1185: =A1184+7 -> 44610 | B1185: ='[5]Fed Steer Margin'!B1185 -> 1700.37 | C1185: ='[5]Fed Steer Margin'!C1185 -> 760.34856 | D1185: ='[5]Fed Steer Margin'!D1185 -> 2460.7186 | E1185: ='[5]Fed Steer Margin'!E1185 -> 2488.35 | F1185: ='[5]Fed Steer Margin'!F1185 -> 27.631441 | G1185: =+(F1185-F1133)/ABS(F1133) -> 1.0756624
A1186: =A1185+7 -> 44617 | B1186: ='[5]Fed Steer Margin'!B1186 -> 1754.1 | C1186: ='[5]Fed Steer Margin'!C1186 -> 760.80118 | D1186: ='[5]Fed Steer Margin'!D1186 -> 2514.9012 | E1186: ='[5]Fed Steer Margin'!E1186 -> 2479.65 | F1186: ='[5]Fed Steer Margin'!F1186 -> -35.251176 | G1186: =+(F1186-F1134)/ABS(F1134) -> 0.87944425
A1187: =A1186+7 -> 44624 | B1187: ='[5]Fed Steer Margin'!B1187 -> 1754.64 | C1187: ='[5]Fed Steer Margin'!C1187 -> 762.04704 | D1187: ='[5]Fed Steer Margin'!D1187 -> 2516.687 | E1187: ='[5]Fed Steer Margin'!E1187 -> 2536.2 | F1187: ='[5]Fed Steer Margin'!F1187 -> 19.512962 | G1187: =+(F1187-F1135)/ABS(F1135) -> 1.0783968
A1188: =A1187+7 -> 44631 | B1188: ='[5]Fed Steer Margin'!B1188 -> 1755.18 | C1188: ='[5]Fed Steer Margin'!C1188 -> 765.11395 | D1188: ='[5]Fed Steer Margin'!D1188 -> 2520.294 | E1188: ='[5]Fed Steer Margin'!E1188 -> 2521.95 | F1188: ='[5]Fed Steer Margin'!F1188 -> 1.6560473 | G1188: =+(F1188-F1136)/ABS(F1136) -> 1.0078961
A1189: =A1188+7 -> 44638 | B1189: ='[5]Fed Steer Margin'!B1189 -> 1784.88 | C1189: ='[5]Fed Steer Margin'!C1189 -> 770.15186 | D1189: ='[5]Fed Steer Margin'!D1189 -> 2555.0319 | E1189: ='[5]Fed Steer Margin'!E1189 -> 2558.25 | F1189: ='[5]Fed Steer Margin'!F1189 -> 3.2181437 | G1189: =+(F1189-F1137)/ABS(F1137) -> 1.012084
A1190: =A1189+7 -> 44645 | B1190: ='[5]Fed Steer Margin'!B1190 -> 1780.74 | C1190: ='[5]Fed Steer Margin'!C1190 -> 779.00883 | D1190: ='[5]Fed Steer Margin'!D1190 -> 2559.7488 | E1190: ='[5]Fed Steer Margin'!E1190 -> 2581.2 | F1190: ='[5]Fed Steer Margin'!F1190 -> 21.451167 | G1190: =+(F1190-F1138)/ABS(F1138) -> 1.0831391
... A1282: =A1281+7 -> 45289 | B1282: ='[5]Fed Steer Margin'!B1282 -> 2620.98 | C1282: ='[5]Fed Steer Margin'!C1282 -> 718.63934 | D1282: ='[5]Fed Steer Margin'!D1282 -> 3339.6193 | E1282: ='[5]Fed Steer Margin'!E1282 -> 3258.15 | F1282: ='[5]Fed Steer Margin'!F1282 -> -81.469344 | G1282: =+(F1282-F1230)/ABS(F1230) -> -1.2283368
A1283: =A1282+7 -> 45296 | B1283: ='[5]Fed Steer Margin'!B1283 -> 2553.3 | C1283: ='[5]Fed Steer Margin'!C1283 -> 713.27234 | D1283: ='[5]Fed Steer Margin'!D1283 -> 3266.5723 | E1283: ='[5]Fed Steer Margin'!E1283 -> 3247.65 | F1283: ='[5]Fed Steer Margin'!F1283 -> -18.922336
A1284: =A1283+7 -> 45303 | B1284: ='[5]Fed Steer Margin'!B1284 -> 2633.22 | C1284: ='[5]Fed Steer Margin'!C1284 -> 710.15024 | D1284: ='[5]Fed Steer Margin'!D1284 -> 3343.3702 | E1284: ='[5]Fed Steer Margin'!E1284 -> 3330.45 | F1284: ='[5]Fed Steer Margin'!F1284 -> -12.920243
A1285: =A1284+7 -> 45310 | B1285: ='[5]Fed Steer Margin'!B1285 -> 2726.64 | C1285: ='[5]Fed Steer Margin'!C1285 -> 706.6534 | D1285: ='[5]Fed Steer Margin'!D1285 -> 3433.2934 | E1285: ='[5]Fed Steer Margin'!E1285 -> 3346.2 | F1285: ='[5]Fed Steer Margin'!F1285 -> -87.093397
A1286: =A1285+7 -> 45317 | B1286: ='[5]Fed Steer Margin'!B1286 -> 2665.62 | C1286: ='[5]Fed Steer Margin'!C1286 -> 702.54063 | D1286: ='[5]Fed Steer Margin'!D1286 -> 3368.1606 | E1286: ='[5]Fed Steer Margin'!E1286 -> 3367.5 | F1286: ='[5]Fed Steer Margin'!F1286 -> -0.66063005
A1287: =A1286+7 -> 45324 | B1287: ='[5]Fed Steer Margin'!B1287 -> 2800.53 | C1287: ='[5]Fed Steer Margin'!C1287 -> 697.41087 | D1287: ='[5]Fed Steer Margin'!D1287 -> 3497.9409 | E1287: ='[5]Fed Steer Margin'!E1287 -> 3465.45 | F1287: ='[5]Fed Steer Margin'!F1287 -> -32.490874
A1288: =A1287+7 -> 45331 | B1288: ='[5]Fed Steer Margin'!B1288 -> 2776.32 | C1288: ='[5]Fed Steer Margin'!C1288 -> 692.1852 | D1288: ='[5]Fed Steer Margin'!D1288 -> 3468.5052 | E1288: ='[5]Fed Steer Margin'!E1288 -> 3477.6 | F1288: ='[5]Fed Steer Margin'!F1288 -> 9.0948003
A1289: =A1288+7 -> 45338 | B1289: ='[5]Fed Steer Margin'!B1289 -> 2838.96 | C1289: ='[5]Fed Steer Margin'!C1289 -> 687.58169 | D1289: ='[5]Fed Steer Margin'!D1289 -> 3526.5417 | E1289: ='[5]Fed Steer Margin'!E1289 -> 3494.7 | F1289: ='[5]Fed Steer Margin'!F1289 -> -31.841686
A1290: =A1289+7 -> 45345 | B1290: ='[5]Fed Steer Margin'!B1290 -> 2719.71 | C1290: ='[5]Fed Steer Margin'!C1290 -> 682.7852 | D1290: ='[5]Fed Steer Margin'!D1290 -> 3402.4952 | E1290: ='[5]Fed Steer Margin'!E1290 -> 3588.75 | F1290: ='[5]Fed Steer Margin'!F1290 -> 186.2548
A1291: =A1290+7 -> 45352 | B1291: ='[5]Fed Steer Margin'!B1291 -> 2839.05 | C1291: ='[5]Fed Steer Margin'!C1291 -> 677.05648 | D1291: ='[5]Fed Steer Margin'!D1291 -> 3516.1065 | E1291: ='[5]Fed Steer Margin'!E1291 -> 3412.65 | F1291: ='[5]Fed Steer Margin'!F1291 -> -103.45648
A1292: =A1291+7 -> 45359 | B1292: ='[5]Fed Steer Margin'!B1292 -> 2781.99 | C1292: ='[5]Fed Steer Margin'!C1292 -> 671.45526 | D1292: ='[5]Fed Steer Margin'!D1292 -> 3453.4453 | E1292: ='[5]Fed Steer Margin'!E1292 -> 3590.1 | F1292: ='[5]Fed Steer Margin'!F1292 -> 136.65474
A1293: =A1292+7 -> 45366 | B1293: ='[5]Fed Steer Margin'!B1293 -> 2820.87 | C1293: ='[5]Fed Steer Margin'!C1293 -> 666.16857 | D1293: ='[5]Fed Steer Margin'!D1293 -> 3487.0386 | E1293: ='[5]Fed Steer Margin'!E1293 -> 3602.25 | F1293: ='[5]Fed Steer Margin'!F1293 -> 115.21143
A1294: =A1293+7 -> 45373 | B1294: ='[5]Fed Steer Margin'!B1294 -> 2827.71 | C1294: ='[5]Fed Steer Margin'!C1294 -> 660.14263 | D1294: ='[5]Fed Steer Margin'!D1294 -> 3487.8526 | E1294: ='[5]Fed Steer Margin'!E1294 -> 3639 | F1294: ='[5]Fed Steer Margin'!F1294 -> 151.14737
... A1439: =A1438+7 -> 46388 | B1439: ='[5]Fed Steer Margin'!B1439 -> #N/A | C1439: ='[5]Fed Steer Margin'!C1439 -> 0 | D1439: ='[5]Fed Steer Margin'!D1439 -> #N/A | E1439: ='[5]Fed Steer Margin'!E1439 -> 0 | F1439: ='[5]Fed Steer Margin'!F1439

Sheet FED STEER MARGIN_graphs
B1: Fed-steer margins
AC2: Last year | AD2: ='[5]FED STEER MARGIN_graphs'!M2 -> This year | AE2: ='[5]FED STEER MARGIN_graphs'!N2 -> 5-Year Ave (2021-25) | AF2: ='[5]FED STEER MARGIN_graphs'!O2 -> 10-Year Ave (2016-25) | AI2: Fed-Steer Margin ($ per 1,500 lbs Steer)
A3: ='[5]FED STEER MARGIN_graphs'!A3 -> Week No. | B3: Week No. | C3: 1999 | D3: 2000 | E3: 2001 | F3: 2002 | G3: 2003 | H3: 2004 | I3: 2005 | J3: 2006 | K3: 2007 | L3: 2008 | M3: 2009 | N3: 2010 | O3: 2011 | P3: 2012 | Q3: 2013 | R3: 2014 | S3: 2015 | T3: 2016 | U3: 2017 | V3: 2018 | W3: 2019 | X3: 2020 | Y3: 2021 | Z3: 2022 | AA3: 2023 | AB3: 2024 | AC3: 2025 | AD3: ='[5]FED STEER MARGIN_graphs'!M3 -> 2026 ytd | AE3: ='[5]FED STEER MARGIN_graphs'!N3 -> Avg 2021-25 | AF3: ='[5]FED STEER MARGIN_graphs'!O3 -> Avg 2016-25 | AI3: Weekly Fed Steer Margin
A4: ='[5]FED STEER MARGIN_graphs'!A4 -> 46024 | B4: 1 | D4: 309.72469 | E4: 296.88713 | F4: 28.041447 | G4: 314.67288 | H4: =+'Fed Steer Margin'!F239 -> 9.8879401 | I4: =+'Fed Steer Margin'!F292 -> 247.08351 | J4: =+'Fed Steer Margin'!F344 -> 325.30924 | K4: =+'Fed Steer Margin'!F396 -> 22.873419 | L4: =+'Fed Steer Margin'!F448 -> -184.88121 | M4: =+'Fed Steer Margin'!F500 -> 96.91539 | N4: =+'Fed Steer Margin'!F552 -> -96.425797 | O4: =+'Fed Steer Margin'!F605 -> 55.617415 | P4: =+'Fed Steer Margin'!$F657 -> 44.81085 | Q4: =+'Fed Steer Margin'!$F709 -> -192.12541 | R4: =+'Fed Steer Margin'!$F761 -> 196.33295 | S4: =+'Fed Steer Margin'!$F813 -> 175.85253 | T4: =+'Fed Steer Margin'!$F865 -> -82.958031 | U4: =+'Fed Steer Margin'!$F918 -> 88.873176 | V4: =+'Fed Steer Margin'!$F970 -> 201.03332 | W4: =+'Fed Steer Margin'!F1022 -> 99.357863 | X4: =+'Fed Steer Margin'!F1074 -> 20.971604 | Y4: =+'Fed Steer Margin'!F1127 -> -161.66969 | Z4: =+'Fed Steer Margin'!F1179 -> 152.92234 | AA4: 163.93411 | AB4: -18.922336 | AC4: 375.17043 | AD4: ='[5]FED STEER MARGIN_graphs'!M4 | AE4: ='[5]FED STEER MARGIN_graphs'!N4 -> 102.28697 | AF4: ='[5]FED STEER MARGIN_graphs'!O4 -> 83.871279
A5: ='[5]FED STEER MARGIN_graphs'!A5 -> 46031 | B5: 2 | D5: 304.80967 | E5: 260.30392 | F5: 63.079106 | G5: 374.44331 | H5: =+'Fed Steer Margin'!F240 -> 119.13207 | I5: =+'Fed Steer Margin'!F293 -> 283.79875 | J5: =+'Fed Steer Margin'!F345 -> 297.66883 | K5: =+'Fed Steer Margin'!F397 -> 71.226461 | L5: =+'Fed Steer Margin'!F449 -> -169.26158 | M5: =+'Fed Steer Margin'!F501 -> 21.473272 | N5: =+'Fed Steer Margin'!F553 -> -121.27522 | O5: =+'Fed Steer Margin'!F606 -> 72.147894 | P5: =+'Fed Steer Margin'!$F658 -> 73.717807 | Q5: =+'Fed Steer Margin'!$F710 -> -194.91853 | R5: =+'Fed Steer Margin'!$F762 -> 274.79032 | S5: =+'Fed Steer Margin'!$F814 -> 451.51507 | T5: =+'Fed Steer Margin'!$F866 -> -60.222616 | U5: =+'Fed Steer Margin'!$F919 -> 123.81304 | V5: =+'Fed Steer Margin'!$F971 -> 154.62149 | W5: =+'Fed Steer Margin'!F1023 -> 50.527363 | X5: =+'Fed Steer Margin'!F1075 -> -37.723515 | Y5: =+'Fed Steer Margin'!F1128 -> -209.95352 | Z5: =+'Fed Steer Margin'!F1180 -> 228.52482 | AA5: 111.69075 | AB5: -12.920243 | AC5: 473.25976 | AD5: ='[5]FED STEER MARGIN_graphs'!M5 -> 148.55951 | AE5: ='[5]FED STEER MARGIN_graphs'!N5 -> 118.12031 | AF5: ='[5]FED STEER MARGIN_graphs'!O5 -> 82.161731 | AH5: 1
A6: ='[5]FED STEER MARGIN_graphs'!A6 -> 46038 | B6: 3 | D6: 316.97904 | E6: 272.37689 | F6: 101.18326 | G6: 434.44237 | H6: =+'Fed Steer Margin'!F241 -> 121.45628 | I6: =+'Fed Steer Margin'!F294 -> 317.17511 | J6: =+'Fed Steer Margin'!F346 -> 296.23102 | K6: =+'Fed Steer Margin'!F398 -> 60.917646 | L6: =+'Fed Steer Margin'!F450 -> -202.38873 | M6: =+'Fed Steer Margin'!F502 -> -10.792163 | N6: =+'Fed Steer Margin'!F554 -> -151.63083 | O6: =+'Fed Steer Margin'!F607 -> 79.504529 | P6: =+'Fed Steer Margin'!$F659 -> 108.94814 | Q6: =+'Fed Steer Margin'!$F711 -> -201.77539 | R6: =+'Fed Steer Margin'!$F763 -> 239.54507 | S6: =+'Fed Steer Margin'!$F815 -> 516.00806 | T6: =+'Fed Steer Margin'!$F867 -> -134.67107 | U6: =+'Fed Steer Margin'!$F920 -> 78.37233 | V6: =+'Fed Steer Margin'!$F972 -> -71.087481 | W6: =+'Fed Steer Margin'!F1024 -> 0.89247124 | X6: =+'Fed Steer Margin'!F1076 -> -14.706794 | Y6: =+'Fed Steer Margin'!F1129 -> -221.51277 | Z6: =+'Fed Steer Margin'!F1181 -> 153.54792 | AA6: 171.00441 | AB6: -87.093397 | AC6: 467.67641 | AD6: ='[5]FED STEER MARGIN_graphs'!M6 -> 97.292248 | AE6: ='[5]FED STEER MARGIN_graphs'!N6 -> 96.724514 | AF6: ='[5]FED STEER MARGIN_graphs'!O6 -> 34.242202 | AH6: 2
A7: ='[5]FED STEER MARGIN_graphs'!A7 -> 46045 | B7: 4 | D7: 321.19154 | E7: 310.31189 | F7: 63.433252 | G7: 346.42006 | H7: =+'Fed Steer Margin'!F242 -> 237.92038 | I7: =+'Fed Steer Margin'!F295 -> 325.89464 | J7: =+'Fed Steer Margin'!F347 -> 262.89962 | K7: =+'Fed Steer Margin'!F399 -> 40.781765 | L7: =+'Fed Steer Margin'!F451 -> -175.88824 | M7: =+'Fed Steer Margin'!F503 -> 4.0200255 | N7: =+'Fed Steer Margin'!F555 -> -72.377671 | O7: =+'Fed Steer Margin'!F608 -> 117.61546 | P7: =+'Fed Steer Margin'!$F660 -> 87.928195 | Q7: =+'Fed Steer Margin'!$F712 -> -181.56148 | R7: =+'Fed Steer Margin'!$F764 -> 299.73706 | S7: =+'Fed Steer Margin'!$F816 -> 409.62308 | T7: =+'Fed Steer Margin'!$F868 -> -108.02397 | U7: =+'Fed Steer Margin'!$F921 -> 215.38981 | V7: =+'Fed Steer Margin'!$F973 -> 29.076472 | W7: =+'Fed Steer Margin'!F1025 -> -3.575278 | X7: =+'Fed Steer Margin'!F1077 -> -53.432945 | Y7: =+'Fed Steer Margin'!F1130 -> -215.88885 | Z7: =+'Fed Steer Margin'!F1182 -> 151.10963 | AA7: 127.07551 | AB7: -0.66063005 | AC7: 497.65085 | AD7: ='[5]FED STEER MARGIN_graphs'!M7 -> 117.03142 | AE7: ='[5]FED STEER MARGIN_graphs'!N7 -> 111.8573 | AF7: ='[5]FED STEER MARGIN_graphs'!O7 -> 63.87206 | AH7: 3
A8: ='[5]FED STEER MARGIN_graphs'!A8 -> 46052 | B8: 5 | D8: 274.1102 | E8: 280.19104 | F8: 57.404373 | G8: 254.99888 | H8: =+'Fed Steer Margin'!F243 -> 103.26627 | I8: =+'Fed Steer Margin'!F296 -> 346.10547 | J8: =+'Fed Steer Margin'!F348 -> 218.45629 | K8: =+'Fed Steer Margin'!F400 -> 39.010863 | L8: =+'Fed Steer Margin'!F452 -> -167.567 | M8: =+'Fed Steer Margin'!F504 -> 35.207128 | N8: =+'Fed Steer Margin'!F556 -> -94.219598 | O8: =+'Fed Steer Margin'!F609 -> 33.039631 | P8: =+'Fed Steer Margin'!$F661 -> 41.933145 | Q8: =+'Fed Steer Margin'!$F713 -> -100.55679 | R8: =+'Fed Steer Margin'!$F765 -> 408.7663 | S8: =+'Fed Steer Margin'!$F817 -> 411.16536 | T8: =+'Fed Steer Margin'!$F869 -> -116.88525 | U8: =+'Fed Steer Margin'!$F922 -> 162.17586 | V8: =+'Fed Steer Margin'!$F974 -> 141.42396 | W8: =+'Fed Steer Margin'!F1026 -> -42.428768 | X8: =+'Fed Steer Margin'!F1078 -> -51.212566 | Y8: =+'Fed Steer Margin'!F1131 -> -216.87175 | Z8: =+'Fed Steer Margin'!F1183 -> 157.23661 | AA8: 140.33095 | AB8: -32.490874 | AC8: 490.83333 | AD8: ='[5]FED STEER MARGIN_graphs'!M8 -> 214.51122 | AE8: ='[5]FED STEER MARGIN_graphs'!N8 -> 107.80765 | AF8: ='[5]FED STEER MARGIN_graphs'!O8 -> 63.211151 | AH8: 4
A9: ='[5]FED STEER MARGIN_graphs'!A9 -> 46059 | B9: 6 | D9: 267.84874 | E9: 257.40255 | F9: 132.52363 | G9: 291.70098 | H9: =+'Fed Steer Margin'!F244 -> 63.029202 | I9: =+'Fed Steer Margin'!F297 -> 432.21829 | J9: =+'Fed Steer Margin'!F349 -> 204.36064 | K9: =+'Fed Steer Margin'!F401 -> 36.750254 | L9: =+'Fed Steer Margin'!F453 -> -159.36129 | M9: =+'Fed Steer Margin'!F505 -> -18.510144 | N9: =+'Fed Steer Margin'!F557 -> -71.185177 | O9: =+'Fed Steer Margin'!F610 -> 116.98305 | P9: =+'Fed Steer Margin'!$F662 -> 96.89485 | Q9: =+'Fed Steer Margin'!$F714 -> -166.16117 | R9: =+'Fed Steer Margin'!$F766 -> 365.72483 | S9: =+'Fed Steer Margin'!$F818 -> 418.68078 | T9: =+'Fed Steer Margin'!$F870 -> -138.07663 | U9: =+'Fed Steer Margin'!$F923 -> 114.28977 | V9: =+'Fed Steer Margin'!$F975 -> 92.020639 | W9: =+'Fed Steer Margin'!F1027 -> 3.5441535 | X9: =+'Fed Steer Margin'!F1079 -> -143.73133 | Y9: =+'Fed Steer Margin'!F1132 -> -276.15108 | Z9: =+'Fed Steer Margin'!F1184 -> 85.322042 | AA9: 155.93962 | AB9: 9.0948003 | AC9: 527.91568 | AD9: ='[5]FED STEER MARGIN_graphs'!M9 -> 229.56685 | AE9: ='[5]FED STEER MARGIN_graphs'!N9 -> 100.42421 | AF9: ='[5]FED STEER MARGIN_graphs'!O9 -> 43.016766 | AH9: 5
A10: ='[5]FED STEER MARGIN_graphs'!A10 -> 46066 | B10: 7 | D10: 267.89311 | E10: 304.40213 | F10: 211.28228 | G10: 293.88632 | H10: =+'Fed Steer Margin'!F245 -> -43.924386 | I10: =+'Fed Steer Margin'!F298 -> 441.47747 | J10: =+'Fed Steer Margin'!F350 -> 142.98822 | K10: =+'Fed Steer Margin'!F402 -> 63.512796 | L10: =+'Fed Steer Margin'!F454 -> -119.3229 | M10: =+'Fed Steer Margin'!F506 -> -39.993187 | N10: =+'Fed Steer Margin'!F558 -> -24.852815 | O10: =+'Fed Steer Margin'!F611 -> 64.189215 | P10: =+'Fed Steer Margin'!$F663 -> 45.087027 | Q10: =+'Fed Steer Margin'!$F715 -> -236.30802 | R10: =+'Fed Steer Margin'!$F767 -> 309.71744 | S10: =+'Fed Steer Margin'!$F819 -> 370.03342 | T10: =+'Fed Steer Margin'!$F871 -> -217.70911 | U10: =+'Fed Steer Margin'!$F924 -> 145.10976 | V10: =+'Fed Steer Margin'!$F976 -> 137.43026 | W10: =+'Fed Steer Margin'!F1028 -> -15.470963 | X10: =+'Fed Steer Margin'!F1080 -> -165.52198 | Y10: =+'Fed Steer Margin'!F1133 -> -365.19405 | Z10: =+'Fed Steer Margin'!F1185 -> 27.631441 | AA10: 142.82916 | AB10: -31.841686 | AC10: 394.6648 | AD10: ='[5]FED STEER MARGIN_graphs'!M10 -> 167.19901 | AE10: ='[5]FED STEER MARGIN_graphs'!N10 -> 33.617932 | AF10: ='[5]FED STEER MARGIN_graphs'!O10 -> 5.1927626 | AH10: 6
A11: ='[5]FED STEER MARGIN_graphs'!A11 -> 46073 | B11: 8 | D11: 255.01847 | E11: 289.14141 | F11: 157.22006 | G11: 191.51456 | H11: =+'Fed Steer Margin'!F246 -> -67.826954 | I11: =+'Fed Steer Margin'!F299 -> 389.32961 | J11: =+'Fed Steer Margin'!F351 -> 131.2874 | K11: =+'Fed Steer Margin'!F403 -> 104.66797 | L11: =+'Fed Steer Margin'!F455 -> -131.31799 | M11: =+'Fed Steer Margin'!F507 -> -52.550209 | N11: =+'Fed Steer Margin'!F559 -> -6.4521953 | O11: =+'Fed Steer Margin'!F612 -> 52.118235 | P11: =+'Fed Steer Margin'!$F664 -> 75.7574 | Q11: =+'Fed Steer Margin'!$F716 -> -190.24061 | R11: =+'Fed Steer Margin'!$F768 -> 317.57828 | S11: =+'Fed Steer Margin'!$F820 -> 416.35641 | T11: =+'Fed Steer Margin'!$F872 -> -213.94421 | U11: =+'Fed Steer Margin'!$F925 -> 153.65994 | V11: =+'Fed Steer Margin'!$F977 -> 194.15204 | W11: =+'Fed Steer Margin'!F1029 -> -71.108914 | X11: =+'Fed Steer Margin'!F1081 -> -135.80996 | Y11: =+'Fed Steer Margin'!F1134 -> -292.40558 | Z11: =+'Fed Steer Margin'!F1186 -> -35.251176 | AA11: 56.370607 | AB11: 186.2548 | AC11: 570.3878 | AD11: ='[5]FED STEER MARGIN_graphs'!M11 -> -88.294823 | AE11: ='[5]FED STEER MARGIN_graphs'!N11 -> 97.071289 | AF11: ='[5]FED STEER MARGIN_graphs'!O11 -> 41.230533 | AH11: 7
A12: ='[5]FED STEER MARGIN_graphs'!A12 -> 46080 | B12: 9 | D12: 237.46693 | E12: 321.34734 | F12: 156.85567 | G12: 202.13932 | H12: =+'Fed Steer Margin'!F247 -> 12.012541 | I12: =+'Fed Steer Margin'!F300 -> 270.96678 | J12: =+'Fed Steer Margin'!F352 -> 137.38053 | K12: =+'Fed Steer Margin'!F404 -> 85.321457 | L12: =+'Fed Steer Margin'!F456 -> -124.66261 | M12: =+'Fed Steer Margin'!F508 -> -73.09168 | N12: =+'Fed Steer Margin'!F560 -> -12.700237 | O12: =+'Fed Steer Margin'!F613 -> 40.431029 | P12: =+'Fed Steer Margin'!$F665 -> 67.584402 | Q12: =+'Fed Steer Margin'!$F717 -> -126.32254 | R12: =+'Fed Steer Margin'!$F769 -> 364.15843 | S12: =+'Fed Steer Margin'!$F821 -> 510.94424 | T12: =+'Fed Steer Margin'!$F873 -> -244.7837 | U12: =+'Fed Steer Margin'!$F926 -> 205.81824 | V12: =+'Fed Steer Margin'!$F978 -> 146.99053 | W12: =+'Fed Steer Margin'!F1030 -> -131.84578 | X12: =+'Fed Steer Margin'!F1082 -> -104.38592 | Y12: =+'Fed Steer Margin'!F1135 -> -248.90007 | Z12: =+'Fed Steer Margin'!F1187 -> 19.512962 | AA12: 250.30385 | AB12: -103.45648 | AC12: 415.84628 | AD12: ='[5]FED STEER MARGIN_graphs'!M12 -> 3.2183967 | AE12: ='[5]FED STEER MARGIN_graphs'!N12 -> 66.661309 | AF12: ='[5]FED STEER MARGIN_graphs'!O12 -> 20.509991 | AH12: 8
A13: ='[5]FED STEER MARGIN_graphs'!A13 -> 46087 | B13: 10 | D13: 213.48333 | E13: 386.88786 | F13: 228.94824 | G13: 188.79776 | H13: =+'Fed Steer Margin'!F248 -> 11.315327 | I13: =+'Fed Steer Margin'!F301 -> 166.62233 | J13: =+'Fed Steer Margin'!F353 -> 128.78659 | K13: =+'Fed Steer Margin'!F405 -> 158.72987 | L13: =+'Fed Steer Margin'!F457 -> -149.57374 | M13: =+'Fed Steer Margin'!F509 -> 11.793187 | N13: =+'Fed Steer Margin'!F561 -> -23.510424 | O13: =+'Fed Steer Margin'!F614 -> -2.6949114 | P13: =+'Fed Steer Margin'!$F666 -> 102.54049 | Q13: =+'Fed Steer Margin'!$F718 -> -229.02706 | R13: =+'Fed Steer Margin'!$F770 -> 338.91901 | S13: =+'Fed Steer Margin'!$F822 -> 494.60638 | T13: =+'Fed Steer Margin'!$F874 -> -207.47488 | U13: =+'Fed Steer Margin'!$F927 -> 341.39762 | V13: =+'Fed Steer Margin'!$F979 -> 89.304057 | W13: =+'Fed Steer Margin'!F1031 -> -181.11778 | X13: =+'Fed Steer Margin'!F1083 -> -116.83751 | Y13: =+'Fed Steer Margin'!F1136 -> -209.73011 | Z13: =+'Fed Steer Margin'!F1188 -> 1.6560473 | AA13: 172.92635 | AB13: 136.65474 | AC13: -66.153046 | AD13: ='[5]FED STEER MARGIN_graphs'!M13 -> -292.2121 | AE13: ='[5]FED STEER MARGIN_graphs'!N13 -> 7.0707962 | AF13: ='[5]FED STEER MARGIN_graphs'!O13 -> -3.93745 | AH13: 9
A14: ='[5]FED STEER MARGIN_graphs'!A14 -> 46094 | B14: 11 | D14: 272.66224 | E14: 371.54193 | F14: 221.81953 | G14: 149.13766 | H14: =+'Fed Steer Margin'!F249 -> -77.819345 | I14: =+'Fed Steer Margin'!F302 -> 182.48713 | J14: =+'Fed Steer Margin'!F354 -> 63.121125 | K14: =+'Fed Steer Margin'!F406 -> 192.33829 | L14: =+'Fed Steer Margin'!F458 -> -181.55749 | M14: =+'Fed Steer Margin'!F510 -> 9.9398591 | N14: =+'Fed Steer Margin'!F562 -> -20.617104 | O14: =+'Fed Steer Margin'!F615 -> 5.6850597 | P14: =+'Fed Steer Margin'!$F667 -> 13.131158 | Q14: =+'Fed Steer Margin'!$F719 -> -200.27411 | R14: =+'Fed Steer Margin'!$F771 -> 342.65932 | S14: =+'Fed Steer Margin'!$F823 -> 428.10088 | T14: =+'Fed Steer Margin'!$F875 -> -184.10782 | U14: =+'Fed Steer Margin'!$F928 -> 386.73288 | V14: =+'Fed Steer Margin'!$F980 -> 206.16532 | W14: =+'Fed Steer Margin'!F1032 -> -305.39861 | X14: =+'Fed Steer Margin'!F1084 -> -148.89149 | Y14: =+'Fed Steer Margin'!F1137 -> -266.31457 | Z14: =+'Fed Steer Margin'!F1189 -> 3.2181437 | AA14: 132.72887 | AB14: 115.21143 | AC14: 459.92457 | AD14: ='[5]FED STEER MARGIN_graphs'!M14 -> -135.16 | AE14: ='[5]FED STEER MARGIN_graphs'!N14 -> 88.953688 | AF14: ='[5]FED STEER MARGIN_graphs'!O14 -> 39.926871 | AH14: 10
A15: ='[5]FED STEER MARGIN_graphs'!A15 -> 46101 | B15: 12 | D15: 255.40046 | E15: 353.2346 | F15: 199.2372 | G15: 137.65275 | H15: =+'Fed Steer Margin'!F250 -> -180.90335 | I15: =+'Fed Steer Margin'!F303 -> 259.50291 | J15: =+'Fed Steer Margin'!F355 -> 13.068358 | K15: =+'Fed Steer Margin'!F407 -> 126.54237 | L15: =+'Fed Steer Margin'!F459 -> -190.72163 | M15: =+'Fed Steer Margin'!F511 -> 48.18195 | N15: =+'Fed Steer Margin'!F563 -> 25.350999 | O15: =+'Fed Steer Margin'!F616 -> 12.709066 | P15: =+'Fed Steer Margin'!$F668 -> 38.350708 | Q15: =+'Fed Steer Margin'!$F720 -> -245.26166 | R15: =+'Fed Steer Margin'!$F772 -> 366.36454 | S15: =+'Fed Steer Margin'!$F824 -> 402.46116 | T15: =+'Fed Steer Margin'!$F876 -> -347.42266 | U15: =+'Fed Steer Margin'!$F929 -> 328.80818 | V15: =+'Fed Steer Margin'!$F981 -> 61.70136 | W15: =+'Fed Steer Margin'!F1033 -> -453.06807 | X15: =+'Fed Steer Margin'!F1085 -> -164.82514 | Y15: =+'Fed Steer Margin'!F1138 -> -258.01539 | Z15: =+'Fed Steer Margin'!F1190 -> 21.451167 | AA15: 105.74452 | AB15: 151.14737 | AC15: 412.30173 | AD15: ='[5]FED STEER MARGIN_graphs'!M15 -> -50.391429 | AE15: ='[5]FED STEER MARGIN_graphs'!N15 -> 86.52588 | AF15: ='[5]FED STEER MARGIN_graphs'!O15 -> -14.217693 | AH15: 11
A16: ='[5]FED STEER MARGIN_graphs'!A16 -> 46108 | B16: 13 | D16: 291.35432 | E16: 291.57488 | F16: 86.315153 | G16: 175.68924 | H16: =+'Fed Steer Margin'!F251 -> -212.00316 | I16: =+'Fed Steer Margin'!F304 -> 281.39031 | J16: =+'Fed Steer Margin'!F356 -> 3.5496411 | K16: =+'Fed Steer Margin'!F408 -> 141.08179 | L16: =+'Fed Steer Margin'!F460 -> -129.05381 | M16: =+'Fed Steer Margin'!F512 -> 34.495563 | N16: =+'Fed Steer Margin'!F564 -> 6.2317185 | O16: =+'Fed Steer Margin'!F617 -> 59.598719 | P16: =+'Fed Steer Margin'!$F669 -> -68.681574 | Q16: =+'Fed Steer Margin'!$F721 -> -262.6965 | R16: =+'Fed Steer Margin'!$F773 -> 422.73121 | S16: =+'Fed Steer Margin'!$F825 -> 419.77078 | T16: =+'Fed Steer Margin'!$F877 -> -263.38516 | U16: =+'Fed Steer Margin'!$F930 -> 291.61034 | V16: =+'Fed Steer Margin'!$F982 -> 12.984116 | W16: =+'Fed Steer Margin'!F1034 -> -243.87947 | X16: =+'Fed Steer Margin'!F1086 -> -150.24168 | Y16: =+'Fed Steer Margin'!F1139 -> -234.6155 | Z16: =+'Fed Steer Margin'!F1191 -> -27.670705 | AA16: 53.624561 | AB16: 202.17458 | AC16: 479.01972 | AD16: ='[5]FED STEER MARGIN_graphs'!M16 -> -84.601702 | AE16: ='[5]FED STEER MARGIN_graphs'!N16 -> 94.506531 | AF16: ='[5]FED STEER MARGIN_graphs'!O16 -> 11.96208 | AH16: 12
A17: ='[5]FED STEER MARGIN_graphs'!A17 -> 46115 | B17: 14 | D17: 298.35022 | E17: 367.20593 | F17: 193.40718 | G17: 229.04439 | H17: =+'Fed Steer Margin'!F252 -> -196.02277 | I17: =+'Fed Steer Margin'!F305 -> 193.00356 | J17: =+'Fed Steer Margin'!F357 -> 18.853731 | K17: =+'Fed Steer Margin'!F409 -> 148.47304 | L17: =+'Fed Steer Margin'!F461 -> -128.11786 | M17: =+'Fed Steer Margin'!F513 -> 51.462048 | N17: =+'Fed Steer Margin'!F565 -> 48.245012 | O17: =+'Fed Steer Margin'!F618 -> 102.81573 | P17: =+'Fed Steer Margin'!$F670 -> -135.82294 | Q17: =+'Fed Steer Margin'!$F722 -> -266.19853 | R17: =+'Fed Steer Margin'!$F774 -> 253.39698 | S17: =+'Fed Steer Margin'!$F826 -> 313.6638 | T17: =+'Fed Steer Margin'!$F878 -> -278.34042 | U17: =+'Fed Steer Margin'!$F931 -> 427.6454 | V17: =+'Fed Steer Margin'!$F983 -> -63.983245 | W17: =+'Fed Steer Margin'!F1035 -> -266.03295 | X17: =+'Fed Steer Margin'!F1087 -> -176.32642 | Y17: =+'Fed Steer Margin'!F1140 -> -316.96527 | Z17: =+'Fed Steer Margin'!F1192 -> 61.325995 | AA17: 50.073576 | AB17: 157.58307 | AC17: 207.49586 | AD17: ='[5]FED STEER MARGIN_graphs'!M17 -> -129.89561 | AE17: ='[5]FED STEER MARGIN_graphs'!N17 -> 31.902646 | AF17: ='[5]FED STEER MARGIN_graphs'!O17 -> -19.752441 | AH17: 13
A18: ='[5]FED STEER MARGIN_graphs'!A18 -> 46122 | B18: 15 | D18: 323.21233 | E18: 364.28205 | F18: 118.78594 | G18: 276.80262 | H18: =+'Fed Steer Margin'!F253 -> -69.961475 | I18: =+'Fed Steer Margin'!F306 -> 172.73018 | J18: =+'Fed Steer Margin'!F358 -> -12.167728 | K18: =+'Fed Steer Margin'!F410 -> 172.9502 | L18: =+'Fed Steer Margin'!F462 -> -133.09433 | M18: =+'Fed Steer Margin'!F514 -> 61.575646 | N18: =+'Fed Steer Margin'!F566 -> 44.666611 | O18: =+'Fed Steer Margin'!F619 -> 45.825267 | P18: =+'Fed Steer Margin'!$F671 -> -130.29629 | Q18: =+'Fed Steer Margin'!$F723 -> -285.87919 | R18: =+'Fed Steer Margin'!$F775 -> 344.87785 | S18: =+'Fed Steer Margin'!$F827 -> 347.54119 | T18: =+'Fed Steer Margin'!$F879 -> -241.36244 | U18: =+'Fed Steer Margin'!$F932 -> 197.241 | V18: =+'Fed Steer Margin'!$F984 -> -249.31383 | W18: =+'Fed Steer Margin'!F1036 -> -147.27009 | X18: =+'Fed Steer Margin'!F1088 -> -165.11236 | Y18: =+'Fed Steer Margin'!F1141 -> -284.58185 | AA18: 161.51804 | AB18: 131.51466 | AC18: 759.12257 | AD18: ='[5]FED STEER MARGIN_graphs'!M18 -> 88.559279 | AE18: ='[5]FED STEER MARGIN_graphs'!N18 -> 191.89335 | AF18: ='[5]FED STEER MARGIN_graphs'!O18 -> 17.972854 | AH18: 14
A19: ='[5]FED STEER MARGIN_graphs'!A19 -> 46129 | B19: 16 | D19: 356.61063 | E19: 391.62857 | F19: 44.928569 | G19: 235.91889 | H19: =+'Fed Steer Margin'!F254 -> -63.248876 | I19: =+'Fed Steer Margin'!F307 -> 233.41669 | J19: =+'Fed Steer Margin'!F359 -> 15.474101 | K19: =+'Fed Steer Margin'!F411 -> 214.18801 | L19: =+'Fed Steer Margin'!F463 -> -98.628175 | M19: =+'Fed Steer Margin'!F515 -> 98.256015 | N19: =+'Fed Steer Margin'!F567 -> 74.886498 | O19: =+'Fed Steer Margin'!F620 -> 80.808441 | P19: =+'Fed Steer Margin'!$F672 -> -113.83029 | Q19: =+'Fed Steer Margin'!$F724 -> -179.63345 | R19: =+'Fed Steer Margin'!$F776 -> 289.28571 | S19: =+'Fed Steer Margin'!$F828 -> 331.76745 | T19: =+'Fed Steer Margin'!$F880 -> -387.1196 | U19: =+'Fed Steer Margin'!$F933 -> 372.94187 | V19: =+'Fed Steer Margin'!$F985 -> -202.90151 | W19: =+'Fed Steer Margin'!F1037 -> -146.66865 | X19: =+'Fed Steer Margin'!F1089 -> -167.79591 | Y19: =+'Fed Steer Margin'!F1142 -> -254.17449 | Z19: =+'Fed Steer Margin'!F1194 -> 49.694755 | AA19: 233.69305 | AB19: 148.11889 | AC19: 628.13989 | AD19: ='[5]FED STEER MARGIN_graphs'!M19 | AE19: ='[5]FED STEER MARGIN_graphs'!N19 -> 161.09442 | AF19: ='[5]FED STEER MARGIN_graphs'!O19 -> 27.39283 | AH19: 15
A20: ='[5]FED STEER MARGIN_graphs'!A20 -> 46136 | B20: 17 | D20: 390.62331 | E20: 359.15283 | F20: 122.3335 | G20: 236.91646 | H20: =+'Fed Steer Margin'!F255 -> -54.94428 | I20: =+'Fed Steer Margin'!F308 -> 262.37671 | J20: =+'Fed Steer Margin'!F360 -> 62.528699 | K20: =+'Fed Steer Margin'!F412 -> 246.89985 | L20: =+'Fed Steer Margin'!F464 -> 16.32534 | M20: =+'Fed Steer Margin'!F516 -> 99.816775 | N20: =+'Fed Steer Margin'!F568 -> 127.25549 | O20: =+'Fed Steer Margin'!F621 -> 79.774892 | P20: =+'Fed Steer Margin'!$F673 -> -102.33298 | Q20: =+'Fed Steer Margin'!$F725 -> -101.18382 | R20: =+'Fed Steer Margin'!$F777 -> 310.79274 | S20: =+'Fed Steer Margin'!$F829 -> 292.14748 | T20: =+'Fed Steer Margin'!$F881 -> -442.82624 | U20: =+'Fed Steer Margin'!$F934 -> 485.54072 | V20: =+'Fed Steer Margin'!$F986 -> -196.93544 | W20: =+'Fed Steer Margin'!F1038 -> -150.91055 | X20: =+'Fed Steer Margin'!F1090 -> -162.34433 | Y20: =+'Fed Steer Margin'!F1143 -> -169.28847 | Z20: =+'Fed Steer Margin'!F1195 -> 21.955192 | AA20: 216.2478 | AB20: 338.03818 | AC20: 708.78877 | AD20: ='[5]FED STEER MARGIN_graphs'!M20 | AE20: ='[5]FED STEER MARGIN_graphs'!N20 -> 223.14829 | AF20: ='[5]FED STEER MARGIN_graphs'!O20 -> 64.826563 | AH20: 16
A21: ='[5]FED STEER MARGIN_graphs'!A21 -> 46143 | B21: 18 | D21: 400.65184 | E21: 384.86543 | F21: 198.39164 | G21: 206.98963 | H21: =+'Fed Steer Margin'!F256 -> -127.03922 | I21: =+'Fed Steer Margin'!F309 -> 281.3753 | J21: =+'Fed Steer Margin'!F361 -> 126.01192 | K21: =+'Fed Steer Margin'!F413 -> 272.29424 | L21: =+'Fed Steer Margin'!F465 -> 8.6176841 | M21: =+'Fed Steer Margin'!F517 -> 117.85085 | N21: =+'Fed Steer Margin'!F569 -> 86.180935 | O21: =+'Fed Steer Margin'!F622 -> 41.340681 | P21: =+'Fed Steer Margin'!$F674 -> -99.344461 | Q21: =+'Fed Steer Margin'!$F726 -> -130.68872 | R21: =+'Fed Steer Margin'!$F778 -> 404.04957 | S21: =+'Fed Steer Margin'!$F830 -> 277.65869 | T21: =+'Fed Steer Margin'!$F882 -> -401.87612 | U21: =+'Fed Steer Margin'!$F935 -> 513.02736 | V21: =+'Fed Steer Margin'!$F987 -> -293.2758 | W21: =+'Fed Steer Margin'!F1039 -> 15.504994 | X21: =+'Fed Steer Margin'!F1091 -> -66.900124 | Y21: =+'Fed Steer Margin'!F1144 -> -165.60493 | Z21: =+'Fed Steer Margin'!F1196 -> 111.80836 | AA21: 345.31784 | AB21: 308.15901 | AC21: 672.45053 | AD21: ='[5]FED STEER MARGIN_graphs'!M21 | AE21: ='[5]FED STEER MARGIN_graphs'!N21 -> 254.42616 | AF21: ='[5]FED STEER MARGIN_graphs'!O21 -> 103.86111 | AH21: 17
A22: ='[5]FED STEER MARGIN_graphs'!A22 -> 46150 | B22: 19 | D22: 394.99087 | E22: 468.34203 | F22: 190.11387 | G22: 207.75063 | H22: =+'Fed Steer Margin'!F257 -> -5.5905466 | I22: =+'Fed Steer Margin'!F310 -> 199.87072 | J22: =+'Fed Steer Margin'!F362 -> 84.874652 | K22: =+'Fed Steer Margin'!F414 -> 341.01346 | L22: =+'Fed Steer Margin'!F466 -> 38.807881 | M22: =+'Fed Steer Margin'!F518 -> 102.71153 | N22: =+'Fed Steer Margin'!F570 -> 96.340196 | O22: =+'Fed Steer Margin'!F623 -> -43.758229 | P22: =+'Fed Steer Margin'!$F675 -> -95.791085 | Q22: =+'Fed Steer Margin'!$F727 -> -111.32315 | R22: =+'Fed Steer Margin'!$F779 -> 354.08621 | S22: =+'Fed Steer Margin'!$F831 -> 306.00599 | T22: =+'Fed Steer Margin'!$F883 -> -370.09856 | U22: =+'Fed Steer Margin'!$F936 -> 709.01325 | V22: =+'Fed Steer Margin'!$F988 -> -23.62889 | W22: =+'Fed Steer Margin'!F1040 -> -23.67014 | X22: =+'Fed Steer Margin'!F1092 -> -60.34873 | Y22: =+'Fed Steer Margin'!F1145 -> -169.68236 | Z22: =+'Fed Steer Margin'!F1197 -> 119.80981 | AA22: 269.88477 | AB22: 248.11204 | AC22: 825.66488 | AD22: ='[5]FED STEER MARGIN_graphs'!M22 | AE22: ='[5]FED STEER MARGIN_graphs'!N22 -> 258.75783 | AF22: ='[5]FED STEER MARGIN_graphs'!O22 -> 152.50561 | AH22: 18
A23: ='[5]FED STEER MARGIN_graphs'!A23 -> 46157 | B23: 20 | D23: 373.14418 | E23: 345.98069 | F23: 151.58905 | G23: 203.6254 | H23: =+'Fed Steer Margin'!F258 -> -118.94006 | I23: =+'Fed Steer Margin'!F311 -> 205.50891 | J23: =+'Fed Steer Margin'!F363 -> -8.2127543 | K23: =+'Fed Steer Margin'!F415 -> 277.32075 | L23: =+'Fed Steer Margin'!F467 -> -23.521456 | M23: =+'Fed Steer Margin'!F519 -> 23.257927 | N23: =+'Fed Steer Margin'!F571 -> 116.15721 | O23: =+'Fed Steer Margin'!F624 -> -28.440906 | P23: =+'Fed Steer Margin'!$F676 -> -101.6827 | Q23: =+'Fed Steer Margin'!$F728 -> -64.027742 | R23: =+'Fed Steer Margin'!$F780 -> 436.56214 | S23: =+'Fed Steer Margin'!$F832 -> 346.81102 | T23: =+'Fed Steer Margin'!$F884 -> -254.60995 | U23: =+'Fed Steer Margin'!$F937 -> 586.63699 | V23: =+'Fed Steer Margin'!$F989 -> -61.160686 | W23: =+'Fed Steer Margin'!F1041 -> 96.60162 | X23: =+'Fed Steer Margin'!F1093 -> -110.29647 | Y23: =+'Fed Steer Margin'!F1146 -> -85.550916 | Z23: =+'Fed Steer Margin'!F1198 -> 200.09948 | AA23: 351.26675 | AB23: 269.19558 | AC23: 782.97944 | AD23: ='[5]FED STEER MARGIN_graphs'!M23 | AE23: ='[5]FED STEER MARGIN_graphs'!N23 -> 303.59807 | AF23: ='[5]FED STEER MARGIN_graphs'!O23 -> 177.51618 | AH23: 19
A24: ='[5]FED STEER MARGIN_graphs'!A24 -> 46164 | B24: 21 | D24: 264.23365 | E24: 421.56048 | F24: 107.8417 | G24: 30.948051 | H24: =+'Fed Steer Margin'!F259 -> -187.56799 | I24: =+'Fed Steer Margin'!F312 -> 192.40986 | J24: =+'Fed Steer Margin'!F364 -> 106.05624 | K24: =+'Fed Steer Margin'!F416 -> 268.69801 | L24: =+'Fed Steer Margin'!F468 -> -8.0994811 | M24: =+'Fed Steer Margin'!F520 -> 78.808755 | N24: =+'Fed Steer Margin'!F572 -> 215.12534 | O24: =+'Fed Steer Margin'!F625 -> -13.891802 | P24: =+'Fed Steer Margin'!$F677 -> -58.103525 | Q24: =+'Fed Steer Margin'!$F729 -> -40.568175 | R24: =+'Fed Steer Margin'!$F781 -> 393.65159 | S24: =+'Fed Steer Margin'!$F833 -> 261.05193 | T24: =+'Fed Steer Margin'!$F885 -> -48.610128 | U24: =+'Fed Steer Margin'!$F938 -> 579.67126 | V24: =+'Fed Steer Margin'!$F990 -> -226.7083 | W24: =+'Fed Steer Margin'!F1042 -> -182.14918 | X24: =+'Fed Steer Margin'!F1094 -> 25.194097 | Y24: =+'Fed Steer Margin'!F1147 -> -158.53799 | Z24: =+'Fed Steer Margin'!F1199 -> 148.68169 | AA24: 159.81853 | AB24: 258.74821 | AC24: 681.00019 | AD24: ='[5]FED STEER MARGIN_graphs'!M24 | AE24: ='[5]FED STEER MARGIN_graphs'!N24 -> 217.94213 | AF24: ='[5]FED STEER MARGIN_graphs'!O24 -> 123.71084 | AH24: 20
A25: ='[5]FED STEER MARGIN_graphs'!A25 -> 46171 | B25: 22 | D25: 292.07147 | E25: 376.27816 | F25: 102.54269 | G25: 21.159618 | H25: =+'Fed Steer Margin'!F260 -> -136.6909 | I25: =+'Fed Steer Margin'!F313 -> 194.38624 | J25: =+'Fed Steer Margin'!F365 -> 115.70652 | K25: =+'Fed Steer Margin'!F417 -> 245.80429 | L25: =+'Fed Steer Margin'!F469 -> -21.392346 | M25: =+'Fed Steer Margin'!F521 -> 94.870761 | N25: =+'Fed Steer Margin'!F573 -> 165.13676 | O25: =+'Fed Steer Margin'!F626 -> -127.38421 | P25: =+'Fed Steer Margin'!$F678 -> -102.03423 | Q25: =+'Fed Steer Margin'!$F730 -> 51.620491 | R25: =+'Fed Steer Margin'!$F782 -> 374.15026 | S25: =+'Fed Steer Margin'!$F834 -> 275.43242 | T25: =+'Fed Steer Margin'!$F886 -> -29.338923 | U25: =+'Fed Steer Margin'!$F939 -> 493.86262 | V25: =+'Fed Steer Margin'!$F991 -> -180.199 | W25: =+'Fed Steer Margin'!F1043 -> -83.479682 | X25: =+'Fed Steer Margin'!F1095 -> 228.10783 | Y25: =+'Fed Steer Margin'!F1148 -> -53.782588 | Z25: =+'Fed Steer Margin'!F1200 -> 254.76456 | AA25: 373.98753 | AB25: 428.5893 | AC25: 728.48078 | AD25: ='[5]FED STEER MARGIN_graphs'!M25 | AE25: ='[5]FED STEER MARGIN_graphs'!N25 -> 346.40792 | AF25: ='[5]FED STEER MARGIN_graphs'!O25 -> 216.09924 | AH25: 21
A26: ='[5]FED STEER MARGIN_graphs'!A26 -> 46178 | B26: 23 | D26: 231.08321 | E26: 391.81878 | F26: 31.514466 | G26: 54.881428 | H26: =+'Fed Steer Margin'!F261 -> -129.21431 | I26: =+'Fed Steer Margin'!F314 -> 187.49316 | J26: =+'Fed Steer Margin'!F366 -> 91.692225 | K26: =+'Fed Steer Margin'!F418 -> 169.4117 | L26: =+'Fed Steer Margin'!F470 -> -8.4844346 | M26: =+'Fed Steer Margin'!F522 -> 12.248425 | N26: =+'Fed Steer Margin'!F574 -> 138.33109 | O26: =+'Fed Steer Margin'!F627 -> -132.37921 | P26: =+'Fed Steer Margin'!$F679 -> -23.131711 | Q26: =+'Fed Steer Margin'!$F731 -> -20.402327 | R26: =+'Fed Steer Margin'!$F783 -> 433.87932 | S26: =+'Fed Steer Margin'!$F835 -> 378.55905 | T26: =+'Fed Steer Margin'!$F887 -> -113.88542 | U26: =+'Fed Steer Margin'!$F940 -> 571.16286 | V26: =+'Fed Steer Margin'!$F992 -> -173.73589 | W26: =+'Fed Steer Margin'!F1044 -> -100.74145 | X26: =+'Fed Steer Margin'!F1096 -> 193.60057 | Y26: =+'Fed Steer Margin'!F1149 -> 10.121118 | Z26: =+'Fed Steer Margin'!F1201 -> 177.3018 | AA26: 440.39875 | AB26: 224.88494 | AC26: 733.05595 | AD26: ='[5]FED STEER MARGIN_graphs'!M26 | AE26: ='[5]FED STEER MARGIN_graphs'!N26 -> 317.15251 | AF26: ='[5]FED STEER MARGIN_graphs'!O26 -> 196.21632 | AH26: 22
A27: ='[5]FED STEER MARGIN_graphs'!A27 -> 46185 | B27: 24 | D27: 215.21461 | E27: 283.51953 | F27: 66.592705 | G27: -120.9304 | H27: =+'Fed Steer Margin'!F262 -> -202.98915 | I27: =+'Fed Steer Margin'!F315 -> 210.83173 | J27: =+'Fed Steer Margin'!F367 -> 114.81199 | K27: =+'Fed Steer Margin'!F419 -> 187.27922 | L27: =+'Fed Steer Margin'!F471 -> 24.221292 | M27: =+'Fed Steer Margin'!F523 -> -74.683479 | N27: =+'Fed Steer Margin'!F575 -> 136.20038 | O27: =+'Fed Steer Margin'!F628 -> -92.21003 | P27: =+'Fed Steer Margin'!$F680 -> -65.303919 | Q27: =+'Fed Steer Margin'!$F732 -> -102.87051 | R27: =+'Fed Steer Margin'!$F784 -> 456.36204 | S27: =+'Fed Steer Margin'!$F836 -> 227.24773 | T27: =+'Fed Steer Margin'!$F888 -> -42.634668 | U27: =+'Fed Steer Margin'!$F941 -> 499.75284 | V27: =+'Fed Steer Margin'!$F993 -> -246.94482 | W27: =+'Fed Steer Margin'!F1045 -> -158.69072 | X27: =+'Fed Steer Margin'!F1097 -> 172.22819 | Y27: =+'Fed Steer Margin'!F1150 -> 41.664841 | Z27: =+'Fed Steer Margin'!F1202 -> 165.52228 | AA27: 594.32695 | AB27: 96.184507 | AC27: 681.92356 | AD27: ='[5]FED STEER MARGIN_graphs'!M27 | AE27: ='[5]FED STEER MARGIN_graphs'!N27 -> 315.92443 | AF27: ='[5]FED STEER MARGIN_graphs'!O27 -> 180.3333 | AH27: 23
A28: ='[5]FED STEER MARGIN_graphs'!A28 -> 46192 | B28: 25 | D28: 238.53038 | E28: 360.84674 | F28: 57.452234 | G28: -307.23141 | H28: =+'Fed Steer Margin'!F263 -> -220.08064 | I28: =+'Fed Steer Margin'!F316 -> 217.14764 | J28: =+'Fed Steer Margin'!F368 -> 88.526601 | K28: =+'Fed Steer Margin'!F420 -> 186.21411 | L28: =+'Fed Steer Margin'!F472 -> 21.850158 | M28: =+'Fed Steer Margin'!F524 -> -81.970102 | N28: =+'Fed Steer Margin'!F576 -> 136.15699 | O28: =+'Fed Steer Margin'!F629 -> -20.353783 | P28: =+'Fed Steer Margin'!$F681 -> -46.327675 | Q28: =+'Fed Steer Margin'!$F733 -> -56.825782 | R28: =+'Fed Steer Margin'!$F785 -> 385.29411 | S28: =+'Fed Steer Margin'!$F837 -> 196.78526 | T28: =+'Fed Steer Margin'!$F889 -> -68.935337 | U28: =+'Fed Steer Margin'!$F942 -> 374.5062 | V28: =+'Fed Steer Margin'!$F994 -> -303.72046 | W28: =+'Fed Steer Margin'!F1046 -> -163.18224 | X28: =+'Fed Steer Margin'!F1098 -> 123.9103 | Y28: =+'Fed Steer Margin'!F1151 -> 94.765998 | Z28: =+'Fed Steer Margin'!F1203 -> 178.92001 | AA28: 524.15353 | AB28: 0.24352655 | AC28: 913.99709 | AD28: ='[5]FED STEER MARGIN_graphs'!M28 | AE28: ='[5]FED STEER MARGIN_graphs'!N28 -> 342.41603 | AF28: ='[5]FED STEER MARGIN_graphs'!O28 -> 167.46586 | AH28: 24
A29: ='[5]FED STEER MARGIN_graphs'!A29 -> 46199 | B29: 26 | D29: 262.54041 | E29: 308.14651 | F29: 136.57618 | G29: -587.51193 | H29: =+'Fed Steer Margin'!F264 -> -202.82209 | I29: =+'Fed Steer Margin'!F317 -> 232.06072 | J29: =+'Fed Steer Margin'!F369 -> 27.106192 | K29: =+'Fed Steer Margin'!F421 -> 134.67704 | L29: =+'Fed Steer Margin'!F473 -> 91.94564 | M29: =+'Fed Steer Margin'!F525 -> -67.345915 | N29: =+'Fed Steer Margin'!F577 -> 135.64285 | O29: =+'Fed Steer Margin'!F630 -> -38.556937 | P29: =+'Fed Steer Margin'!$F682 -> -56.770139 | Q29: =+'Fed Steer Margin'!$F734 -> -6.485769 | R29: =+'Fed Steer Margin'!$F786 -> 430.60503 | S29: =+'Fed Steer Margin'!$F838 -> 469.10292 | T29: =+'Fed Steer Margin'!$F890 -> -82.805464 | U29: =+'Fed Steer Margin'!$F943 -> 300.98099 | V29: =+'Fed Steer Margin'!$F995 -> -223.69451 | W29: =+'Fed Steer Margin'!F1047 -> -102.78315 | X29: =+'Fed Steer Margin'!F1099 -> -117.42132 | Y29: =+'Fed Steer Margin'!F1152 -> 105.48414 | Z29: =+'Fed Steer Margin'!F1204 -> 140.77466 | AA29: 439.92458 | AB29: 60.337284 | AC29: 752.57224 | AD29: ='[5]FED STEER MARGIN_graphs'!M29 | AE29: ='[5]FED STEER MARGIN_graphs'!N29 -> 299.81858 | AF29: ='[5]FED STEER MARGIN_graphs'!O29 -> 127.33694
A30: ='[5]FED STEER MARGIN_graphs'!A30 -> 46206 | B30: 27 | D30: 193.04711 | E30: 394.5608 | F30: 68.108754 | G30: -568.89677 | H30: =+'Fed Steer Margin'!F265 -> 19.408366 | I30: =+'Fed Steer Margin'!F318 -> 298.16762 | J30: =+'Fed Steer Margin'!F370 -> 77.471647 | K30: =+'Fed Steer Margin'!F422 -> 153.12573 | L30: =+'Fed Steer Margin'!F474 -> 106.97351 | M30: =+'Fed Steer Margin'!F526 -> -79.392375 | N30: =+'Fed Steer Margin'!F578 -> 270.07966 | O30: =+'Fed Steer Margin'!F631 -> -57.05708 | P30: =+'Fed Steer Margin'!$F683 -> -134.24611 | Q30: =+'Fed Steer Margin'!$F735 -> 0.68349516 | R30: =+'Fed Steer Margin'!$F787 -> 481.84413 | S30: =+'Fed Steer Margin'!$F839 -> 226.55535 | T30: =+'Fed Steer Margin'!$F891 -> -94.698986 | U30: =+'Fed Steer Margin'!$F944 -> 333.00831 | V30: =+'Fed Steer Margin'!$F996 -> -239.32151 | W30: =+'Fed Steer Margin'!F1048 -> -214.03998 | X30: =+'Fed Steer Margin'!F1100 -> -186.65791 | Y30: =+'Fed Steer Margin'!F1153 -> -54.656491 | Z30: =+'Fed Steer Margin'!F1205 -> -83.926624 | AA30: 439.83751 | AB30: 560.07007 | AC30: 792.58671 | AD30: ='[5]FED STEER MARGIN_graphs'!M30 | AE30: ='[5]FED STEER MARGIN_graphs'!N30 -> 330.78224 | AF30: ='[5]FED STEER MARGIN_graphs'!O30 -> 125.22011
A31: ='[5]FED STEER MARGIN_graphs'!A31 -> 46213 | B31: 28 | D31: 265.29143 | E31: 258.26687 | F31: 126.90496 | G31: -703.81609 | H31: =+'Fed Steer Margin'!F266 -> -69.770827 | I31: =+'Fed Steer Margin'!F319 -> 221.37084 | J31: =+'Fed Steer Margin'!F371 -> 57.994591 | K31: =+'Fed Steer Margin'!F423 -> 81.918093 | L31: =+'Fed Steer Margin'!F475 -> 115.83978 | M31: =+'Fed Steer Margin'!F527 -> -4.4780793 | N31: =+'Fed Steer Margin'!F579 -> 112.67179 | O31: =+'Fed Steer Margin'!F632 -> -103.48292 | P31: =+'Fed Steer Margin'!$F684 -> -142.22293 | Q31: =+'Fed Steer Margin'!$F736 -> -92.70327 | R31: =+'Fed Steer Margin'!$F788 -> 559.06948 | S31: =+'Fed Steer Margin'!$F840 -> 517.77343 | T31: =+'Fed Steer Margin'!$F892 -> -294.05605 | U31: =+'Fed Steer Margin'!$F945 -> 126.52157 | V31: =+'Fed Steer Margin'!$F997 -> -152.66937 | W31: =+'Fed Steer Margin'!F1049 -> -91.723355 | X31: =+'Fed Steer Margin'!F1101 -> -27.505292 | Y31: =+'Fed Steer Margin'!F1154 -> -31.321936 | Z31: =+'Fed Steer Margin'!F1206 -> -84.766747 | AA31: 418.85767 | AB31: 454.00713 | AC31: 802.42596 | AD31: ='[5]FED STEER MARGIN_graphs'!M31 | AE31: ='[5]FED STEER MARGIN_graphs'!N31 -> 311.84041 | AF31: ='[5]FED STEER MARGIN_graphs'!O31 -> 111.97696
A32: ='[5]FED STEER MARGIN_graphs'!A32 -> 46220 | B32: 29 | D32: 181.15423 | E32: 245.44255 | F32: 16.557784 | G32: -917.6142 | H32: =+'Fed Steer Margin'!F267 -> -65.506342 | I32: =+'Fed Steer Margin'!F320 -> 144.58274 | J32: =+'Fed Steer Margin'!F372 -> 78.3846 | K32: =+'Fed Steer Margin'!F424 -> 98.871457 | L32: =+'Fed Steer Margin'!F476 -> 103.37717 | M32: =+'Fed Steer Margin'!F528 -> -97.309439 | N32: =+'Fed Steer Margin'!F580 -> 158.64277 | O32: =+'Fed Steer Margin'!F633 -> -138.87655 | P32: =+'Fed Steer Margin'!$F685 -> -268.32487 | Q32: =+'Fed Steer Margin'!$F737 -> -55.308337 | R32: =+'Fed Steer Margin'!$F789 -> 442.09536 | S32: =+'Fed Steer Margin'!$F841 -> 252.25836 | T32: =+'Fed Steer Margin'!$F893 -> -224.72559 | U32: =+'Fed Steer Margin'!$F946 -> 171.11499 | V32: =+'Fed Steer Margin'!$F998 -> -180.72921 | W32: =+'Fed Steer Margin'!F1050 -> -107.23824 | X32: =+'Fed Steer Margin'!F1102 -> -14.532932 | Y32: =+'Fed Steer Margin'!F1155 -> -63.380866 | Z32: =+'Fed Steer Margin'!F1207 -> -21.671321 | AA32: 437.88898 | AB32: 331.01379 | AC32: 868.93745 | AD32: ='[5]FED STEER MARGIN_graphs'!M32 | AE32: ='[5]FED STEER MARGIN_graphs'!N32 -> 310.55761 | AF32: ='[5]FED STEER MARGIN_graphs'!O32 -> 119.6677
A33: ='[5]FED STEER MARGIN_graphs'!A33 -> 46227 | B33: 30 | D33: 215.69839 | E33: 221.18304 | F33: 58.193897 | G33: -998.74278 | H33: =+'Fed Steer Margin'!F268 -> -92.409046 | I33: =+'Fed Steer Margin'!F321 -> 137.8766 | J33: =+'Fed Steer Margin'!F373 -> 2.3074726 | K33: =+'Fed Steer Margin'!F425 -> 110.02196 | L33: =+'Fed Steer Margin'!F477 -> 85.459226 | M33: =+'Fed Steer Margin'!F529 -> -91.421436 | N33: =+'Fed Steer Margin'!F581 -> 125.46137 | O33: =+'Fed Steer Margin'!F634 -> -192.22215 | P33: =+'Fed Steer Margin'!$F686 -> -295.33114 | Q33: =+'Fed Steer Margin'!$F738 -> -71.858472 | R33: =+'Fed Steer Margin'!$F790 -> 489.25719 | S33: =+'Fed Steer Margin'!$F842 -> 233.74346 | T33: =+'Fed Steer Margin'!$F894 -> -275.59875 | U33: =+'Fed Steer Margin'!$F947 -> 142.53384 | V33: =+'Fed Steer Margin'!$F999 -> -99.492405 | W33: =+'Fed Steer Margin'!F1051 -> -105.02598 | X33: =+'Fed Steer Margin'!F1103 -> -91.132597 | Y33: =+'Fed Steer Margin'!F1156 -> -50.919749 | Z33: =+'Fed Steer Margin'!F1208 -> -56.366104 | AA33: 448.62538 | AB33: 480.43996 | AC33: 761.41726 | AD33: ='[5]FED STEER MARGIN_graphs'!M33 | AE33: ='[5]FED STEER MARGIN_graphs'!N33 -> 316.63935 | AF33: ='[5]FED STEER MARGIN_graphs'!O33 -> 115.44809
A34: ='[5]FED STEER MARGIN_graphs'!A34 -> 46234 | B34: 31 | D34: 174.72758 | E34: 187.8834 | F34: 63.011747 | G34: -912.60287 | H34: =+'Fed Steer Margin'!F269 -> -15.55892 | I34: =+'Fed Steer Margin'!F322 -> 192.08554 | J34: =+'Fed Steer Margin'!F374 -> 81.771936 | K34: =+'Fed Steer Margin'!F426 -> 8.6289828 | L34: =+'Fed Steer Margin'!F478 -> 35.421547 | M34: =+'Fed Steer Margin'!F530 -> -111.74024 | N34: =+'Fed Steer Margin'!F582 -> 120.8704 | O34: =+'Fed Steer Margin'!F635 -> -151.7272 | P34: =+'Fed Steer Margin'!$F687 -> -249.59223 | Q34: =+'Fed Steer Margin'!$F739 -> -52.026312 | R34: =+'Fed Steer Margin'!$F791 -> 566.60174 | S34: =+'Fed Steer Margin'!$F843 -> 212.51458 | T34: =+'Fed Steer Margin'!$F895 -> -258.97119 | U34: =+'Fed Steer Margin'!$F948 -> 103.92652 | V34: =+'Fed Steer Margin'!$F1000 -> -73.151951 | W34: =+'Fed Steer Margin'!F1052 -> -133.30322 | X34: =+'Fed Steer Margin'!F1104 -> -86.146574 | Y34: =+'Fed Steer Margin'!F1157 -> -111.94724 | Z34: =+'Fed Steer Margin'!F1209 -> -84.406176 | AA34: 478.08916 | AB34: 384.60714 | AC34: 695.70954 | AD34: ='[5]FED STEER MARGIN_graphs'!M34 | AE34: ='[5]FED STEER MARGIN_graphs'!N34 -> 272.41048 | AF34: ='[5]FED STEER MARGIN_graphs'!O34 -> 91.440601
A35: ='[5]FED STEER MARGIN_graphs'!A35 -> 46241 | B35: 32 | D35: 180.70454 | E35: 167.87336 | F35: 163.72812 | G35: -898.11109 | H35: =+'Fed Steer Margin'!F270 -> 45.83 | I35: =+'Fed Steer Margin'!F323 -> 117.71552 | J35: =+'Fed Steer Margin'!F375 -> 105.97651 | K35: =+'Fed Steer Margin'!F427 -> -38.21241 | L35: =+'Fed Steer Margin'!F479 -> 24.067098 | M35: =+'Fed Steer Margin'!F531 -> -168.59388 | N35: =+'Fed Steer Margin'!F583 -> 97.630226 | O35: =+'Fed Steer Margin'!F636 -> -160.5101 | P35: =+'Fed Steer Margin'!$F688 -> -367.69424 | Q35: =+'Fed Steer Margin'!$F740 -> -77.237708 | R35: =+'Fed Steer Margin'!$F792 -> 514.17612 | S35: =+'Fed Steer Margin'!$F844 -> 249.89459 | T35: =+'Fed Steer Margin'!$F896 -> -222.79777 | U35: =+'Fed Steer Margin'!$F949 -> 98.287433 | V35: =+'Fed Steer Margin'!$F1001 -> -186.81232 | W35: =+'Fed Steer Margin'!F1053 -> -150.8793 | X35: =+'Fed Steer Margin'!F1105 -> -94.299459 | Y35: =+'Fed Steer Margin'!F1158 -> -148.61405 | Z35: =+'Fed Steer Margin'!F1210 -> -52.839472 | AA35: 384.25281 | AB35: 423.46804 | AC35: 822.78712 | AD35: ='[5]FED STEER MARGIN_graphs'!M35 | AE35: ='[5]FED STEER MARGIN_graphs'!N35 -> 285.81089 | AF35: ='[5]FED STEER MARGIN_graphs'!O35 -> 87.255303
A36: ='[5]FED STEER MARGIN_graphs'!A36 -> 46248 | B36: 33 | D36: 149.12807 | E36: 198.11623 | F36: 30.858836 | G36: -552.70051 | H36: =+'Fed Steer Margin'!F271 -> -20.772512 | I36: =+'Fed Steer Margin'!F324 -> 141.00725 | J36: =+'Fed Steer Margin'!F376 -> 152.68856 | K36: =+'Fed Steer Margin'!F428 -> -27.659928 | L36: =+'Fed Steer Margin'!F480 -> 141.14284 | M36: =+'Fed Steer Margin'!F532 -> -186.90838 | N36: =+'Fed Steer Margin'!F584 -> 85.323333 | O36: =+'Fed Steer Margin'!F637 -> -149.76466 | P36: =+'Fed Steer Margin'!$F689 -> -257.41391 | Q36: =+'Fed Steer Margin'!$F741 -> 66.37682 | R36: =+'Fed Steer Margin'!$F793 -> 434.80003 | S36: =+'Fed Steer Margin'!$F845 -> 287.88228 | T36: =+'Fed Steer Margin'!$F897 -> -149.68001 | U36: =+'Fed Steer Margin'!$F950 -> 21.767274 | V36: =+'Fed Steer Margin'!$F1002 -> -147.45049 | W36: =+'Fed Steer Margin'!F1054 -> -109.35488 | X36: =+'Fed Steer Margin'!F1106 -> -26.195518 | Y36: =+'Fed Steer Margin'!F1159 -> -169.08022 | Z36: =+'Fed Steer Margin'!F1211 -> -33.053839 | AA36: 301.42498 | AB36: 345.59905 | AC36: 830.29822 | AD36: ='[5]FED STEER MARGIN_graphs'!M36 | AE36: ='[5]FED STEER MARGIN_graphs'!N36 -> 255.03764 | AF36: ='[5]FED STEER MARGIN_graphs'!O36 -> 86.427457
A37: ='[5]FED STEER MARGIN_graphs'!A37 -> 46255 | B37: 34 | D37: 164.63923 | E37: 150.60359 | F37: 75.128271 | G37: -581.96707 | H37: =+'Fed Steer Margin'!F272 -> -65.364452 | I37: =+'Fed Steer Margin'!F325 -> 110.54418 | J37: =+'Fed Steer Margin'!F377 -> 139.94796 | K37: =+'Fed Steer Margin'!F429 -> -27.321365 | L37: =+'Fed Steer Margin'!F481 -> 64.628247 | M37: =+'Fed Steer Margin'!F533 -> -170.89115 | N37: =+'Fed Steer Margin'!F585 -> 132.9957 | O37: =+'Fed Steer Margin'!F638 -> -190.73412 | P37: =+'Fed Steer Margin'!$F690 -> -221.93578 | Q37: =+'Fed Steer Margin'!$F742 -> 55.31812 | R37: =+'Fed Steer Margin'!$F794 -> 457.43133 | S37: =+'Fed Steer Margin'!$F846 -> 191.73148 | T37: =+'Fed Steer Margin'!$F898 -> -283.62688 | U37: =+'Fed Steer Margin'!$F951 -> 36.822305 | V37: =+'Fed Steer Margin'!$F1003 -> -227.37149 | W37: =+'Fed Steer Margin'!F1055 -> -105.2171 | X37: =+'Fed Steer Margin'!F1107 -> 51.928431 | Y37: =+'Fed Steer Margin'!F1160 -> -105.86818 | Z37: =+'Fed Steer Margin'!F1212 -> -93.133619 | AA37: 363.39428 | AB37: 176.68018 | AC37: 930.31604 | AD37: ='[5]FED STEER MARGIN_graphs'!M37 | AE37: ='[5]FED STEER MARGIN_graphs'!N37 -> 254.27774 | AF37: ='[5]FED STEER MARGIN_graphs'!O37 -> 74.392397
A38: ='[5]FED STEER MARGIN_graphs'!A38 -> 46262 | B38: 35 | D38: 170.53959 | E38: 150.98699 | F38: -30.302651 | G38: -710.80641 | H38: =+'Fed Steer Margin'!F273 -> -70.091283 | I38: =+'Fed Steer Margin'!F326 -> 155.64158 | J38: =+'Fed Steer Margin'!F378 -> 84.720578 | K38: =+'Fed Steer Margin'!F430 -> 3.0343176 | L38: =+'Fed Steer Margin'!F482 -> 45.564286 | M38: =+'Fed Steer Margin'!F534 -> -167.66897 | N38: =+'Fed Steer Margin'!F586 -> 90.100093 | O38: =+'Fed Steer Margin'!F639 -> -165.64386 | P38: =+'Fed Steer Margin'!$F691 -> -238.89596 | Q38: =+'Fed Steer Margin'!$F743 -> 0.44710602 | R38: =+'Fed Steer Margin'!$F795 -> 372.81743 | S38: =+'Fed Steer Margin'!$F847 -> 317.26973 | T38: =+'Fed Steer Margin'!$F899 -> -282.40107 | U38: =+'Fed Steer Margin'!$F952 -> -75.977745 | V38: =+'Fed Steer Margin'!$F1004 -> -169.25235 | W38: =+'Fed Steer Margin'!F1056 -> -62.50987 | X38: =+'Fed Steer Margin'!F1108 -> 36.507809 | Y38: =+'Fed Steer Margin'!F1161 -> 4.9960556 | Z38: =+'Fed Steer Margin'!F1213 -> 16.196461 | AA38: 433.40788 | AB38: 242.59347 | AC38: 974.41382 | AD38: ='[5]FED STEER MARGIN_graphs'!M38 | AE38: ='[5]FED STEER MARGIN_graphs'!N38 -> 334.32154 | AF38: ='[5]FED STEER MARGIN_graphs'!O38 -> 111.79745
A39: ='[5]FED STEER MARGIN_graphs'!A39 -> 46269 | B39: 36 | D39: 186.57347 | E39: 104.61636 | F39: 19.219814 | G39: -548.64545 | H39: =+'Fed Steer Margin'!F274 -> -17.599499 | I39: =+'Fed Steer Margin'!F327 -> 219.88001 | J39: =+'Fed Steer Margin'!F379 -> 121.91086 | K39: =+'Fed Steer Margin'!F431 -> 11.012232 | L39: =+'Fed Steer Margin'!F483 -> 30.070436 | M39: =+'Fed Steer Margin'!F535 -> -162.05048 | N39: =+'Fed Steer Margin'!F587 -> 109.55723 | O39: =+'Fed Steer Margin'!F640 -> -146.52187 | P39: =+'Fed Steer Margin'!$F692 -> -218.12308 | Q39: =+'Fed Steer Margin'!$F744 -> -72.450682 | R39: =+'Fed Steer Margin'!$F796 -> 264.75082 | S39: =+'Fed Steer Margin'!$F848 -> 234.82662 | T39: =+'Fed Steer Margin'!$F900 -> -317.71624 | U39: =+'Fed Steer Margin'!$F953 -> -126.75225 | V39: =+'Fed Steer Margin'!$F1005 -> -175.38612 | W39: =+'Fed Steer Margin'!F1057 -> -46.229197 | X39: =+'Fed Steer Margin'!F1109 -> 30.78474 | Y39: =+'Fed Steer Margin'!F1162 -> 70.155669 | Z39: =+'Fed Steer Margin'!F1214 -> 47.699234 | AA39: 250.03948 | AB39: 88.952479 | AC39: 1128.0158 | AD39: ='[5]FED STEER MARGIN_graphs'!M39 | AE39: ='[5]FED STEER MARGIN_graphs'!N39 -> 316.97253 | AF39: ='[5]FED STEER MARGIN_graphs'!O39 -> 94.956361
A40: ='[5]FED STEER MARGIN_graphs'!A40 -> 46276 | B40: 37 | D40: 141.17005 | E40: 118.50118 | F40: 19.159149 | G40: -222.41731 | H40: =+'Fed Steer Margin'!F275 -> -16.999912 | I40: =+'Fed Steer Margin'!F328 -> 274.48042 | J40: =+'Fed Steer Margin'!F380 -> 173.39147 | K40: =+'Fed Steer Margin'!F432 -> -68.845715 | L40: =+'Fed Steer Margin'!F484 -> 46.614087 | M40: =+'Fed Steer Margin'!F536 -> -242.31247 | N40: =+'Fed Steer Margin'!F588 -> 112.77109 | O40: =+'Fed Steer Margin'!F641 -> -140.87441 | P40: =+'Fed Steer Margin'!$F693 -> -242.94384 | Q40: =+'Fed Steer Margin'!$F745 -> -32.628986 | R40: =+'Fed Steer Margin'!$F797 -> 280.95201 | S40: =+'Fed Steer Margin'!$F849 -> 151.72306 | T40: =+'Fed Steer Margin'!$F901 -> -366.45609 | U40: =+'Fed Steer Margin'!$F954 -> -165.80477 | V40: =+'Fed Steer Margin'!$F1006 -> -156.30268 | W40: =+'Fed Steer Margin'!F1058 -> -158.76893 | X40: =+'Fed Steer Margin'!F1110 -> 22.022526 | Y40: =+'Fed Steer Margin'!F1163 -> 30.695857 | Z40: =+'Fed Steer Margin'!F1215 -> 47.856128 | AA40: 286.84919 | AB40: 254.48822 | AC40: 1109.3743 | AD40: ='[5]FED STEER MARGIN_graphs'!M40 | AE40: ='[5]FED STEER MARGIN_graphs'!N40 -> 345.85274 | AF40: ='[5]FED STEER MARGIN_graphs'!O40 -> 90.395375
... A54: ='[5]FED STEER MARGIN_graphs'!A54 -> 46374 | B54: 51 | D54: 196.22528 | E54: -40.342353 | F54: 220.52801 | G54: 40.779361 | H54: =+'Fed Steer Margin'!F289 -> 38.171857 | I54: =+'Fed Steer Margin'!F342 -> 391.48327 | J54: =+'Fed Steer Margin'!F394 -> -6.8858129 | K54: =+'Fed Steer Margin'!F446 -> -181.86411 | L54: =+'Fed Steer Margin'!F498 -> 63.48604 | M54: =+'Fed Steer Margin'!F550 -> -158.28662 | N54: =+'Fed Steer Margin'!F602 -> 63.863396 | O54: =+'Fed Steer Margin'!F655 -> 0.91989959 | P54: =+'Fed Steer Margin'!$F707 -> -291.16115 | Q54: =+'Fed Steer Margin'!$F759 -> 70.307279 | R54: =+'Fed Steer Margin'!$F811 -> 393.9817 | S54: =+'Fed Steer Margin'!$F863 -> -382.04725 | T54: =+'Fed Steer Margin'!$F915 -> -117.84939 | U54: =+'Fed Steer Margin'!$F968 -> -9.57343 | V54: =+'Fed Steer Margin'!$F1020 -> -38.067368 | W54: =+'Fed Steer Margin'!F1072 -> -58.837799 | X54: =+'Fed Steer Margin'!F1124 -> -421.90229 | Y54: =+'Fed Steer Margin'!F1177 -> 26.73818 | Z54: =+'Fed Steer Margin'!F1229 -> 195.51478 | AA54: -114.58107 | AB54: 483.70595 | AC54: 179.00571 | AD54: ='[5]FED STEER MARGIN_graphs'!M54 | AE54: ='[5]FED STEER MARGIN_graphs'!N54 -> 154.07671 | AF54: ='[5]FED STEER MARGIN_graphs'!O54 -> 12.415328
A55: ='[5]FED STEER MARGIN_graphs'!A55 -> 46381 | B55: 52 | D55: 213.61653 | E55: 4.2466308 | F55: 136.79057 | G55: 171.64219 | H55: =+'Fed Steer Margin'!F290 -> 163.36154 | I55: =+'Fed Steer Margin'!F343 -> 348.7645 | J55: =+'Fed Steer Margin'!F395 -> 13.161548 | K55: =+'Fed Steer Margin'!F447 -> -246.2833 | L55: =+'Fed Steer Margin'!F499 -> 11.946043 | M55: =+'Fed Steer Margin'!F551 -> -152.38233 | N55: =+'Fed Steer Margin'!F603 -> 124.13949 | O55: =+'Fed Steer Margin'!F656 -> 78.426009 | P55: =+'Fed Steer Margin'!$F708 -> -185.20119 | Q55: =+'Fed Steer Margin'!$F760 -> 140.01302 | R55: =+'Fed Steer Margin'!$F812 -> 134.0098 | S55: =+'Fed Steer Margin'!$F864 -> -111.25231 | T55: =+'Fed Steer Margin'!$F916 -> -95.304087 | U55: =+'Fed Steer Margin'!$F969 -> 5.3850705 | V55: =+'Fed Steer Margin'!$F1021 -> -107.57943 | W55: =+'Fed Steer Margin'!F1073 -> 6.516319 | X55: =+'Fed Steer Margin'!F1125 -> -352.82659 | Y55: =+'Fed Steer Margin'!F1178 -> 210.36719 | Z55: =+'Fed Steer Margin'!F1230 -> 356.79469 | AA55: -81.469344 | AB55: 532.58368 | AC55: #N/A | AD55: ='[5]FED STEER MARGIN_graphs'!M55 | AE55: ='[5]FED STEER MARGIN_graphs'!N55 -> 254.56905 | AF55: ='[5]FED STEER MARGIN_graphs'!O55 -> 52.71861
D56: 312.86224

Sheet FedCat_Steer graph

Sheet FedSt_Basis graph

Sheet Steers(500-599lbs) LW graph

Sheet Graph_FeederSteer(500-599)Basis
B1: Feeder Steer (500-599) Basis | V1: Feeder Steer (500-599) Basis ($/cwt live weight
R2: Last year | S2: This Year | T2: 5-Year Ave (2020-24) | U2: 10-Year Ave (2015-24)
A3: Week No. | B3: Week No. | C3: 2010 | D3: 2011 | E3: 2012 | F3: 2013 | G3: 2014 | H3: 2015 | I3: 2016 | J3: 2017 | K3: 2018 | L3: 2019 | M3: 2020 | N3: 2021 | O3: 2022 | P3: 2023 | Q3: 2024 | R3: 2025 | S3: 2026 | T3: avg 2020-24 | U3: Avg 2015-24
A4: ='[5]FED STEER MARGIN_graphs'!A4 -> 46024 | B4: 1 | C4: =+[5]CttlePrices_Basis!$O265 -> 4.001867 | D4: =+[5]CttlePrices_Basis!$O317 -> 12.666656 | E4: =+[5]CttlePrices_Basis!$O369 -> -30.970375 | F4: =+[5]CttlePrices_Basis!$O421 -> 2.027564 | G4: =+[5]CttlePrices_Basis!$O473 -> -34.427692 | H4: =+[5]CttlePrices_Basis!$O525 -> 24.2118 | I4: =+[5]CttlePrices_Basis!$O577 -> 7.8753963 | J4: =+[5]CttlePrices_Basis!$O629 -> 28.94634 | K4: =+[5]CttlePrices_Basis!$O681 -> 47.881258 | L4: =+[5]CttlePrices_Basis!O733 -> 0.900154 | M4: =+[5]CttlePrices_Basis!O785 -> 26.831866 | N4: =+[5]CttlePrices_Basis!$O837 -> 21.495663 | O4: =+[5]CttlePrices_Basis!$O889 -> 8.174494 | P4: =+[5]CttlePrices_Basis!$O941 -> 14.05044 | Q4: =+[5]CttlePrices_Basis!$O993 -> 12.766995 | R4: =+[5]CttlePrices_Basis!$O1045 -> 55.253784 | S4: =+[5]CttlePrices_Basis!$O1097 -> #N/A | T4: =IFERROR(AVERAGE(O4:S4),"-") -> - | U4: =AVERAGE(J4:S4) -> #N/A
A5: =+A4+7 -> 46031 | B5: 2 | C5: =+[5]CttlePrices_Basis!$O266 -> 6.4394172 | D5: =+[5]CttlePrices_Basis!$O318 -> 10.195232 | E5: =+[5]CttlePrices_Basis!$O370 -> -21.933765 | F5: =+[5]CttlePrices_Basis!$O422 -> 10.864242 | G5: =+[5]CttlePrices_Basis!$O474 -> -8.751469 | H5: =+[5]CttlePrices_Basis!$O526 -> 19.939139 | I5: =+[5]CttlePrices_Basis!$O578 -> 31.560229 | J5: =+[5]CttlePrices_Basis!$O630 -> 29.156121 | K5: =+[5]CttlePrices_Basis!$O682 -> 39.65598 | L5: =+[5]CttlePrices_Basis!O734 -> 16.64587 | M5: =+[5]CttlePrices_Basis!O786 -> 26.689701 | N5: =+[5]CttlePrices_Basis!$O838 -> 39.349824 | O5: =+[5]CttlePrices_Basis!$O890 -> 10.64819 | P5: =+[5]CttlePrices_Basis!$O942 -> 15.280625 | Q5: =+[5]CttlePrices_Basis!$O994 -> 10.8897 | R5: =+[5]CttlePrices_Basis!$O1046 -> 56.07564 | S5: =+[5]CttlePrices_Basis!$O1098 -> 123.2111 | T5: =AVERAGE(L5:P5) -> 21.722842 | U5: =AVERAGE(G5:P5) -> 22.017421
A6: =+A5+7 -> 46038 | B6: 3 | C6: =+[5]CttlePrices_Basis!$O267 -> 7.056264 | D6: =+[5]CttlePrices_Basis!$O319 -> 15.034234 | E6: =+[5]CttlePrices_Basis!$O371 -> -21.24236 | F6: =+[5]CttlePrices_Basis!$O423 -> 12.093287 | G6: =+[5]CttlePrices_Basis!$O475 -> 2.2641168 | H6: =+[5]CttlePrices_Basis!$O527 -> 41.627862 | I6: =+[5]CttlePrices_Basis!$O579 -> 47.918253 | J6: =+[5]CttlePrices_Basis!$O631 -> 14.651064 | K6: =+[5]CttlePrices_Basis!$O683 -> 32.14106 | L6: =+[5]CttlePrices_Basis!O735 -> 19.813104 | M6: =+[5]CttlePrices_Basis!O787 -> 34.5031 | N6: =+[5]CttlePrices_Basis!$O839 -> 28.449862 | O6: =+[5]CttlePrices_Basis!$O891 -> 16.486784 | P6: =+[5]CttlePrices_Basis!$O943 -> 37.968624 | Q6: =+[5]CttlePrices_Basis!$O995 -> 32.00837 | R6: =+[5]CttlePrices_Basis!$O1047 -> 82.967045 | S6: =+[5]CttlePrices_Basis!$O1099 -> 142.89482 | T6: =AVERAGE(L6:P6) -> 27.444295 | U6: =AVERAGE(G6:P6) -> 27.582383
A7: =+A6+7 -> 46045 | B7: 4 | C7: =+[5]CttlePrices_Basis!$O268 -> 3.8349188 | D7: =+[5]CttlePrices_Basis!$O320 -> 16.634782 | E7: =+[5]CttlePrices_Basis!$O372 -> -14.995232 | F7: =+[5]CttlePrices_Basis!$O424 -> 17.084278 | G7: =+[5]CttlePrices_Basis!$O476 -> 0.5956725 | H7: =+[5]CttlePrices_Basis!$O528 -> 37.366356 | I7: =+[5]CttlePrices_Basis!$O580 -> 28.663787 | J7: =+[5]CttlePrices_Basis!$O632 -> 17.66952 | K7: =+[5]CttlePrices_Basis!$O684 -> 38.09875 | L7: =+[5]CttlePrices_Basis!O736 -> 25.393804 | M7: =+[5]CttlePrices_Basis!O788 -> 41.332313 | N7: =+[5]CttlePrices_Basis!$O840 -> 39.51449 | O7: =+[5]CttlePrices_Basis!$O892 -> 18.88048 | P7: =+[5]CttlePrices_Basis!$O944 -> 20.829859 | Q7: =+[5]CttlePrices_Basis!$O996 -> 23.97923 | R7: =+[5]CttlePrices_Basis!$O1048 -> 57.211046 | S7: =+[5]CttlePrices_Basis!$O1100 -> 125.6958 | T7: =AVERAGE(L7:P7) -> 29.190189 | U7: =AVERAGE(G7:P7) -> 26.834503
A8: =+A7+7 -> 46052 | B8: 5 | C8: =+[5]CttlePrices_Basis!$O269 -> 6.9358208 | D8: =+[5]CttlePrices_Basis!$O321 -> 19.9675 | E8: =+[5]CttlePrices_Basis!$O373 -> -12.043665 | F8: =+[5]CttlePrices_Basis!$O425 -> 17.63176 | G8: =+[5]CttlePrices_Basis!$O477 -> 0.9403344 | H8: =+[5]CttlePrices_Basis!$O529 -> 22.598792 | I8: =+[5]CttlePrices_Basis!$O581 -> 38.393966 | J8: =+[5]CttlePrices_Basis!$O633 -> 23.04955 | K8: =+[5]CttlePrices_Basis!$O685 -> 23.470608 | L8: =+[5]CttlePrices_Basis!O737 -> 14.53584 | M8: =+[5]CttlePrices_Basis!O789 -> 36.587665 | N8: =+[5]CttlePrices_Basis!$O841 -> 38.156936 | O8: =+[5]CttlePrices_Basis!$O893 -> -6.583358 | P8: =+[5]CttlePrices_Basis!$O945 -> 33.68071 | Q8: =+[5]CttlePrices_Basis!$O997 -> 37.04504 | R8: =+[5]CttlePrices_Basis!$O1049 -> 73.392376 | S8: =+[5]CttlePrices_Basis!$O1101 -> 130.6521 | T8: =AVERAGE(L8:P8) -> 23.275559 | U8: =AVERAGE(G8:P8) -> 22.483104
A9: =+A8+7 -> 46059 | B9: 6 | C9: =+[5]CttlePrices_Basis!$O270 -> 9.531535 | D9: =+[5]CttlePrices_Basis!$O322 -> 23.015721 | E9: =+[5]CttlePrices_Basis!$O374 -> -9.0546196 | F9: =+[5]CttlePrices_Basis!$O426 -> 24.0795 | G9: =+[5]CttlePrices_Basis!$O478 -> -0.790496 | H9: =+[5]CttlePrices_Basis!$O530 -> 29.991819 | I9: =+[5]CttlePrices_Basis!$O582 -> 39.775116 | J9: =+[5]CttlePrices_Basis!$O634 -> 22.598456 | K9: =+[5]CttlePrices_Basis!$O686 -> 34.50692 | L9: =+[5]CttlePrices_Basis!O738 -> 11.805466 | M9: =+[5]CttlePrices_Basis!O790 -> 38.285936 | N9: =+[5]CttlePrices_Basis!$O842 -> 53.489088 | O9: =+[5]CttlePrices_Basis!$O894 -> 6.9382 | P9: =+[5]CttlePrices_Basis!$O946 -> 44.536 | Q9: =+[5]CttlePrices_Basis!$O998 -> 60.708535 | R9: =+[5]CttlePrices_Basis!$O1050 -> 85.1726 | S9: =+[5]CttlePrices_Basis!$O1102 -> 111.74594 | T9: =AVERAGE(L9:P9) -> 31.010938 | U9: =AVERAGE(G9:P9) -> 28.113651
A10: =+A9+7 -> 46066 | B10: 7 | C10: =+[5]CttlePrices_Basis!$O271 -> 8.283555 | D10: =+[5]CttlePrices_Basis!$O323 -> 23.181386 | E10: =+[5]CttlePrices_Basis!$O375 -> -10.130686 | F10: =+[5]CttlePrices_Basis!$O427 -> 26.880177 | G10: =+[5]CttlePrices_Basis!$O479 -> 4.4809462 | H10: =+[5]CttlePrices_Basis!$O531 -> 31.057806 | I10: =+[5]CttlePrices_Basis!$O583 -> 48.05274 | J10: =+[5]CttlePrices_Basis!$O635 -> 27.331752 | K10: =+[5]CttlePrices_Basis!$O687 -> 33.35752 | L10: =+[5]CttlePrices_Basis!O739 -> 23.596552 | M10: =+[5]CttlePrices_Basis!O791 -> 42.97567 | N10: =+[5]CttlePrices_Basis!$O843 -> 51.182356 | O10: =+[5]CttlePrices_Basis!$O895 -> 9.31459 | P10: =+[5]CttlePrices_Basis!$O947 -> 53.894864 | Q10: =+[5]CttlePrices_Basis!$O999 -> 59.565448 | R10: =+[5]CttlePrices_Basis!$O1051 -> 93.204655 | S10: =+[5]CttlePrices_Basis!$O1103 -> 122.23246 | T10: =AVERAGE(L10:P10) -> 36.192806 | U10: =AVERAGE(G10:P10) -> 32.52448
A11: =+A10+7 -> 46073 | B11: 8 | C11: =+[5]CttlePrices_Basis!$O272 -> 10.951384 | D11: =+[5]CttlePrices_Basis!$O324 -> 21.387378 | E11: =+[5]CttlePrices_Basis!$O376 -> -5.966194 | F11: =+[5]CttlePrices_Basis!$O428 -> 28.593437 | G11: =+[5]CttlePrices_Basis!$O480 -> -3.51613 | H11: =+[5]CttlePrices_Basis!$O532 -> 32.632918 | I11: =+[5]CttlePrices_Basis!$O584 -> 38.212377 | J11: =+[5]CttlePrices_Basis!$O636 -> 29.394333 | K11: =+[5]CttlePrices_Basis!$O688 -> 41.53585 | L11: =+[5]CttlePrices_Basis!O740 -> 9.2016467 | M11: =+[5]CttlePrices_Basis!O792 -> 38.70328 | N11: =+[5]CttlePrices_Basis!$O844 -> 50.917543 | O11: =+[5]CttlePrices_Basis!$O896 -> 10.075625 | P11: =+[5]CttlePrices_Basis!$O948 -> 62.135893 | Q11: =+[5]CttlePrices_Basis!$O1000 -> 43.375043 | R11: =+[5]CttlePrices_Basis!$O1052 -> 51.590655 | S11: =+[5]CttlePrices_Basis!$O1104 -> 101.37897 | T11: =AVERAGE(L11:P11) -> 34.206798 | U11: =AVERAGE(G11:P11) -> 30.929334
A12: =+A11+7 -> 46080 | B12: 9 | C12: =+[5]CttlePrices_Basis!$O273 -> 8.690324 | D12: =+[5]CttlePrices_Basis!$O325 -> 16.708477 | E12: =+[5]CttlePrices_Basis!$O377 -> -10.54878 | F12: =+[5]CttlePrices_Basis!$O429 -> 20.775685 | G12: =+[5]CttlePrices_Basis!$O481 -> -11.467704 | H12: =+[5]CttlePrices_Basis!$O533 -> 24.89936 | I12: =+[5]CttlePrices_Basis!$O585 -> 34.97804 | J12: =+[5]CttlePrices_Basis!$O637 -> 23.271418 | K12: =+[5]CttlePrices_Basis!$O689 -> 40.89805 | L12: =+[5]CttlePrices_Basis!O741 -> 19.882728 | M12: =+[5]CttlePrices_Basis!O793 -> 51.762132 | N12: =+[5]CttlePrices_Basis!$O845 -> 44.52921 | O12: =+[5]CttlePrices_Basis!$O897 -> 12.042215 | P12: =+[5]CttlePrices_Basis!$O949 -> 44.306 | Q12: =+[5]CttlePrices_Basis!$O1001 -> 49.0652 | R12: =+[5]CttlePrices_Basis!$O1053 -> 45.1569 | S12: =+[5]CttlePrices_Basis!$O1105 -> 126.85 | T12: =AVERAGE(L12:P12) -> 34.504457 | U12: =AVERAGE(G12:P12) -> 28.510145
A13: =+A12+7 -> 46087 | B13: 10 | C13: =+[5]CttlePrices_Basis!$O274 -> 12.07208 | D13: =+[5]CttlePrices_Basis!$O326 -> 18.248138 | E13: =+[5]CttlePrices_Basis!$O378 -> -11.88192 | F13: =+[5]CttlePrices_Basis!$O430 -> 27.634826 | G13: =+[5]CttlePrices_Basis!$O482 -> 1.251424 | H13: =+[5]CttlePrices_Basis!$O534 -> 27.03073 | I13: =+[5]CttlePrices_Basis!$O586 -> 43.315837 | J13: =+[5]CttlePrices_Basis!$O638 -> 25.058919 | K13: =+[5]CttlePrices_Basis!$O690 -> 43.290126 | L13: =+[5]CttlePrices_Basis!O742 -> -0.9484336 | M13: =+[5]CttlePrices_Basis!O794 -> 42.337217 | N13: =+[5]CttlePrices_Basis!$O846 -> 48.293257 | O13: =+[5]CttlePrices_Basis!$O898 -> 14.06002 | P13: =+[5]CttlePrices_Basis!$O950 -> 58.110402 | Q13: =+[5]CttlePrices_Basis!$O1002 -> 16.60517 | R13: =+[5]CttlePrices_Basis!$O1054 -> 20.9266 | S13: =+[5]CttlePrices_Basis!$O1106 -> 126.9913 | T13: =AVERAGE(L13:P13) -> 32.370493 | U13: =AVERAGE(G13:P13) -> 30.17995
A14: =+A13+7 -> 46094 | B14: 11 | C14: =+[5]CttlePrices_Basis!$O275 -> 7.386592 | D14: =+[5]CttlePrices_Basis!$O327 -> 24.06584 | E14: =+[5]CttlePrices_Basis!$O379 -> -6.939428 | F14: =+[5]CttlePrices_Basis!$O431 -> 25.510988 | G14: =+[5]CttlePrices_Basis!$O483 -> -3.5475676 | H14: =+[5]CttlePrices_Basis!$O535 -> 33.464371 | I14: =+[5]CttlePrices_Basis!$O587 -> 26.296838 | J14: =+[5]CttlePrices_Basis!$O639 -> 26.108615 | K14: =+[5]CttlePrices_Basis!$O691 -> 35.448491 | L14: =+[5]CttlePrices_Basis!O743 -> 0.5121328 | M14: =+[5]CttlePrices_Basis!O795 -> 64.250176 | N14: =+[5]CttlePrices_Basis!$O847 -> 54.610854 | O14: =+[5]CttlePrices_Basis!$O899 -> 10.12253 | P14: =+[5]CttlePrices_Basis!$O951 -> 73.991075 | Q14: =+[5]CttlePrices_Basis!$O1003 -> 78.948548 | R14: =+[5]CttlePrices_Basis!$O1055 -> 91.07152 | S14: =+[5]CttlePrices_Basis!$O1107 -> 139.03111 | T14: =AVERAGE(L14:P14) -> 40.697354 | U14: =AVERAGE(G14:P14) -> 32.125752
A15: =+A14+7 -> 46101 | B15: 12 | C15: =+[5]CttlePrices_Basis!$O276 -> 1.778016 | D15: =+[5]CttlePrices_Basis!$O328 -> 13.920818 | E15: =+[5]CttlePrices_Basis!$O380 -> -1.593626 | F15: =+[5]CttlePrices_Basis!$O432 -> 4.507775 | G15: =+[5]CttlePrices_Basis!$O484 -> -1.1393048 | H15: =+[5]CttlePrices_Basis!$O536 -> 30.623344 | I15: =+[5]CttlePrices_Basis!$O588 -> 23.61028 | J15: =+[5]CttlePrices_Basis!$O640 -> 18.84052 | K15: =+[5]CttlePrices_Basis!$O692 -> 41.749452 | L15: =+[5]CttlePrices_Basis!O744 -> -8.405304 | M15: =+[5]CttlePrices_Basis!O796 -> 28.245502 | N15: =+[5]CttlePrices_Basis!$O848 -> 30.345074 | O15: =+[5]CttlePrices_Basis!$O900 -> 24.230236 | P15: =+[5]CttlePrices_Basis!$O952 -> 41.352955 | Q15: =+[5]CttlePrices_Basis!$O1004 -> 33.7412 | R15: =+[5]CttlePrices_Basis!$O1056 -> 61.891564 | S15: =+[5]CttlePrices_Basis!$O1108 -> 155.83253 | T15: =AVERAGE(L15:P15) -> 23.153692 | U15: =AVERAGE(G15:P15) -> 22.945275
A16: =+A15+7 -> 46108 | B16: 13 | C16: =+[5]CttlePrices_Basis!$O277 -> 3.2437465 | D16: =+[5]CttlePrices_Basis!$O329 -> 7.74204 | E16: =+[5]CttlePrices_Basis!$O381 -> -5.7050976 | F16: =+[5]CttlePrices_Basis!$O433 -> 15.155008 | G16: =+[5]CttlePrices_Basis!$O485 -> 1.171481 | H16: =+[5]CttlePrices_Basis!$O537 -> 26.823429 | I16: =+[5]CttlePrices_Basis!$O589 -> 25.127937 | J16: =+[5]CttlePrices_Basis!$O641 -> 29.687584 | K16: =+[5]CttlePrices_Basis!$O693 -> 29.951586 | L16: =+[5]CttlePrices_Basis!O745 -> 4.1228544 | M16: =+[5]CttlePrices_Basis!O797 -> 43.598481 | N16: =+[5]CttlePrices_Basis!$O849 -> 11.435427 | O16: =+[5]CttlePrices_Basis!$O901 -> -16.137295 | P16: =+[5]CttlePrices_Basis!$O953 -> 11.051688 | Q16: =+[5]CttlePrices_Basis!$O1005 -> 46.774912 | R16: =+[5]CttlePrices_Basis!$O1057 -> 39.459127 | S16: =+[5]CttlePrices_Basis!$O1109 -> 140.86164 | T16: =AVERAGE(L16:P16) -> 10.814231 | U16: =AVERAGE(G16:P16) -> 16.683317
... A29: =+A28+7 -> 46199 | B29: 26 | C29: =+[5]CttlePrices_Basis!$O290 -> -6.5050218 | D29: =+[5]CttlePrices_Basis!$O342 -> 3.491098 | E29: =+[5]CttlePrices_Basis!$O394 -> -18.274918 | F29: =+[5]CttlePrices_Basis!$O446 -> 10.189566 | G29: =+[5]CttlePrices_Basis!$O498 -> 17.83612 | H29: =+[5]CttlePrices_Basis!$O550 -> 60.07708 | I29: =+[5]CttlePrices_Basis!$O602 -> 22.628439 | J29: =+[5]CttlePrices_Basis!$O654 -> 24.284061 | K29: =+[5]CttlePrices_Basis!$O706 -> 15.459815 | L29: =+[5]CttlePrices_Basis!O758 -> 10.807647 | M29: =+[5]CttlePrices_Basis!O810 -> 28.53704 | N29: =+[5]CttlePrices_Basis!$O862 -> 31.422925 | O29: =+[5]CttlePrices_Basis!$O914 -> 12.78064 | P29: =+[5]CttlePrices_Basis!$O966 -> -18.371428 | Q29: =+[5]CttlePrices_Basis!$O1018 -> 45.47399 | R29: =+[5]CttlePrices_Basis!$O1070 -> 114.08989 | S29: =+[5]CttlePrices_Basis!$O1122 -> #N/A | T29: =AVERAGE(L29:P29) -> 13.035365 | U29: =AVERAGE(G29:P29) -> 20.546234
A30: =+A29+7 -> 46206 | B30: 27 | C30: =+[5]CttlePrices_Basis!$O291 -> -3.997176 | D30: =+[5]CttlePrices_Basis!$O343 -> 6.406488 | E30: =+[5]CttlePrices_Basis!$O395 -> -10.138203 | F30: =+[5]CttlePrices_Basis!$O447 -> -0.514735 | G30: =+[5]CttlePrices_Basis!$O499 -> 28.475226 | H30: =+[5]CttlePrices_Basis!$O551 -> 34.637626 | I30: =+[5]CttlePrices_Basis!$O603 -> 18.371378 | J30: =+[5]CttlePrices_Basis!$O655 -> 18.918622 | K30: =+[5]CttlePrices_Basis!$O707 -> 26.744878 | L30: =+[5]CttlePrices_Basis!O759 -> 14.480074 | N30: =+[5]CttlePrices_Basis!$O863 -> 18.310097 | O30: =+[5]CttlePrices_Basis!$O915 -> 2.099325 | P30: =+[5]CttlePrices_Basis!$O967 -> 3.940294 | Q30: =+[5]CttlePrices_Basis!$O1019 -> 71.39572 | R30: =+[5]CttlePrices_Basis!$O1071 -> 133.319 | S30: =+[5]CttlePrices_Basis!$O1123 -> #N/A | T30: =AVERAGE(L30:P30) -> 9.7074474 | U30: =AVERAGE(G30:P30) -> 18.441947
A31: =+A30+7 -> 46213 | B31: 28 | C31: =+[5]CttlePrices_Basis!$O292 -> -2.068158 | D31: =+[5]CttlePrices_Basis!$O344 -> 10.897582 | E31: =+[5]CttlePrices_Basis!$O396 -> 3.1497 | F31: =+[5]CttlePrices_Basis!$O448 -> 12.470245 | G31: =+[5]CttlePrices_Basis!$O500 -> 32.632206 | H31: =+[5]CttlePrices_Basis!$O552 -> 33.887481 | I31: =+[5]CttlePrices_Basis!$O604 -> 10.281005 | J31: =+[5]CttlePrices_Basis!$O656 -> 14.930343 | K31: =+[5]CttlePrices_Basis!$O708 -> 6.965721 | L31: =+[5]CttlePrices_Basis!O760 -> 9.756592 | M31: =+[5]CttlePrices_Basis!O812 -> 41.819362 | N31: =+[5]CttlePrices_Basis!$O864 -> 7.21099 | O31: =+[5]CttlePrices_Basis!$O916 -> 10.044835 | P31: =+[5]CttlePrices_Basis!$O968 -> -6.210035 | Q31: =+[5]CttlePrices_Basis!$O1020 -> 69.73908 | R31: =+[5]CttlePrices_Basis!$O1072 -> 150.34521 | S31: =+[5]CttlePrices_Basis!$O1124 -> #N/A | T31: =AVERAGE(L31:P31) -> 12.524349 | U31: =AVERAGE(G31:P31) -> 16.13185
A32: =+A31+7 -> 46220 | B32: 29 | C32: =+[5]CttlePrices_Basis!$O293 -> -2.9179874 | D32: =+[5]CttlePrices_Basis!$O345 -> 5.375416 | E32: =+[5]CttlePrices_Basis!$O397 -> 3.534078 | F32: =+[5]CttlePrices_Basis!$O449 -> 16.505675 | G32: =+[5]CttlePrices_Basis!$O501 -> 28.810912 | H32: =+[5]CttlePrices_Basis!$O553 -> 17.834944 | I32: =+[5]CttlePrices_Basis!$O605 -> 35.064583 | J32: =+[5]CttlePrices_Basis!$O657 -> 29.91352 | K32: =+[5]CttlePrices_Basis!$O709 -> 15.839818 | L32: =+[5]CttlePrices_Basis!O761 -> 24.877129 | M32: =+[5]CttlePrices_Basis!O813 -> 33.490622 | N32: =+[5]CttlePrices_Basis!$O865 -> 6.829961 | O32: =+[5]CttlePrices_Basis!$O917 -> 7.6586 | P32: =+[5]CttlePrices_Basis!$O969 -> -6.726336 | Q32: =+[5]CttlePrices_Basis!$O1021 -> 88.27128 | R32: =+[5]CttlePrices_Basis!$O1073 -> 120.8612 | S32: =+[5]CttlePrices_Basis!$O1125 -> #N/A | T32: =AVERAGE(L32:P32) -> 13.225995 | U32: =AVERAGE(G32:P32) -> 19.359375
A33: =+A32+7 -> 46227 | B33: 30 | C33: =+[5]CttlePrices_Basis!$O294 -> 1.0253616 | D33: =+[5]CttlePrices_Basis!$O346 -> 2.893046 | E33: =+[5]CttlePrices_Basis!$O398 -> -4.63911 | F33: =+[5]CttlePrices_Basis!$O450 -> -3.287676 | G33: =+[5]CttlePrices_Basis!$O502 -> 27.269085 | H33: =+[5]CttlePrices_Basis!$O554 -> 43.290091 | I33: =+[5]CttlePrices_Basis!$O606 -> 25.563208 | J33: =+[5]CttlePrices_Basis!$O658 -> 32.49435 | K33: =+[5]CttlePrices_Basis!$O710 -> 10.022755 | L33: =+[5]CttlePrices_Basis!O762 -> 12.594998 | M33: =+[5]CttlePrices_Basis!O814 -> 21.651145 | N33: =+[5]CttlePrices_Basis!$O866 -> -2.19348 | O33: =+[5]CttlePrices_Basis!$O918 -> 6.345612 | P33: =+[5]CttlePrices_Basis!$O970 -> -8.38776 | Q33: =+[5]CttlePrices_Basis!$O1022 -> 58.50654 | R33: =+[5]CttlePrices_Basis!$O1074 -> 137.77471 | S33: =+[5]CttlePrices_Basis!$O1126 -> #N/A | T33: =AVERAGE(L33:P33) -> 6.002103 | U33: =AVERAGE(G33:P33) -> 16.865
